Workbook

Sheet Consolidado Gabi
A3: Colaboradores e prestadores de serviços - MBR | R3: 45352
A4: Item | B4: Funcionários e prestadores de serviço | C4: C. custo | D4: Tipo | E4: CBO | F4: Status | G4: Centro de custo | H4: admissão/contrato | I4: demissão/distrato | J4: Dt desligamento | K4: At/Ft | L4: Tempo | M4: Total | N4: Valor bruto | O4: Valor líquido | P4: Média m. líquida | Q4: Saldo à pagar | R4: B. horas | S4: Valor
B5: Adolfo Gabriel Pereira | C5: SANTOS | D5: CLT | E5: 514320 | F5: Ativo | H5: 45264 | L5: 3 | M5: =#REF! -> #REF! | N5: 2372.34 | O5: =#REF! -> #REF! | P5: =M5/L5 -> #REF! | R5: -14.24 | S5: =1849.81/220*R5 -> -119.73316
B6: Alan Deyvid de Siqueira | C6: PRAIA GRANDE | D6: CLT | E6: 514320 | F6: Ativo | H6: 45302 | L6: 2 | M6: =#REF! -> #REF! | N6: 2647.33 | O6: =#REF! -> #REF! | P6: =M6/L6 -> #REF! | R6: -0.03 | S6: =1849.81/220*R6 -> -0.25224682
B7: Andrea Aparecida de Oliveira Ferreira | C7: PESSOAL | D7: CLT | E7: 514320 | F7: Ativo | H7: 45260 | L7: 4 | M7: =#REF! -> #REF! | N7: 2089.81 | O7: =#REF! -> #REF! | P7: =M7/L7 -> #REF! | R7: 21.48 | S7: =R7*12.6 -> 270.648
B8: Ed Carlos dos Santos | C8: PRAIA GRANDE | D8: CLT | E8: 514320 | F8: Afastado | H8: 44972 | K8: 0 | L8: 13 | M8: =#REF! -> #REF! | N8: 77.08 | O8: 77.08 | P8: =M8/L8 -> #REF! | S8: =(R8*12.62) -> 0
B9: Gabriel Henrique Araujo da Cruz | C9: PRAIA GRANDE | D9: CLT | E9: 514320 | F9: Ativo | H9: 45376 | L9: =(J$36-H9)/30 -> -1.4 | M9: =#REF! -> #REF! | O9: =#REF! -> #REF! | P9: =M9/L9 -> #REF! | R9: -1.04 | S9: =1849.81/220*R9 -> -8.7445564
B10: Gustavo Francisco de Souza Almeida | C10: PRAIA GRANDE | D10: CLT | F10: Ativo | H10: 45018 | L10: =(J$36-H10)/30 -> 10.533333 | M10: =#REF! -> #REF! | N10: 2557.35 | O10: =#REF! -> #REF! | P10: =M10/L10 -> #REF! | R10: 0 | S10: =R10*12.6 -> 0
B11: Joel Maicon Cardoso de Oliveira | C11: PRAIA GRANDE | D11: CLT | E11: 514320 | F11: Ativo | H11: 45096 | L11: 9 | M11: =#REF! -> #REF! | N11: =SUM(#REF!) -> #REF! | O11: =#REF! -> #REF! | P11: =M11/L11 -> #REF! | R11: 9.44 | S11: =R11*12.6 -> 118.944
B12: Jhon Weslley Rodrigues da Silva Fernandes | C12: PRAIA GRANDE | D12: CLT | E12: 514320 | F12: Ativo | H12: 45376 | L12: =(J$36-H12)/30 -> -1.4 | M12: =#REF! -> #REF! | N12: =SUM(#REF!) -> #REF! | O12: =#REF! -> #REF! | P12: =M12/L12 -> #REF! | R12: 1.49 | S12: =R12*12.6 -> 18.774
B13: Leonardo de Souza Negreiros | C13: SANTOS | D13: CLT | E13: 514320 | F13: Ativo | H13: 45145 | L13: 7 | M13: =#REF! -> #REF! | N13: 3126.1 | O13: =#REF! -> #REF! | P13: =M13/L13 -> #REF! | R13: 4.4 | S13: =R13*12.6 -> 55.44
B14: Maximus Rhaziel Stahnke | C14: SANTOS | D14: CLT | E14: 514320 | F14: Ativo | H14: 45264 | L14: 3 | M14: =#REF! -> #REF! | N14: 2334.32 | O14: =#REF! -> #REF! | P14: =M14/L14 -> #REF! | R14: 3.54 | S14: =R14*12.6 -> 44.604
B15: Roberto Henrique dos Santos | C15: PRAIA GRANDE | D15: CLT | E15: 514320 | F15: Ativo | H15: 45264 | L15: 3 | M15: =#REF! -> #REF! | N15: 2337.35 | O15: =#REF! -> #REF! | P15: =M15/L15 -> #REF! | R15: -10.48 | S15: =1849.81/220*R15 -> -88.118222
B16: Robson Roque Bernardo | C16: SANTOS | D16: CLT | E16: 514320 | F16: Ativo | H16: 45264 | L16: 3 | M16: =#REF! -> #REF! | N16: 2331.57 | O16: =#REF! -> #REF! | P16: =M16/L16 -> #REF! | R16: -13.27 | S16: =1849.81/220*R16 -> -111.57718
B17: Victor Hugo do Nascimento Soares | C17: SANTOS | D17: CLT | E17: 514320 | F17: Ativo | H17: 45313 | L17: 2 | M17: =#REF! -> #REF! | N17: 2331.35 | O17: =#REF! -> #REF! | P17: =M17/L17 -> #REF! | R17: -0.16 | S17: =1849.81/220*R17 -> -1.3453164
B18: Abraao da Silva Costa | C18: SANTOS | D18: ME | F18: Ativo | H18: 45281 | L18: 3 | M18: =#REF! -> #REF! | N18: =#REF! -> #REF! | O18: =#REF! -> #REF! | P18: =M18/L18 -> #REF!
B19: =#REF! -> #REF! | C19: PRAIA GRANDE | D19: MEI | F19: Ativo | G19: Ar | H19: 44138 | K19: 0 | L19: 39 | M19: =#REF! -> #REF! | N19: =#REF! -> #REF! | O19: =#REF! -> #REF! | P19: =M19/L19 -> #REF!
B20: =#REF! -> #REF! | C20: PRAIA GRANDE | D20: MEI | F20: Ativo | G20: Ar | H20: 44138 | K20: 0 | L20: 39 | M20: =#REF! -> #REF! | N20: =#REF! -> #REF! | O20: =#REF! -> #REF! | P20: =M20/L20 -> #REF!
B21: Cristiano vasconcelos Firmino | C21: SANTOS | D21: MEI | F21: Ativo | H21: 45302 | L21: 2 | M21: =#REF! -> #REF! | N21: =#REF! -> #REF! | O21: =#REF! -> #REF! | P21: =M21/L21 -> #REF!
B22: Daniela Barreto dos Santos | C22: MAR BRASIL | D22: MEI | F22: Ativo | H22: 44774 | L22: 19 | M22: =#REF! -> #REF! | N22: 1000 | O22: 1000 | P22: =M22/L22 -> #REF!
B23: =#REF! -> #REF! | C23: PRAIA GRANDE | D23: MEI | F23: Ativo | G23: Ar | H23: 44270 | K23: 0 | L23: 36 | M23: =#REF! -> #REF! | N23: 5481.06 | O23: 5481.06 | P23: =M23/L23 -> #REF!
B24: Fernando Rodrigues Teixeira | C24: SANTOS | D24: MEI | F24: Ativo | H24: 45264 | L24: 3 | M24: 16588.71 | N24: =#REF! -> #REF! | O24: =#REF! -> #REF! | P24: =M24/L24 -> 5529.57
B25: Gabriel Wagner Bellini | C25: SANTOS | D25: MEI | F25: Ativo | G25: Ar | H25: 45348 | K25: 5 | L25: 1 | M25: 4836.21 | N25: =#REF! -> #REF! | O25: =#REF! -> #REF! | P25: =M25/L25 -> 4836.21
B26: Gabrielli Baeta de Oliveira | C26: MAR BRASIL | D26: MEI | F26: Ativo | H26: 45348 | L26: 1 | M26: 3413.79 | N26: =#REF! -> #REF! | O26: =#REF! -> #REF! | P26: =M26/L26 -> 3413.79
B27: Marcos Vinicius Fortes | C27: CHILLER | D27: MEI | F27: Ativo | H27: 44907 | K27: 0 | L27: 15 | M27: =#REF! -> #REF! | N27: =#REF! -> #REF! | O27: =#REF! -> #REF! | P27: =M27/L27 -> #REF!
B28: =#REF! -> #REF! | C28: MAR BRASIL | D28: MEI | F28: Ativo | G28: Ar | H28: 44046 | K28: 0 | L28: =(J$36-H28)/30 -> 42.933333 | M28: =#REF! -> #REF! | N28: 3000 | O28: 3000 | P28: =M28/L28 -> #REF!
B29: =#REF! -> #REF! | C29: OFTALMO | D29: MEI | F29: Ativo | G29: DEA | K29: 0 | M29: =#REF! -> #REF! | N29: =#REF! -> #REF! | O29: =#REF! -> #REF!
B30: Rafael Luiz Claro | C30: BERTIOGA/PRAIA GRAND | D30: MEI | F30: Ativo | H30: 45078 | K30: 0 | L30: =(J$36-H30)/30 -> 8.5333333 | M30: =#REF! -> #REF! | N30: =#REF! -> #REF! | O30: 2000 | P30: =M30/L30 -> #REF!
B31: Renato Ubiratan Pereira Leal Costa | C31: PRAIA GRANDE | D31: MEI | F31: Ativo | H31: 45028 | K31: 0 | L31: 11 | M31: =#REF! -> #REF! | N31: =#REF! -> #REF! | O31: =#REF! -> #REF! | P31: =M31/L31 -> #REF!
B32: Richard Salgado Costa | C32: MAR BRASIL | D32: MEI | F32: Ativo | H32: 44851 | K32: 0 | L32: 17 | M32: =#REF! -> #REF! | N32: =#REF! -> #REF! | O32: =#REF! -> #REF! | P32: =M32/L32 -> #REF!
B33: Sonia Aparecida Ferreira | C33: PESSOAL | D33: MEI | F33: Ativo | K33: 0 | L33: =(J$36-H33)/30 -> 1511.1333 | M33: =#REF! -> #REF! | N33: =#REF! -> #REF! | O33: =#REF! -> #REF! | P33: =M33/L33 -> #REF!
B34: Warley Xavier Lopes | C34: SANTOS | D34: MEI | F34: Ativo | H34: 44851 | K34: 0 | L34: 17 | M34: =#REF! -> #REF! | N34: =#REF! -> #REF! | O34: =#REF! -> #REF! | P34: =M34/L34 -> #REF!
B35: Total: | M35: =SUM(M5:M34) -> #REF! | N35: =SUM(N5:N34) -> #REF! | O35: =SUM(O5:O34) -> #REF! | P35: =SUM(P5:P34) -> #REF! | Q35: =SUM(Q7:Q34) -> 0 | R35: =R14+R13+R12+R11+R7 -> 40.35 | S35: =S14+S13+S12+S11+S7 -> 508.41
I36: 45268 | J36: 45334 | R36: =R17+R16+R15+R9+R6+R5 -> -39.22 | S36: =S17+S16+S15+S9+S6+S5 -> -329.77067
R38: CLT | S38: MEI
R39: =SUM( O5:O17) -> #REF! | S39: =SUM(O18:O34) -> #REF!
S41: =SUM(R39:S39) -> #REF!

Sheet BANCO DE HORAS
A1: Funcionários | D1: Banc remanescente | F1: 44562 | H1: 44593 | J1: 44621 | L1: 44652 | N1: 44682 | P1: 44713 | R1: Saldo remanescente | T1: NOVEMBRO | V1: DEZEMBRO | X1: JANEIRO | Z1: Total à pagar
A2: Descrição | B2: Valores hora extra | C2: Valores DSR | D2: Horas | E2: Valores | F2: Horas | G2: Valores | H2: Horas | I2: Valores | J2: Horas | K2: Valores | L2: Horas | M2: Valores | N2: Horas | O2: Valores | P2: Horas | Q2: Valores | R2: Horas | S2: Valor | T2: Horas | U2: Valor | V2: Horas | W2: Valor | X2: Horas | Y2: Valor | Z2: Horas | AA2: Valores
A3: Ana Lucia de Lima | B3: 11.65 | C3: =B3/4 -> 2.9125 | D3: 0.64444444 | E3: =(15.47*B3)+33.3011 -> 213.5266 | F3: 0.34513889 | G3: =(8.28*B3)+17.82373 -> 114.28573 | H3: 0.029861111 | I3: =(0.72*B3)+1.54989 -> 9.93789 | J3: 0.063194444 | K3: =(1.52*B3)+3.271989 -> 20.979989 | L3: 0.375 | M3: =(9*B3)+19.37362 -> 124.22362 | N3: 0.125 | O3: =(3*B3)+6.457873 -> 41.407873 | P3: 0.55277778 | Q3: =(13.27*B3)+28.56533 -> 183.16083 | T3: 0.25138889 | U3: =B3*6.03+14.05 -> 84.2995 | V3: 0.17013889 | W3: =B3*4.08+9.51 -> 57.042 | Z3: =T3+V3 -> 0.42152778 | AA3: =U3+W3 -> 141.3415
A4: Diana Miranda | B4: =788.08/71.53 -> 11.017475 | C4: =B4/4 -> 2.7543688 | F4: 1.1965278 | G4: =(28.72*B4)+58.4615 -> 374.88339 | H4: 0.0020833333 | I4: =(B4*0.05)+0.101778 -> 0.65265176 | J4: 0.096527778 | K4: =(2.32*B4)+4.722516 -> 30.283058 | L4: 0.36805556 | M4: =(8.83*B4)+17.97406 -> 115.25837 | N4: 0.98958333 | O4: =(23.75*B4)+48.34473 -> 310.00977 | P4: 1.4194444 | Q4: =(34.07*B4)+69.35178 -> 444.71716 | T4: 0.81805556 | U4: =19.63*B4+43.25 -> 259.52304 | V4: 0.099305556 | W4: =B4*2.38+5.24 -> 31.461591 | Z4: =T4-V4 -> 0.71875 | AA4: =U4-W4 -> 228.06145
A5: Douglas Pedrosa Abrantes | B5: =2529.67/235.03 -> 10.763179 | C5: =B5/4 -> 2.6907948 | Z5: =T5 -> 0 | AA5: =U5 -> 0
A6: Fagner Evinson Tosatti Albuquerque Araruna | B6: =112.08/9.62 -> 11.650728 | C6: =B6/4 -> 2.9126819 | R6: 0.86458333 | S6: =20.75*B6+48.35 -> 290.1026 | T6: 0.88611111 | U6: =21.27*B6+49.56 -> 297.37098 | V6: 1.7048611 | W6: =B6*40.92+95.35 -> 572.09778 | Z6: =T6+R6+V6 -> 3.4555556 | AA6: =S6+U6+W6 -> 1159.5714
A7: Gabriel Wagner Bellini | B7: =112.08/9.62 -> 11.650728 | C7: =B7/4 -> 2.9126819 | H7: 0.51736111 | I7: =(B7*12.42)+26.73574 -> 171.43778 | J7: 0.04375 | K7: =(B7*1.05)+2.260268 -> 14.493532 | L7: 2.7736111 | M7: =(66.57*B7)+143.301 -> 918.88994 | N7: 4.3541667 | O7: =(104.5*B7)+224.9504 -> 1442.4514 | P7: 2.1916667 | Q7: =(52.6*B7)+113.2286 -> 726.05687 | T7: 0.825 | U7: =19.8*B7+46.14 -> 276.82441 | Z7: =T7+V7 -> 0.825 | AA7: =U7 -> 276.82441
A8: João Pedro da Silva Pimenta | B8: =112.08/9.62 -> 11.650728 | C8: =B8/4 -> 2.9126819 | V8: 0.74861111 | W8: =B8*17.97+41.87 -> 251.23358 | Z8: =V8 -> 0.74861111 | AA8: =W8 -> 251.23358
A9: Misael dos Santos Silva | B9: =112.08/9.62 -> 11.650728 | C9: =B9/4 -> 2.9126819 | T9: 0.18333333 | U9: =4.4*B9+10.25 -> 61.513202 | V9: 0.16041667 | Z9: =T9+V9 -> 0.34375 | AA9: =U9 -> 61.513202
A10: Renan dos Santos Ramos Batista | B10: =112.08/9.62 -> 11.650728 | C10: =B10/4 -> 2.9126819 | R10: 0.35972222 | S10: =8.63*B10+20.11 -> 120.65578 | T10: 0.47569444 | U10: =11.42*B10+26.61 -> 159.66131 | Z10: =T10+R10 -> 0.83541667 | AA10: =U10 -> 159.66131
A11: Renato Ubiratan Pereira Leal Costa | B11: =112.08/9.62 -> 11.650728 | C11: =B11/4 -> 2.9126819 | R11: 6.6854167 | S11: =(160.45*B11)+273.87 -> 2143.2293 | T11: 0.63472222 | U11: =15.17*B11+35.35 -> 212.09154 | Z11: =T11+R11+V11 -> 7.3201389 | AA11: =U11+S11 -> 2355.3208

Sheet CONSOLIDADO ATIVO INATIVO NOVO
A1: Item | B1: Funcionários e prestadores de serviço | C1: Setor | D1: Cargo Inicial | E1: Último Cargo | F1: C. custo | G1: Tipo | H1: CBO | I1: Status | J1: Data inicial | K1: Data desligamento | L1: Tempo | M1: Valor inicial | N1: Último Pagto | O1: Média m. líquida | P1: Total
A2: 1 | B2: Eduardo Luksevicius | C2: Operacional | D2: Prestador Credenciado III | E2: Prestador Credenciado I | F2: PRAIA GRANDE | G2: MEI | I2: Inativo | J2: 44270 | K2: 45900 | L2: =DATEDIF(J2,K2,"m") -> 53 | M2: ='MEI - NOVA'!P19 -> 2500 | N2: ='MEI - NOVA'!BN19 -> 7416.35 | O2: ='[2]Setor 1'!$H$9 -> 4122.3168 | P2: ='MEI - NOVA'!BX19 -> 230686.49
A3: 2 | B3: Airton Rodrigues da Silva | C3: Operacional | D3: Prestador Credenciado III | E3: Prestador Credenciado I | F3: PRAIA GRANDE | G3: MEI | I3: Inativo | J3: 44138 | K3: 45687 | L3: =DATEDIF(J3,K3,"m") -> 50 | M3: ='MEI - NOVA'!K4 -> 5000 | N3: ='MEI - NOVA'!BH4 -> 9407.55 | O3: =P3/L3 -> 5284.2926 | P3: ='MEI - NOVA'!BX4 -> 264214.63
A4: 3 | B4: Miguel A Gomes Guerreiro | C4: Oftamologico | D4: Tecnico Oftamologico | E4: Tecnico Oftamologico | F4: OFTALMO | G4: MEI | I4: Inativo | J4: 44256 | K4: 45778 | L4: =DATEDIF(J4,K4,"m") -> 50 | M4: ='MEI - NOVA'!L44 -> 1500 | N4: ='MEI - NOVA'!BK44 -> 1000 | O4: =P4/L4 -> 1076 | P4: ='MEI - NOVA'!BX44 -> 53800
A5: 4 | B5: Alexandre Nascimento dos Santos | C5: Operacional | D5: Prestador Credenciado III | E5: Prestador Credenciado I | F5: PRAIA GRANDE | G5: MEI | I5: Inativo | J5: 44138 | K5: 45609 | L5: =DATEDIF(J5,K5,"m") -> 48 | M5: ='MEI - NOVA'!K8 -> 3500 | N5: ='MEI - NOVA'!BG8 -> 1747.61 | O5: =P5/L5 -> 4734.1785 | P5: ='MEI - NOVA'!BX8 -> 227240.57
A6: 5 | B6: Mathaus Liksevicius | C6: Tecnologia | D6: Suporte Nível III | E6: Gestor de Tecnologia | F6: MAR BRASIL | G6: MEI | I6: Inativo | J6: 44046 | K6: 45506 | L6: =DATEDIF(J6,K6,"m") -> 47 | M6: ='MEI - NOVA'!AV38 -> 3000 | N6: ='MEI - NOVA'!BD38 -> 3000 | O6: =P6/L6 -> 702.12766 | P6: ='MEI - NOVA'!BX38 -> 33000
A7: 6 | B7: Ed Carlos dos Santos | C7: Operacional | D7: Oficial de Serviços Gerais III | E7: Oficial de Serviços Gerais III | F7: PG | G7: CLT | H7: 514325 | I7: Inativo | J7: 44972 | L7: =DATEDIF(J7,TODAY(),"m") -> 39 | M7: ='CLT NOVA'!AM222 -> 2263.53 | N7: ='CLT NOVA'!AN222 -> 532.28 | O7: =P7/L7 -> 105.89077 | P7: ='CLT NOVA'!BX222 -> 4129.74
A8: 7 | B8: Marcos Vinicius Fortes | C8: Operacional | D8: Prestador Credenciado III | E8: Prestador Credenciado I | F8: STS 36693/22 | G8: MEI | I8: Inativo | J8: 44907 | K8: 45900 | L8: =DATEDIF(J8,K8,"m") -> 32 | M8: ='MEI - NOVA'!AK42 -> 4250 | N8: ='MEI - NOVA'!BL42 -> 5380 | O8: =P8/L8 -> 4465.2622 | P8: ='MEI - NOVA'!BX42 -> 142888.39
A9: 8 | B9: Renato Ubiratan Pereira Leal Costa | C9: Operacional | D9: Prestador Credenciado III | E9: Prestador Credenciado II | F9: STS 36693/22 | G9: MEI | I9: Ativo | J9: 45028 | L9: =DATEDIF(J9,TODAY(),"m") -> 37 | M9: ='MEI - NOVA'!AO51 -> 4275 | N9: ='MEI - NOVA'!BW51 -> 3407.5 | O9: =P9/L9 -> 4448.8584 | P9: ='MEI - NOVA'!BX51 -> 164607.76
A10: 9 | B10: Nickolas Alves Custódio | C10: Tecnologia | D10: Suporte Nível III | E10: Gestor de Tecnologia | F10: CONECTIUS | G10: MEI | I10: Inativo | J10: 45059 | L10: =DATEDIF(J10,TODAY(),"m") -> 36 | M10: ='MEI - NOVA'!AM46 -> 1500 | N10: ='MEI - NOVA'!BP46 -> 4500 | O10: =P10/L10 -> 2821.2111 | P10: ='MEI - NOVA'!BX46 -> 101563.6
A11: 10 | B11: Rafael Luiz Claro | C11: Operacional | D11: Engenheiro Mecânico | E11: Engenheiro Mecânico | F11: BERTIOGA/PRAIA GRAND | G11: MEI | I11: Ativo | J11: 45078 | L11: =DATEDIF(J11,TODAY(),"m") -> 36 | M11: ='MEI - NOVA'!AH49 -> 5004.12 | N11: ='MEI - NOVA'!BW49 -> 0 | O11: =P11/L11 -> 2396.1528 | P11: ='MEI - NOVA'!BX49 -> 86261.5
A12: 11 | B12: Renato Ubiratan Pereira Leal Costa | C12: Operacional | D12: Oficial de Serviços Gerais III | E12: Prestador Credenciado III | F12: PG 171/19 | G12: CLT | H12: 514320 | I12: Inativo | J12: 44138 | K12: 45027 | L12: =DATEDIF(J12,K12,"m") -> 29 | M12: ='CLT NOVA'!K538 -> 1564.88 | N12: ='CLT NOVA'!AN538 -> 4364.02 | O12: =P12/L12 -> 1949.2586 | P12: ='CLT NOVA'!BX538 -> 56528.5
A13: 12 | B13: Fabio Aparecido Dutra Paranaiba | C13: Operacional | D13: Supervisor Operacional | E13: Supervisor Operacional | F13: PRAIA GRANDE | G13: MEI | I13: Inativo | J13: 44185 | K13: 45061 | L13: =DATEDIF(J13,K13,"m") -> 28 | M13: ='MEI - NOVA'!K20 -> 5134.02 | N13: ='MEI - NOVA'!AO20 -> 7400 | O13: =P13/L13 -> 7818.9489 | P13: ='MEI - NOVA'!BX20 -> 218930.57
A14: 13 | B14: Fernanda Nakita | C14: Recursos Humanos | D14: Analista de Recursos Humanos III | E14: Analista de Recursos Humanos III | F14: PRAIA GRANDE | G14: MEI | I14: Inativo | J14: 44516 | K14: 45342 | L14: =DATEDIF(J14,K14,"m") -> 27 | M14: ='MEI - NOVA'!V23 -> 1144.33 | N14: ='MEI - NOVA'!AX23 -> 2025.89 | O14: =P14/L14 -> 2094.6748 | P14: ='MEI - NOVA'!BX23 -> 56556.22
A15: 14 | B15: Ana Lucia de Lima | C15: Limpeza | D15: Auxiliar de Serviços Gerais | E15: Auxilar de serviços | F15: PESSOAL | G15: CLT | H15: 514320 | I15: Inativo | J15: 44305 | K15: 45111 | L15: =DATEDIF(J15,K15,"m") -> 26 | M15: ='CLT NOVA'!Q81 -> 1465.77 | N15: ='CLT NOVA'!AQ81 -> 2934.43 | O15: =P15/L15 -> 2321.9377 | P15: ='CLT NOVA'!BX81 -> 60370.38
A16: 15 | B16: Warley Xavier Lopes | C16: Operacional | D16: Prestador Credenciado III | E16: Prestador Credenciado III | F16: SANTOS | G16: MEI | I16: Inativo | J16: 44851 | K16: 45626 | L16: =DATEDIF(J16,K16,"m") -> 25 | M16: ='MEI - NOVA'!AI59 -> 4250 | N16: ='MEI - NOVA'!BG59 -> 4078.55 | O16: =P16/L16 -> 4370.4392 | P16: ='MEI - NOVA'!BX59 -> 109260.98
A17: 16 | B17: Gabriel Wagner Bellini | C17: Operacional | D17: Oficial de Serviços Gerais III | E17: Oficial de Serviços Gerais III | F17: PG | G17: CLT | H17: 514320 | I17: Inativo | J17: 44593 | K17: 45337 | L17: =DATEDIF(J17,K17,"m") -> 24 | M17: ='CLT NOVA'!Z368 -> 1687.42 | N17: ='CLT NOVA'!AX368 -> 4041.13 | O17: =P17/L17 -> 2460.2342 | P17: ='CLT NOVA'!BX368 -> 59045.62
A18: 17 | B18: Andrea Aparecida de Oliveira Ferreira | C18: Rancho | D18: Auxiliar de Serviços Gerais | E18: Auxiliar de Serviços Gerais | F18: PESSOAL | G18: CLT | H18: 514320 | I18: Ativo | J18: 45260 | L18: =DATEDIF(J18,TODAY(),"m") -> 30 | M18: ='CLT NOVA'!AV17 -> 2474.73 | N18: ='CLT NOVA'!BW17 -> 3341.11 | O18: =P18/L18 -> 2441.5597 | P18: ='CLT NOVA'!BX17 -> 73246.79
A19: 18 | B19: Robson Roque Bernardo | C19: Operacional | D19: Oficial de Serviços Gerais III | E19: Oficial de Serviços Gerais II | F19: STS 36693/22 | G19: CLT | H19: 514320 | I19: Ativo | J19: 45264 | L19: =DATEDIF(J19,TODAY(),"m") -> 29 | M19: ='CLT NOVA'!AV564 -> 2110.63 | N19: ='CLT NOVA'!BW564 -> 2297.02 | O19: =P19/L19 -> 2208.7748 | P19: ='CLT NOVA'!BX564 -> 64054.47
A20: 19 | B20: Daniela Barreto dos Santos | C20: Financeiro | D20: Assistente Financeiro | E20: Analista Financeiro I | F20: MAR BRASIL | G20: MEI | I20: Inativo | J20: 44774 | K20: 45461 | L20: =DATEDIF(J20,K20,"m") -> 22 | M20: ='MEI - NOVA'!AF15 -> 1000 | N20: ='MEI - NOVA'!BA15 -> 4000 | O20: =P20/L20 -> 1659.0909 | P20: ='MEI - NOVA'!BX15 -> 36500
A21: 20 | B21: Richard Salgado Costa | C21: Operacional | D21: Gestor Operacional | E21: Gestor Operacional | F21: MAR BRASIL | G21: MEI | I21: Inativo | J21: 44851 | K21: 45547 | L21: =DATEDIF(J21,K21,"m") -> 22 | M21: ='MEI - NOVA'!AI54 -> 4250 | N21: ='MEI - NOVA'!BF54 -> 5712 | O21: =P21/L21 -> 7437.1827 | P21: ='MEI - NOVA'!BX54 -> 163618.02
A22: 21 | B22: Victor Hugo do Nascimento Soares | C22: Operacional | D22: Oficial de Serviços Gerais III | E22: Oficial de Serviços Gerais III | F22: STS 36693/22 | G22: CLT | H22: 514320 | I22: Inativo | J22: 45313 | L22: =DATEDIF(J22,TODAY(),"m") -> 28 | M22: ='CLT NOVA'!AX591 -> 2184.02 | N22: ='CLT NOVA'!BV591 -> 1328.06 | O22: =P22/L22 -> 1953.8339 | P22: ='CLT NOVA'!BX591 -> 54707.35
A23: 22 | B23: Diana Miranda | C23: Financeiro | D23: Auxiliar Financeiro III | E23: Analista Financeiro III | F23: MAR BRASIL | G23: CLT | H23: 411005 | I23: Inativo | J23: 44516 | K23: 45142 | L23: =DATEDIF(J23,K23,"m") -> 20 | M23: ='CLT NOVA'!X145 -> 2552.32 | N23: ='CLT NOVA'!AR145 -> 6672.35 | O23: =P23/L23 -> 3182.3585 | P23: ='CLT NOVA'!BX145 -> 63647.17
A24: 23 | B24: Deuzelina Almeida e Silva | C24: Rancho | D24: Auxiliar de Serviços Gerais | E24: Auxiliar de Serviços Gerais | F24: Conectius | G24: CLT | H24: 514320 | I24: Ativo | J24: 45351 | L24: =DATEDIF(J24,TODAY(),"m") -> 27 | M24: ='CLT NOVA'!AX787 -> 103.53 | N24: ='CLT NOVA'!BW787 -> 3021.83 | O24: =P24/L24 -> 2096.5059 | P24: ='CLT NOVA'!BX787 -> 56605.66
A25: 24 | B25: Gabriel Wagner Bellini | C25: Operacional | D25: Prestador Credenciado III | E25: Prestador Credenciado III | F25: SANTOS | G25: MEI | I25: Ativo | J25: 45348 | L25: =DATEDIF(J25,TODAY(),"m") -> 27 | M25: ='MEI - NOVA'!AY24 -> 4250 | N25: ='MEI - NOVA'!BW24 -> 6350 | O25: =P25/L25 -> 4820.0374 | P25: ='MEI - NOVA'!BX24 -> 130141.01
A26: 25 | B26: Joel Maicon Cardoso de Oliveira | C26: Operacional | D26: Oficial de Serviços Gerais III | E26: Oficial de Serviços Gerais III | F26: PG | G26: CLT | H26: 514320 | I26: Inativo | J26: 45096 | K26: 45722 | L26: =DATEDIF(J26,K26,"m") -> 20 | M26: ='CLT NOVA'!AQ315 -> 2018.2 | N26: ='CLT NOVA'!BK315 -> 723.73 | O26: =P26/L26 -> 2195.3255 | P26: ='CLT NOVA'!BX315 -> 43906.51
A27: 26 | B27: Gabriel da Silva Andrade | C27: Rancho | D27: Auxiliar de Serviços Gerais | E27: Auxiliar de Serviços Gerais | F27: Conectius | G27: CLT | H27: 514320 | I27: Inativo | J27: 45383 | L27: =DATEDIF(J27,TODAY(),"m") -> 26 | M27: ='CLT NOVA'!AW802 -> 1885.3 | N27: ='CLT NOVA'!BV802 -> 5504.48 | O27: =P27/L27 -> 2136.8215 | P27: ='CLT NOVA'!BX802 -> 55557.36
A28: 27 | B28: Gustavo Francisco de Souza Almeida | C28: Operacional | D28: Oficial de Serviços Gerais III | E28: Auxiliar Adm Operacional III | F28: PG | G28: CLT | H28: 411005 | I28: Inativo | J28: 45018 | K28: 45610 | L28: =DATEDIF(J28,K28,"m") -> 19 | M28: ='CLT NOVA'!AN394 -> 1890.67 | N28: ='CLT NOVA'!BG394 -> 9085.72 | O28: =P28/L28 -> 3056.5753 | P28: ='CLT NOVA'!BX394 -> 58074.93
A29: 28 | B29: Ademir Jose dos Santos | C29: Operacional | D29: Encarregado Operacional | E29: Motorista | F29: MAR BRASIL | G29: MEI | I29: Inativo | J29: 45390 | L29: =DATEDIF(J29,TODAY(),"m") -> 25 | M29: ='MEI - NOVA'!BA3 -> 4000 | N29: ='MEI - NOVA'!BS3 -> 3134 | O29: =P29/L29 -> 2393.4932 | P29: ='MEI - NOVA'!BX3 -> 59837.33
A30: 29 | B30: Sonia Aparecida Ferreira | C30: Limpeza | D30: Auxiliar de Limpeza | E30: Auxiliar de Limpeza | F30: PESSOAL | G30: MEI | I30: Inativo | J30: 44866 | K30: 45383 | L30: =DATEDIF(J30,K30,"m") -> 17 | M30: ='MEI - NOVA'!AI48 -> 390 | N30: ='MEI - NOVA'!AZ48 -> 300 | O30: =P30/L30 -> 311.76471 | P30: ='MEI - NOVA'!BX48 -> 5300
A31: 30 | B31: Carlos Eduardo Romero Vicente | C31: Licitações | D31: Analista Nível I | E31: Gestor de Licitações | F31: MAR BRASIL | G31: MEI | I31: Ativo | J31: 45474 | L31: =DATEDIF(J31,TODAY(),"m") -> 23 | M31: ='MEI - NOVA'!BC13 -> 4868.49 | N31: ='MEI - NOVA'!BW13 -> 8015.41 | O31: =P31/L31 -> 5198.317 | P31: ='MEI - NOVA'!BX13 -> 119561.29
A32: 31 | B32: Gisele Aparecida Pereira Lazari | C32: Recursos Humanos | D32: Analista de Recursos Humanos III | E32: Analista de Recursos Humanos II | F32: MAR BRASIL | G32: MEI | I32: Ativo | J32: 45481 | L32: =DATEDIF(J32,TODAY(),"m") -> 22 | M32: ='MEI - NOVA'!BD28 -> 3000 | N32: ='MEI - NOVA'!BW28 -> 5000 | O32: =P32/L32 -> 4014.6627 | P32: ='MEI - NOVA'!BX28 -> 88322.58
A33: 32 | B33: Ricardo dos Santos Lima | C33: Operacional | D33: Supervisor Operacional | E33: Gestor Operacional | F33: MAR BRASIL | G33: MEI | I33: Inativo | J33: 45456 | L33: =DATEDIF(J33,TODAY(),"m") -> 23 | M33: ='MEI - NOVA'!BC53 -> 5500 | N33: ='MEI - NOVA'!BP53 -> 5500 | O33: =P33/L33 -> 4773.913 | P33: ='MEI - NOVA'!BX53 -> 109800
A34: 33 | B34: Douglas Pedrosa Abrantes | C34: Operacional | D34: Oficial de Serviços Gerais III | E34: Oficial de Serviços Gerais III | F34: PG | G34: CLT | H34: 911205 | I34: Inativo | J34: 44270 | K34: 44756 | L34: =DATEDIF(J34,K34,"m") -> 15 | M34: ='CLT NOVA'!P208 -> 1593.19 | N34: ='CLT NOVA'!AD208 -> 6142.53 | O34: =P34/L34 -> 2047.6287 | P34: ='CLT NOVA'!BX208 -> 30714.43
A35: 34 | B35: Misael dos Santos Silva | C35: Operacional | D35: Oficial de Serviços Gerais III | E35: Oficial de Serviços Gerais III | F35: PG | G35: CLT | H35: 514320 | I35: Inativo | J35: 44746 | K35: 45225 | L35: =DATEDIF(J35,K35,"m") -> 15 | M35: ='CLT NOVA'!AE485 -> 1715.69 | N35: ='CLT NOVA'!AT485 -> 6536.18 | O35: =P35/L35 -> 2510.3093 | P35: ='CLT NOVA'!BX485 -> 37654.64
A36: 35 | B36: Bruno Oliveira Carvalho | C36: Tecnologia | D36: Estagiário | E36: Estagiário | F36: DZM | G36: EST | I36: Ativo | J36: 45495 | L36: =DATEDIF(J36,TODAY(),"m") -> 22 | M36: 706 | N36: ='CLT NOVA'!BW129 -> 1000 | O36: =P36/L36 -> 744.44864 | P36: ='CLT NOVA'!BX129 -> 16377.87
A37: 36 | B37: Pako Ruhan Cavalcanti de Andrade | C37: Operacional | D37: Oficial de Serviços Gerais III | E37: Oficial de Serviços Gerais II | F37: STS 36693/22 | G37: CLT | H37: 514320 | I37: Ativo | J37: 45498 | L37: =DATEDIF(J37,TODAY(),"m") -> 22 | M37: ='CLT NOVA'!BD498 -> 2202.66 | N37: ='CLT NOVA'!BW498 -> 53.34 | O37: =P37/L37 -> 1755.0436 | P37: ='CLT NOVA'!BX498 -> 38610.96
A38: 37 | B38: Wanderley Souza da Silva | C38: Operacional | D38: Oficial de Serviços Gerais III | E38: Oficial de Serviços Gerais III | F38: PG | G38: CLT | H38: 514320 | I38: Ativo | J38: 45505 | L38: =DATEDIF(J38,TODAY(),"m") -> 22 | M38: ='CLT NOVA'!BD655 -> 2172.72 | N38: ='CLT NOVA'!BW655 -> 2450.51 | O38: =P38/L38 -> 2174.0777 | P38: ='CLT NOVA'!BX655 -> 47829.71
A39: 38 | B39: Leandro Munis Rodrigues da Silva | C39: Operacional | D39: Prestador Credenciado III | E39: Prestador Credenciado III | F39: PRAIA GRANDE | G39: MEI | I39: Inativo | J39: 44138 | K39: 44602 | L39: =DATEDIF(J39,K39,"m") -> 15 | M39: ='MEI - NOVA'!K35 -> 4157.67 | N39: ='MEI - NOVA'!Y35 -> 4275 | O39: =P39/L39 -> 3666.3187 | P39: ='MEI - NOVA'!BX35 -> 54994.78
A40: 39 | B40: Adolfo Gabriel Pereira | C40: Operacional | D40: Oficial de Serviços Gerais | E40: Oficial de Serviços Gerais | F40: STS 36693/22 | G40: CLT | H40: 514320 | I40: Inativo | J40: 45264 | K40: 45664 | L40: =DATEDIF(J40,K40,"m") -> 13 | M40: ='CLT NOVA'!AV17 -> 2474.73 | N40: ='CLT NOVA'!BI33 -> 44.12 | O40: =P40/L40 -> 1607.6308 | P40: ='CLT NOVA'!BX33 -> 20899.2
A41: 40 | B41: Matheus Rodrigues Abrantes de Paula | C41: Licitações | D41: Analista de Licitação / Jurídico | E41: Analista de Licitação / Jurídico | F41: MAR BRASIL | G41: MEI | I41: Ativo | J41: 45547 | L41: =DATEDIF(J41,TODAY(),"m") -> 20 | M41: ='MEI - NOVA'!BF40 -> 3000 | N41: ='MEI - NOVA'!BW40 -> 8015.41 | O41: =P41/L41 -> 4871.1835 | P41: ='MEI - NOVA'!BX40 -> 97423.67
A42: 41 | B42: Wiilian Camara | C42: Operacional | D42: Suporte Nível III | E42: Suporte Nível II | F42: PRAIA GRANDE | G42: MEI | I42: Ativo | J42: 45566 | L42: =DATEDIF(J42,TODAY(),"m") -> 20 | M42: ='MEI - NOVA'!BF62 -> 2500 | N42: ='MEI - NOVA'!BW62 -> 4500 | O42: =P42/L42 -> 3450 | P42: ='MEI - NOVA'!BX62 -> 69000
A43: 42 | B43: Willian Hauro da Silva | C43: Operacional | D43: Prestador Credenciado III | E43: Prestador Credenciado III | F43: PRAIA GRANDE | G43: MEI | I43: Inativo | J43: 44586 | K43: 44986 | L43: =DATEDIF(J43,K43,"m") -> 13 | M43: ='MEI - NOVA'!Z58 -> 3220 | N43: ='MEI - NOVA'!BK62 -> 4500 | O43: =P43/L43 -> 3753.4731 | P43: ='MEI - NOVA'!BX58 -> 48795.15
A44: 43 | B44: Wagner Marques Sinna | C44: Operacional | D44: Oficial de Serviços Gerais III | E44: Oficial de Serviços Gerais III | F44: PG | G44: CLT | H44: 911205 | I44: Inativo | J44: 44228 | K44: 44603 | L44: =DATEDIF(J44,K44,"m") -> 12 | M44: ='CLT NOVA'!N642 -> 1542.62 | N44: ='CLT NOVA'!Z642 -> 2947.17 | O44: =P44/L44 -> 1884.4158 | P44: ='CLT NOVA'!BX642 -> 22612.99
A45: 44 | B45: Renan de Souza Miranda | C45: Operacional | D45: Oficial de Serviços Gerais III | E45: Oficial de Serviços Gerais III | F45: PG | G45: CLT | H45: 514320 | I45: Inativo | J45: 45604 | L45: =DATEDIF(J45,TODAY(),"m") -> 18 | M45: ='CLT NOVA'!BH524 -> 2163.12 | N45: ='CLT NOVA'!BV524 -> 5214.45 | O45: =P45/L45 -> 2257.0078 | P45: ='CLT NOVA'!BX524 -> 40626.14
A46: 45 | B46: João Pedro Pimenta | C46: Operacional | D46: Oficial de Serviços Gerais III | E46: Oficial de Serviços Gerais III | F46: PG | G46: CLT | H46: 514320 | I46: Inativo | J46: 44916 | K46: 45260 | L46: =DATEDIF(J46,K46,"m") -> 11 | M46: ='CLT NOVA'!AK302 -> 2110.87 | N46: ='CLT NOVA'!AU302 -> 9624.89 | O46: =P46/L46 -> 2847.9373 | P46: ='CLT NOVA'!BX302 -> 31327.31
A47: 46 | B47: Roberto Henrique dos Santos | C47: Operacional | D47: Oficial de Serviços Gerais III | E47: Oficial de Serviços Gerais III | F47: PG | G47: CLT | H47: 514320 | I47: Inativo | J47: 45264 | K47: 45622 | L47: =DATEDIF(J47,K47,"m") -> 11 | M47: ='CLT NOVA'!AV551 -> 2096.53 | N47: ='CLT NOVA'!BG551 -> 6800.21 | O47: =P47/L47 -> 2755.8427 | P47: ='CLT NOVA'!BX551 -> 30314.27
A48: 47 | B48: Caio Felipe Alves Ivo | C48: Operacional | D48: Oficial de Serviços Gerais III | E48: Oficial de Serviços Gerais III | F48: BER2022 | G48: CLT | H48: 514320 | I48: Inativo | J48: 44972 | K48: 45299 | L48: =DATEDIF(J48,K48,"m") -> 10 | M48: ='CLT NOVA'!AM158 -> 2062.05 | N48: ='CLT NOVA'!AW158 -> 496.02 | O48: =P48/L48 -> 2470.218 | P48: ='CLT NOVA'!BX158 -> 24702.18
A49: 48 | B49: Leonardo de Souza Negreiros | C49: Operacional | D49: Oficial de Serviços Gerais III | E49: Oficial de Serviços Gerais III | F49: STS 36693/22 | G49: CLT | H49: 514320 | I49: Inativo | J49: 45145 | K49: 45473 | L49: =DATEDIF(J49,K49,"m") -> 10 | M49: ='CLT NOVA'!AS459 -> 2282.82 | N49: ='CLT NOVA'!BB459 -> 3042.25 | O49: =P49/L49 -> 2916.246 | P49: ='CLT NOVA'!BX459 -> 29162.46
A50: 49 | B50: Diego Pereira Gomes | C50: Operacional | D50: Assistente Adm Operacional III | E50: Assistente Adm Operacional III | F50: MAR BRASIL | G50: MEI | I50: Ativo | J50: 45637 | L50: =DATEDIF(J50,TODAY(),"m") -> 17 | M50: ='MEI - NOVA'!BI18 -> 3000 | N50: ='MEI - NOVA'!BW18 -> 3500 | O50: =P50/L50 -> 2911.7647 | P50: ='MEI - NOVA'!BX18 -> 49500
A51: 50 | B51: Alan Deyvid de Siqueira | C51: Operacional | D51: Prestador Credenciado III | E51: Prestador Credenciado III | F51: PRAIA GRANDE | G51: MEI | I51: Inativo | J51: 45566 | K51: 45900 | L51: =DATEDIF(J51,K51,"m") -> 10 | M51: ='MEI - NOVA'!BF7 -> 4099.16 | N51: ='MEI - NOVA'!BN7 -> 5350 | O51: =P51/L51 -> 3864.609 | P51: ='MEI - NOVA'!BX7 -> 38646.09
A52: 51 | B52: Geovanna Chaves da Silva Carvalho | C52: Licitações | D52: Assistente de Licitações Nivel III | E52: Assistente de Licitações Nivel III | F52: MAR BRASIL | G52: MEI | I52: Ativo | J52: 45688 | L52: =DATEDIF(J52,TODAY(),"m") -> 16 | M52: ='MEI - NOVA'!BJ27 -> 2583.33 | N52: ='MEI - NOVA'!BV27 -> 3783.36 | O52: =P52/L52 -> 3271.5925 | P52: ='MEI - NOVA'!BX27 -> 52345.48
A53: 52 | B53: Guilherme Matheus de Oliveira Barros | C53: Financeiro | D53: Analista Financeiro Nível II | E53: Analista Financeiro Nível II | F53: MAR BRASIL | G53: MEI | I53: Ativo | J53: 45677 | L53: =DATEDIF(J53,TODAY(),"m") -> 16 | M53: ='MEI - NOVA'!BI30 -> 1000 | N53: ='MEI - NOVA'!BW30 -> 4000 | O53: =P53/L53 -> 3187.5 | P53: ='MEI - NOVA'!BX30 -> 51000
A54: 53 | B54: Paulo de Tassio | C54: Operacional | D54: Prestador Credenciado III | E54: Prestador Credenciado III | F54: BERTIOGA | G54: MEI | I54: Ativo | J54: 45691 | L54: =DATEDIF(J54,TODAY(),"m") -> 15 | M54: ='MEI - NOVA'!BJ47 -> 4421 | N54: ='MEI - NOVA'!BW47 -> 3783.33 | O54: =P54/L54 -> 3973.4673 | P54: ='MEI - NOVA'!BX47 -> 59602.01
A55: 54 | B55: Marcelo Mendes de Freitas | C55: Tecnologia | D55: Consultor de Tecnologia | E55: Consultor de Tecnologia | F55: PRAIA GRANDE | G55: MEI | I55: Inativo | J55: 45539 | K55: 45813 | L55: =DATEDIF(J55,K55,"m") -> 9 | M55: ='MEI - NOVA'!BF37 -> 3000 | N55: ='MEI - NOVA'!BK37 -> 3000 | O55: =P55/L55 -> 3033.3333 | P55: ='MEI - NOVA'!BX37 -> 27300
A56: 55 | B56: Alan Deyvid de Siqueira | C56: Operacional | D56: Oficial de Serviços Gerais III | E56: Prestador Credenciado III | F56: PRAIA GRANDE | G56: CLT | H56: 514320 | I56: Inativo | J56: 45302 | K56: 45565 | L56: =DATEDIF(J56,K56,"m") -> 8 | M56: ='CLT NOVA'!AV33 -> 2203.03 | N56: ='CLT NOVA'!BE49 -> 4880.97 | O56: =P56/L56 -> 3071.4862 | P56: ='CLT NOVA'!BX49 -> 24571.89
A57: 56 | B57: Alan Honorato Mendes | C57: Operacional | D57: Mecânico de Refrigeração III | E57: Auxiliar de Refrigeração III | F57: CSP 274/24 | G57: CLT | H57: 9112-05 | I57: Inativo | J57: 45726 | L57: =DATEDIF(J57,TODAY(),"m") -> 14 | M57: ='CLT NOVA'!BK694 -> 540.9 | N57: ='CLT NOVA'!BK694 -> 540.9 | O57: 540.9 | P57: ='CLT NOVA'!BX694 -> 540.9
A58: 57 | B58: Gabriel Henrique Araujo da Cruz | C58: Operacional | D58: Oficial de Serviços Gerais III | E58: Oficial de Serviços Gerais III | F58: PG | G58: CLT | H58: 514425 | I58: Inativo | J58: 45376 | K58: 45624 | L58: =DATEDIF(J58,K58,"m") -> 8 | M58: ='CLT NOVA'!AZ249 -> 2238.52 | N58: ='CLT NOVA'!BG249 -> 6126.11 | O58: =P58/L58 -> 2739.9575 | P58: ='CLT NOVA'!BX249 -> 21919.66
A59: 58 | B59: Jhon Weslley Rodrigues da Silva Fernandes | C59: Operacional | D59: Oficial de Serviços Gerais III | E59: Oficial de Serviços Gerais III | F59: PG | G59: CLT | H59: 514320 | I59: Inativo | J59: 45376 | K59: 45622 | L59: =DATEDIF(J59,K59,"m") -> 8 | M59: ='CLT NOVA'!AZ407 -> 2163.12 | N59: ='CLT NOVA'!BG407 -> 5755.36 | O59: =P59/L59 -> 2642.2565 | P59: ='CLT NOVA'!BX407 -> 21138.052
A60: 59 | B60: Abraao da Silva Costa | C60: Operacional | D60: Prestador Credenciado | E60: Prestador Credenciado | F60: SANTOS | G60: MEI | I60: Inativo | J60: 45281 | K60: 45536 | L60: =DATEDIF(J60,K60,"m") -> 8 | M60: ='MEI - NOVA'!AW2 -> 4250 | N60: ='MEI - NOVA'!BD2 -> 2250 | O60: =P60/L60 -> 4447.2662 | P60: ='MEI - NOVA'!BX2 -> 35578.13
A61: 60 | B61: Cristiano Vasconcelos Firmino | C61: Operacional | D61: Prestador Credenciado III | E61: Prestador Credenciado III | F61: SANTOS | G61: MEI | I61: Inativo | J61: 45302 | K61: 45572 | L61: =DATEDIF(J61,K61,"m") -> 8 | M61: ='MEI - NOVA'!AX14 -> 4250 | N61: ='MEI - NOVA'!BF14 -> 2083.57 | O61: =P61/L61 -> 4942.1587 | P61: ='MEI - NOVA'!BX14 -> 39537.27
A62: 61 | B62: Gabriel Nicolas Feitosa Lemos | C62: Operacional | D62: Oficial de Serviços Gerais III | E62: Oficial de Serviços Gerais III | F62: BER1390 | G62: CLT | H62: 514325 | I62: Inativo | J62: 45701 | L62: =DATEDIF(J62,TODAY(),"m") -> 15 | M62: ='CLT NOVA'!BJ341 -> 1142.66 | N62: ='CLT NOVA'!BQ341 -> 0 | O62: =P62/L62 -> 964.23067 | P62: ='CLT NOVA'!BX341 -> 14463.46
A63: 62 | B63: Giovanne Afonso Penutte Machado | C63: Operacional | D63: Oficial de Serviços Gerais III | E63: Oficial de Serviços Gerais III | F63: STS 36693/22 | G63: CLT | H63: 514325 | I63: Inativo | J63: 45707 | L63: =DATEDIF(J63,TODAY(),"m") -> 15 | M63: ='CLT NOVA'!BJ381 -> 889.89 | N63: ='CLT NOVA'!BR381 -> 896.37 | O63: =P63/L63 -> 1219.4193 | P63: ='CLT NOVA'!BX381 -> 18291.29
A64: 63 | B64: José Roberto De Lira | C64: Operacional | D64: Mecânico de Refrigeração I | E64: Mecânico de Refrigeração I | F64: CSP 274/24 | G64: CLT | H64: 9112-05 | I64: Inativo | J64: 45726 | L64: =DATEDIF(J64,TODAY(),"m") -> 14 | M64: ='CLT NOVA'!BK733 -> 2317.38 | N64: ='CLT NOVA'!BR733 -> 3762.51 | O64: =P64/L64 -> 1846.9293 | P64: ='CLT NOVA'!BX733 -> 25857.01
A65: 64 | B65: Gracy Antonio Nascimento de Jesus | C65: Recursos Humanos | D65: Analista de Recursos Humanos II | E65: Analista de Recursos Humanos II | F65: MAR BRASIL | G65: MEI | I65: Inativo | J65: 45719 | K65: 45915 | L65: =DATEDIF(J65,TODAY(),"m") -> 14 | M65: ='MEI - NOVA'!BK29 -> 3850 | N65: 4500 | O65: =P65/L65 -> 1882.1429 | P65: ='MEI - NOVA'!BX29 -> 26350
A66: 65 | B66: Justino Barbosa Da Silva Junior | C66: Operacional | D66: Encarregado de Refrigeração I | E66: Encarregado de Refrigeração I | F66: CSP 274/24 | G66: CLT | H66: 9101-10 | I66: Ativo | J66: 45726 | L66: =DATEDIF(J66,TODAY(),"m") -> 14 | M66: ='CLT NOVA'!BK746 -> 2491.93 | N66: ='CLT NOVA'!BW746 -> 4084.94 | O66: =P66/L66 -> 3408.1743 | P66: ='CLT NOVA'!BX746 -> 47714.44
A67: 66 | B67: Kauanny Roza Martinelli | C67: Comercial | D67: Assistente Comercial III | E67: Assistente Comercial III | F67: DZM | G67: MEI | I67: Inativo | J67: 45397 | K67: 45652 | L67: =DATEDIF(J67,K67,"m") -> 8 | M67: ='MEI - NOVA'!BA33 -> 2470 | N67: ='MEI - NOVA'!BG33 -> 2470 | O67: =P67/L67 -> 2317.9163 | P67: ='MEI - NOVA'!BX33 -> 18543.33
A68: 67 | B68: Victor Roberto Parpinelli Souza | C68: Operacional | D68: Mecânico de Refrigeração III | E68: Mecânico de Refrigeração III | F68: CSP 274/24 | G68: CLT | H68: 9112-05 | I68: Ativo | J68: 45726 | L68: =DATEDIF(J68,TODAY(),"m") -> 14 | M68: ='CLT NOVA'!BK772 -> 1924.26 | N68: ='CLT NOVA'!BW772 -> 3327.3 | O68: =P68/L68 -> 2660.8064 | P68: ='CLT NOVA'!BX772 -> 37251.29
A69: 68 | B69: Diana Miranda | C69: Financeiro | D69: Analista Financeiro III | E69: Analista Financeiro II | F69: MAR BRASIL | G69: MEI | I69: Inativo | J69: 45383 | K69: 45626 | L69: =DATEDIF(J69,K69,"m") -> 7 | M69: ='MEI - NOVA'!AV16 -> 3500 | N69: ='MEI - NOVA'!BF16 -> 4000 | O69: =P69/L69 -> 6214.2857 | P69: ='MEI - NOVA'!BX16 -> 43500
A70: 69 | B70: Walter Pozzeti Junior | C70: Tecnologia | D70: Marketing | E70: Marketing | F70: MAR BRASIL | G70: MEI | I70: Ativo | J70: 45747 | L70: =DATEDIF(J70,TODAY(),"m") -> 14 | M70: ='MEI - NOVA'!BL61 -> 3616.67 | N70: ='MEI - NOVA'!BW61 -> 3500 | O70: =P70/L70 -> 3008.3336 | P70: ='MEI - NOVA'!BX61 -> 42116.67
A71: 70 | B71: Fabio Antonio Bogajo | C71: Operacional | D71: Mecânico de Refrigeração I | E71: Mecânico de Refrigeração I | F71: CSP 274/24 | G71: CLT | H71: 9112-05 | I71: Ativo | J71: 45729 | L71: =DATEDIF(J71,TODAY(),"m") -> 14 | M71: ='CLT NOVA'!BK720 -> 2329.82 | N71: ='CLT NOVA'!BW720 -> 3128.01 | O71: =P71/L71 -> 2428.0371 | P71: ='CLT NOVA'!BX720 -> 33992.52
A72: 71 | B72: Misael Pereira Da Silva | C72: Operacional | D72: Mecânico de Refrigeração I | E72: Mecânico de Refrigeração I | F72: CSP 274/24 | G72: CLT | H72: 9112-05 | I72: Ativo | J72: 45729 | L72: =DATEDIF(J72,TODAY(),"m") -> 14 | M72: ='CLT NOVA'!BK759 -> 2056.7 | N72: ='CLT NOVA'!BW759 -> 3900.23 | O72: =P72/L72 -> 3168.965 | P72: ='CLT NOVA'!BX759 -> 44365.51
A73: 72 | B73: Luciana Serpeloni Borges | C73: Comercial | D73: Assistente Comercial III | E73: Assistente Comercial III | F73: DZM | G73: MEI | I73: Inativo | J73: 45750 | L73: =DATEDIF(J73,TODAY(),"m") -> 13 | M73: ='MEI - NOVA'!BL36 -> 2763.07 | N73: ='MEI - NOVA'!BP36 -> 2500 | O73: =P73/L73 -> 1751.0054 | P73: ='MEI - NOVA'!BX36 -> 22763.07
A74: 73 | B74: Raphael Kaych Nunes Câmara | C74: Tecnologia | D74: Suporte Nível III | E74: Suporte Nível III | F74: MAR BRASIL | G74: MEI | I74: Ativo | J74: 45740 | L74: =DATEDIF(J74,TODAY(),"m") -> 14 | M74: ='MEI - NOVA'!BL50 -> 2000 | N74: ='MEI - NOVA'!BW50 -> 4000 | O74: =P74/L74 -> 2642.8571 | P74: ='MEI - NOVA'!BX50 -> 37000
A75: 74 | B75: LUIZ VICTOR DA COSTA CRUZ | C75: Operacional | D75: Oficial de Serviços Gerais III | E75: Oficial de Serviços Gerais III | F75: STS 36693/22 | G75: CLT | H75: 514320 | I75: Inativo | J75: 45751 | L75: =DATEDIF(J75,TODAY(),"m") -> 13 | M75: ='CLT NOVA'!BL841 -> 2007.38 | N75: ='CLT NOVA'!BU841 -> 4374.26 | O75: =P75/L75 -> 1881.0269 | P75: ='CLT NOVA'!BX841 -> 24453.35
A76: 75 | B76: Guilherme Henrique Silva Silveira | C76: Operacional | D76: Oficial de Serviços Gerais III | E76: Oficial de Serviços Gerais III | F76: STS 36693/22 | G76: CLT | H76: 514320 | I76: Inativo | J76: 45751 | L76: =DATEDIF(J76,TODAY(),"m") -> 13 | M76: ='CLT NOVA'!BL854 -> 1990.88 | N76: ='CLT NOVA'!BR854 -> 6549.31 | O76: =P76/L76 -> 1529.8454 | P76: ='CLT NOVA'!BX854 -> 19887.99
A77: 76 | B77: Maximus Rhaziel Stahnke | C77: Operacional | D77: Oficial de Serviços Gerais III | E77: Oficial de Serviços Gerais III | F77: STS 36693/22 | G77: CLT | H77: 514320 | I77: Inativo | J77: 45264 | K77: 45458 | L77: =DATEDIF(J77,K77,"m") -> 6 | M77: ='CLT NOVA'!AW472 -> 2174.17 | N77: ='CLT NOVA'!BB472 -> 4977.73 | O77: =P77/L77 -> 3018.3417 | P77: ='CLT NOVA'!BX472 -> 18110.05
A78: 77 | B78: Sthefany de Santana Calacio | C78: Financeiro | D78: Auxiliar Administrativo | E78: Auxiliar Administrativo | F78: DZM | G78: CLT | H78: 411005 | I78: Inativo | J78: 45474 | K78: 45677 | L78: =DATEDIF(J78,K78,"m") -> 6 | M78: ='CLT NOVA'!BC578 -> 2111.74 | N78: ='CLT NOVA'!BI578 -> 4349.43 | O78: =P78/L78 -> 2936.345 | P78: ='CLT NOVA'!BX578 -> 17618.07
A79: 78 | B79: Fernando Rodrigues Teixeira | C79: Operacional | D79: Prestador Credenciado III | E79: Prestador Credenciado III | F79: SANTOS | G79: MEI | I79: Inativo | J79: 45264 | K79: 45454 | L79: =DATEDIF(J79,K79,"m") -> 6 | M79: ='MEI - NOVA'!AW22 -> 4250 | N79: ='MEI - NOVA'!AX23 -> 2025.89 | O79: =P79/L79 -> 4549.1783 | P79: ='MEI - NOVA'!BX22 -> 27295.07
A80: 79 | B80: Flavio Pereira da Silva | C80: Operacional | D80: Oficial de Serviços Gerais III | E80: Oficial de Serviços Gerais III | F80: STS 36693/22 | G80: CLT | H80: 514325 | I80: Ativo | J80: 45785 | L80: =DATEDIF(J80,TODAY(),"m") -> 12 | M80: ='CLT NOVA'!BM880 -> 1931.33 | N80: ='CLT NOVA'!BW880 -> 2461.77 | O80: =P80/L80 -> 2161.3067 | P80: ='CLT NOVA'!BX880 -> 25935.68
A81: 80 | B81: Carlos Eduardo Marquez Querioz | C81: Operacional | D81: Oficial de Serviços Gerais III | E81: Oficial de Serviços Gerais III | F81: STS 36693/22 | G81: CLT | H81: 514325 | I81: Inativo | J81: 45785 | L81: =DATEDIF(J81,TODAY(),"m") -> 12 | M81: ='CLT NOVA'!BM867 -> 1904.83 | N81: ='CLT NOVA'!BQ867 -> 745.05 | O81: =P81/L81 -> 836.14 | P81: ='CLT NOVA'!BX867 -> 10033.68
A82: 81 | B82: Danilo Jame de Jesus | C82: Operacional | D82: Mecânico de Refrigeração III | E82: Mecânico de Refrigeração III | F82: CSP 274/24 | G82: CLT | H82: 9112-05 | I82: Inativo | J82: 45771 | L82: =DATEDIF(J82,TODAY(),"m") -> 13 | M82: ='CLT NOVA'!BL815 -> 651.7 | N82: ='CLT NOVA'!BW815 -> 1618.01 | O82: =P82/L82 -> 2480.3431 | P82: ='CLT NOVA'!BX815 -> 32244.46
A83: 82 | B83: Edson Araujo Sousa | C83: Operacional | D83: Oficial de Serviços Gerais III | E83: Oficial de Serviços Gerais III | F83: CHILLER | G83: CLT | H83: 514320 | I83: Inativo | J83: 45448 | K83: 45624 | L83: =DATEDIF(J83,K83,"m") -> 5 | M83: ='CLT NOVA'!BB236 -> 1872.41 | N83: ='CLT NOVA'!BG236 -> 4948.36 | O83: =P83/L83 -> 2938.878 | P83: ='CLT NOVA'!BX236 -> 14694.39
A84: 83 | B84: Fagner Evinson Tosatti Albuquerque Araruna | C84: Operacional | D84: Oficial de Serviços Gerais III | E84: Prestador Credenciado III | F84: BER | G84: CLT | H84: 514325 | I84: Inativo | J84: 45579 | K84: 45747 | L84: =DATEDIF(J84,K84,"m") -> 5 | M84: ='CLT NOVA'!AI289 -> 2076.8 | N84: ='CLT NOVA'!BK289 -> 3779.97 | O84: =P84/L84 -> 7200.568 | P84: ='CLT NOVA'!BX289 -> 36002.84
A85: 84 | B85: Giovana Bisaio Fernandes | C85: Financeiro | D85: Auxiliar Administrativo | E85: Auxiliar Administrativo | F85: DZM | G85: CLT | H85: 411005 | I85: Inativo | J85: 45505 | K85: 45672 | L85: =DATEDIF(J85,K85,"m") -> 5 | M85: ='CLT NOVA'!BD263 -> 2216.75 | N85: ='CLT NOVA'!BI263 -> 3257.87 | O85: =P85/L85 -> 3031.716 | P85: ='CLT NOVA'!BX263 -> 15158.58
A86: 85 | B86: Gabrielli Baeta de Oliveira | C86: Recursos Humanos | D86: Analista de Recursos Humanos III | E86: Analista de Recursos Humanos III | F86: MAR BRASIL | G86: MEI | I86: Inativo | J86: 45348 | K86: 45506 | L86: =DATEDIF(J86,K86,"m") -> 5 | M86: ='MEI - NOVA'!AY25 -> 3000 | N86: ='MEI - NOVA'!BC25 -> 3193.55 | O86: =P86/L86 -> 3121.468 | P86: ='MEI - NOVA'!BX25 -> 15607.34
A87: 86 | B87: Nicole Fernanda Barbosa | C87: Financeiro | D87: Gestor Financeiro | E87: Gestor Financeiro | F87: MAR BRASIL | G87: MEI | I87: Inativo | J87: 45625 | K87: 45785 | L87: =DATEDIF(J87,K87,"m") -> 5 | M87: ='MEI - NOVA'!BH45 -> 3000 | N87: ='MEI - NOVA'!BK45 -> 4000 | O87: =P87/L87 -> 3040 | P87: ='MEI - NOVA'!BX45 -> 15200
A88: 87 | B88: Ana Carolina Medaglia | C88: Financeiro | D88: Assistente Financeiro | E88: Assistente Financeiro | F88: MAR BRASIL | G88: MEI | I88: Ativo | J88: 45796 | L88: =DATEDIF(J88,TODAY(),"m") -> 12 | M88: ='MEI - NOVA'!BM6 -> 1300 | N88: ='MEI - NOVA'!BS6 -> 4000 | O88: =P88/L88 -> 3300 | P88: ='MEI - NOVA'!BX6 -> 39600
A89: 88 | B89: Matheus Cardoso Ferraz Amaro Santos | C89: Tecnologia | D89: Suporte Nível III | E89: Suporte Nível III | F89: MAR BRASIL | G89: MEI | I89: Inativo | J89: 45810 | L89: =DATEDIF(J89,TODAY(),"m") -> 11 | M89: ='MEI - NOVA'!BN39 -> 2416.66 | N89: ='MEI - NOVA'!BS39 -> 2500 | O89: =P89/L89 -> 1810.6055 | P89: ='MEI - NOVA'!BX39 -> 19916.66
A90: 89 | B90: Marcos Antonio de Paula | C90: Financeiro | D90: Gestor Financeiro | E90: Gestor Financeiro | F90: MAR BRASIL | G90: MEI | I90: Ativo | J90: 45796 | L90: =DATEDIF(J90,TODAY(),"m") -> 12 | M90: ='MEI - NOVA'!BM43 -> 1950 | N90: ='MEI - NOVA'!BW43 -> 5500 | O90: =P90/L90 -> 4329.1667 | P90: ='MEI - NOVA'!BX43 -> 51950
A91: 90 | B91: Fagner Evinson Tosatti Albuquerque Araruna | C91: Operacional | D91: Prestador Credenciado III | E91: Prestador Credenciado III | F91: BER1390 | G91: MEI | I91: Inativo | J91: 45748 | K91: 45915 | L91: =DATEDIF(J91,K91,"m") -> 5 | M91: ='MEI - NOVA'!BL21 -> 4350 | N91: =M91 -> 4350 | O91: =P91/L91 -> 3818 | P91: ='MEI - NOVA'!BX21 -> 19090
A92: 91 | B92: Fabio José Amierio | C92: Operacional | D92: Oficial de Serviços Gerais III | E92: Oficial de Serviços Gerais III | F92: PG | G92: CLT | H92: 911205 | I92: Inativo | J92: 44138 | K92: 44265 | L92: =DATEDIF(J92,K92,"m") -> 4 | M92: ='CLT NOVA'!K276 -> 1315.14 | N92: ='CLT NOVA'!O276 -> 2782.8 | O92: =P92/L92 -> 2361.6825 | P92: ='CLT NOVA'!BX276 -> 9446.73
A93: 92 | B93: Thiago Mendonça de Castro | C93: Jurídico | D93: Jurídico | E93: Jurídico | F93: JÚRICO | G93: MEI | I93: Inativo | J93: 44866 | K93: 44986 | L93: =DATEDIF(J93,K93,"m") -> 4 | M93: ='MEI - NOVA'!AI55 -> 2000 | N93: ='MEI - NOVA'!AM55 -> 2000 | O93: =P93/L93 -> 2790.1525 | P93: ='MEI - NOVA'!BX55 -> 11160.61
A94: 93 | B94: Beatriz Marques Ferreira | C94: Comercial | D94: Assistente Comercial III | E94: Assistente Comercial III | F94: DZM | G94: MEI | I94: Inativo | J94: 45628 | K94: 45757 | L94: =DATEDIF(J94,K94,"m") -> 4 | M94: ='MEI - NOVA'!BH10 -> 3406.88 | N94: ='MEI - NOVA'!BK10 -> 2500 | O94: =P94/L94 -> 3026.72 | P94: ='MEI - NOVA'!BX10 -> 12106.88
A95: 94 | B95: Vicente Quartieri Neto | C95: Operacional | D95: Gestor Operacional | E95: Gestor Operacional | F95: MAR BRASIL | G95: MEI | I95: Inativo | J95: 45597 | K95: 45730 | L95: =DATEDIF(J95,K95,"m") -> 4 | M95: ='MEI - NOVA'!BG56 -> 5000 | N95: ='MEI - NOVA'!BK56 -> 2333.33 | O95: =P95/L95 -> 5583.3325 | P95: ='MEI - NOVA'!BX56 -> 22333.33
A96: 95 | B96: Gustavo Francisco de Souza Almeida | C96: Operacional | D96: Assistente Adm Operacional III | E96: Assistente Adm Operacional III | F96: MAR BRASIL | G96: MEI | I96: Inativo | J96: 45743 | K96: 45873 | L96: =DATEDIF(J96,K96,"m") -> 4 | M96: ='MEI - NOVA'!BL31 -> 2500 | N96: ='MEI - NOVA'!BL31 -> 2500 | O96: =P96/L96 -> 1875 | P96: ='MEI - NOVA'!BX31 -> 7500
A97: 96 | B97: Decio Toledo Leoni Neto | C97: Operacional | D97: Oficial de Serviços Gerais III | E97: Oficial de Serviços Gerais III | F97: STS 36693/22 | G97: CLT | H97: 514320 | I97: Inativo | J97: 45845 | L97: =DATEDIF(J97,TODAY(),"m") -> 10 | M97: ='CLT NOVA'!BO906 -> 2019.08 | N97: ='CLT NOVA'!BT906 -> 0 | O97: ='CLT NOVA'!BS906 -> 1196.39 | P97: ='CLT NOVA'!BX906 -> 10290.87
A98: 97 | B98: Roberto Pinheiro de Moura | C98: Operacional | D98: Mecânico de Refrigeração III | E98: Mecânico de Refrigeração III | F98: CSP 274/24 | G98: CLT | H98: 9112-05 | I98: Ativo | J98: 45832 | L98: =DATEDIF(J98,TODAY(),"m") -> 11 | M98: ='CLT NOVA'!BN997 -> 620.62 | N98: ='CLT NOVA'!BW997 -> 3743.2 | O98: ='CLT NOVA'!BS997 -> 3764 | P98: ='CLT NOVA'!BX997 -> 31306.1
A99: 98 | B99: Beatriz Pereira Fontes | C99: Recursos Humanos | D99: Analista Nível III | E99: Analista Nível III | F99: MAR BRASIL | G99: MEI | I99: Inativo | J99: 45572 | K99: 45691 | L99: =DATEDIF(J99,K99,"m") -> 3 | M99: ='MEI - NOVA'!BG11 -> 3000 | N99: ='MEI - NOVA'!BI11 -> 1500 | O99: =P99/L99 -> 3300 | P99: ='MEI - NOVA'!BX11 -> 9900
A100: 99 | B100: Geovanil Barbosa de Lima | C100: Financeiro | D100: Analista Financeiro I | E100: Analista Financeiro I | F100: MAR BRASIL | G100: MEI | I100: Inativo | J100: 45484 | K100: 45576 | L100: =DATEDIF(J100,K100,"m") -> 3 | M100: ='MEI - NOVA'!BD26 -> 5000 | N100: ='MEI - NOVA'!BF26 -> 1833.33 | O100: =P100/L100 -> 5073.4767 | P100: ='MEI - NOVA'!BX26 -> 15220.43
...

Sheet MEI - NOVA
A1: ITEM | B1: PRESTADORES DE SERVIÇO | C1: STATUS | D1: SETOR | E1: CARGO INICIAL | F1: ÚLTIMO CARGO | G1: DATA INICIAL | H1: DESLIGAMENTO | I1: TEMPO | J1: 44105 | K1: 44136 | L1: 44166 | M1: 44197 | N1: 44228 | O1: 44256 | P1: 44287 | Q1: 44317 | R1: 44348 | S1: 44378 | T1: 44409 | U1: 44440 | V1: 44470 | W1: 44501 | X1: 44531 | Y1: 44562 | Z1: 44593 | AA1: 44621 | AB1: 44652 | AC1: 44682 | AD1: 44713 | AE1: 44743 | AF1: 44774 | AG1: 44805 | AH1: 44835 | AI1: 44866 | AJ1: 44896 | AK1: 44927 | AL1: 44958 | AM1: 44986 | AN1: 45017 | AO1: 45047 | AP1: 45078 | AQ1: 45108 | AR1: 45139 | AS1: 45170 | AT1: 45200 | AU1: 45231 | AV1: 45261 | AW1: 45292 | AX1: 45323 | AY1: 45352 | AZ1: 45383 | BA1: 45413 | BB1: 45444 | BC1: 45474 | BD1: 45505 | BE1: 45536 | BF1: 45566 | BG1: 45597 | BH1: 45627 | BI1: 45658 | BJ1: 45689 | BK1: 45717 | BL1: 45748 | BM1: 45778 | BN1: 45809 | BO1: 45839 | BP1: 45870 | BQ1: 45901 | BR1: 45931 | BS1: 45962 | BT1: 45992 | BU1: 46023 | BV1: 46054 | BW1: 46082
A2: 1 | B2: Abraao da Silva Costa | C2: INATIVO | G2: 45281 | H2: 45536 | AV2: 1508.06 | AW2: 4250 | AX2: 4250 | AY2: 4250 | AZ2: 4250 | BA2: 3825 | BB2: =4250+46.67+136.8 -> 4433.47 | BC2: =6416+100+45.6 -> 6561.6 | BD2: 2250 | BX2: =SUM(J2:BU2) -> 35578.13
A3: 2 | B3: Ademir Jose dos Santos | C3: INATIVO | D3: Operacional | E3: Encarregado Operacional | F3: Motorista | G3: ='CONSOLIDADO ATIVO INATIVO NOVO'!J65 -> 45719 | AZ3: 3066.68 | BA3: 4000 | BB3: 4000 | BC3: 4000 | BD3: 4000 | BE3: 4000 | BF3: 4000 | BG3: 4533.33 | BH3: 2383.32 | BI3: 2700 | BJ3: 2500 | BK3: 2500 | BL3: 2500 | BM3: 2500 | BN3: 2500 | BO3: 2500 | BP3: 2520 | BQ3: 2500 | BR3: 0 | BS3: 3134 | BT3: 0 | BX3: =SUM(J3:BU3) -> 59837.33
A4: 3 | B4: Airton Rodrigues da Silva | C4: INATIVO | D4: Operacional | E4: Prestador Credenciado III | F4: Prestador Credenciado I | G4: ='CONSOLIDADO ATIVO INATIVO NOVO'!J66 -> 45726 | H4: 45687 | K4: 5000 | L4: 5000 | M4: 5000 | N4: 5000 | O4: 5000 | P4: 5000 | Q4: 5000 | R4: =5000+838.72 -> 5838.72 | S4: 5000 | T4: 5000 | U4: 5000 | V4: 5000 | W4: 5000 | X4: 5000 | Y4: 5000 | Z4: 5000 | AA4: 5000 | AB4: =5000+280 -> 5280 | AC4: 5000 | AD4: 4966.96 | AE4: 4961.45 | AG4: 4961.45 | AH4: 4961.45 | AI4: 5000 | AJ4: 5000 | AK4: 5000 | AL4: 5000 | AM4: 5000 | AN4: 5000 | AO4: 5000 | AP4: 5000 | AQ4: 5000 | AR4: 5000 | AS4: 5000 | AT4: 5000 | AU4: =144.6+5000 -> 5144.6 | AV4: 5241 | AW4: 5241 | AX4: =5241+579.27 -> 5820.27 | AY4: 5241 | AZ4: =5241+633.3+557.13 -> 6431.43 | BA4: =4605.85+635.14+633.3 -> 5874.29 | BB4: =5241+435.6+633.3 -> 6309.9 | BC4: =5241+100+91.2+23.33+843.9 -> 6299.43 | BD4: =4081.75+635.14+91.2+100 -> 4908.09 | BE4: =4081.75+635.14+91.2+100 -> 4908.09 | BF4: 9808.2 | BG4: 7609.75 | BH4: 9407.55 | BX4: =SUM(J4:BU4) -> 264214.63
A5: 4 | B5: Anderson Teixeira Luz | C5: INATIVO | D5: Operacional | E5: Prestador Credenciado III | F5: Prestador Credenciado III | G5: 45870 | BP5: 2225 | BQ5: 4250 | BR5: 4750 | BX5: =SUM(J5:BU5) -> 11225
A6: 5 | B6: Ana Carolina Medaglia | C6: ATIVO | D6: Financeiro | E6: Assistente Financeiro | F6: Assistente Financeiro | G6: 45796 | BM6: 1300 | BN6: 3000 | BO6: 3000 | BP6: 4000 | BQ6: 4600 | BR6: 3700 | BS6: 4000 | BT6: 4000 | BU6: 4000 | BV6: 4000 | BW6: 4000 | BX6: =SUM(J6:BW6) -> 39600
A7: 6 | B7: Alan Deyvid de Siqueira | C7: INATIVO | D7: Operacional | E7: Prestador Credenciado III | F7: Prestador Credenciado III | G7: ='CONSOLIDADO ATIVO INATIVO NOVO'!J69 -> 45383 | BF7: =3999.16+100 -> 4099.16 | BG7: =1679.16+100 -> 1779.16 | BH7: 3661 | BI7: 3576.5 | BJ7: 3970.27 | BK7: 4250 | BL7: 5350 | BM7: 5350 | BN7: 5350 | BO7: 1260 | BP7: 0 | BX7: =SUM(J7:BU7) -> 38646.09
A8: 7 | B8: Alexandre Nascimento dos Santos | C8: INATIVO | D8: Operacional | E8: Prestador Credenciado III | F8: Prestador Credenciado I | G8: 44138 | H8: 45609 | K8: 3500 | L8: 3500 | M8: 3500 | N8: 3500 | O8: 3500 | P8: 3500 | Q8: 3500 | R8: =3500+1419.34 -> 4919.34 | S8: 3500 | T8: 3500 | U8: 3500 | V8: 3500 | W8: 4275 | X8: 4275 | Y8: 4275 | Z8: 4275 | AA8: 4275 | AB8: 4275 | AC8: 4275 | AD8: 4275 | AE8: 4148.95 | AF8: 5275 | AG8: =1000+4155.1 -> 5155.1 | AH8: =1000+4148.95 -> 5148.95 | AI8: 4275 | AJ8: 5275 | AK8: 5275 | AL8: 5275 | AM8: 5275 | AN8: 5275 | AO8: 5275 | AP8: 5275 | AQ8: 5275 | AR8: 5275 | AS8: 5275 | AT8: 5275 | AU8: =123.63+5275 -> 5398.63 | AV8: =5746.19+123.63 -> 5869.82 | AW8: =3954.34+750+265.13+526.72 -> 5496.19 | AX8: 5746.19 | AY8: 5746.19 | AZ8: 5746.19 | BA8: 4746.19 | BB8: =5481.06+265.13+23.33 -> 5769.52 | BC8: =5746.19+100+551.4 -> 6397.59 | BD8: =4032.95+265.13+100+1000 -> 5398.08 | BE8: 5398.08 | BF8: 4132.95 | BG8: 1747.61 | BX8: =SUM(J8:BU8) -> 227240.57
A9: 8 | B9: Amanda Aparecida Costa de Oliveira | C9: INATIVO | D9: Comercial | E9: Gestor Comercial | F9: Gestor Comercial | G9: 45367 | H9: 45446 | AY9: 1806.45 | AZ9: 3000 | BA9: 3000 | BB9: 3000 | BC9: 193.54 | BX9: =SUM(J9:BU9) -> 10999.99
A10: 9 | B10: Beatriz Marques Ferreira | C10: INATIVO | D10: Comercial | E10: Assistente Comercial III | F10: Assistente Comercial III | G10: ='CONSOLIDADO ATIVO INATIVO NOVO'!J72 -> 45729 | H10: 45757 | BH10: 3406.88 | BI10: 3700 | BJ10: 2500 | BK10: 2500 | BX10: =SUM(J10:BU10) -> 12106.88
A11: 10 | B11: Beatriz Pereira Fontes | C11: INATIVO | D11: Recursos Humanos | E11: Analista de RH Nível III | F11: Analista de RH Nível III | G11: ='CONSOLIDADO ATIVO INATIVO NOVO'!J73 -> 45750 | H11: 45691 | BF11: 2400 | BG11: 3000 | BH11: 3000 | BI11: 1500 | BX11: =SUM(J11:BU11) -> 9900
A12: 11 | B12: Camila Lourenço Ebenau | C12: INATIVO | D12: Comercial | E12: Assistente Financeiro | F12: Assistente Financeiro | G12: 45399 | H12: 45369 | AZ12: 3532.26 | BA12: 2500 | BB12: 416.66 | BX12: =SUM(J12:BU12) -> 6448.92
A13: 12 | B13: Carlos Eduardo Romero Vicente | C13: ATIVO | D13: Licitações | E13: Analista de Licitação Nível I | F13: Gestor de Licitações | G13: ='CONSOLIDADO ATIVO INATIVO NOVO'!J75 -> 45751 | BC13: 4868.49 | BD13: 3769.89 | BE13: =3500+798.13 -> 4298.13 | BF13: =3500+25.7+1474.3 -> 5000 | BG13: 7000 | BH13: 5000 | BI13: 5000 | BJ13: 5000 | BK13: 5000 | BL13: 5000 | BM13: 5000 | BN13: 5000 | BO13: 5000 | BP13: 6706.9 | BQ13: 7919.23 | BR13: 5757.6 | BS13: 5706.73 | BT13: =5000+2576.62 -> 7576.62 | BU13: =5000+2611.71 -> 7611.71 | BV13: =5000+330.58 -> 5330.58 | BW13: =5000+3015.41 -> 8015.41 | BX13: =SUM(J13:BW13) -> 119561.29
A14: 13 | B14: Cristiano Vasconcelos Firmino | C14: INATIVO | D14: Operacional | E14: Prestador Credenciado III | F14: Prestador Credenciado III | G14: 45302 | H14: 45572 | AW14: 2879.03 | AX14: 4250 | AY14: 4250 | AZ14: 4250 | BA14: 4250 | BB14: =4250+46.67+136.8 -> 4433.47 | BC14: =4250+100+45.6 -> 4395.6 | BD14: =4250+100+45.6 -> 4395.6 | BE14: =4250+100 -> 4350 | BF14: 2083.57 | BX14: =SUM(J14:BU14) -> 39537.27
A15: 14 | B15: Daniela Barreto Dos Santos | C15: INATIVO | D15: Financeiro | E15: Assistente Financeiro | F15: Assistente Financeiro | G15: 44774 | H15: 45461 | AF15: 1000 | AG15: 1000 | AH15: 1000 | AI15: 1000 | AJ15: 1000 | AK15: 1000 | AL15: 1000 | AM15: 1000 | AN15: 1000 | AO15: 1000 | AP15: 1000 | AQ15: 1000 | AR15: 1000 | AS15: 1000 | AT15: 1000 | AU15: 1000 | AV15: 1000 | AW15: 1000 | AX15: 4000 | AY15: 4000 | AZ15: 6500 | BA15: 4000 | BX15: =SUM(J15:BU15) -> 36500
A16: 15 | B16: Diana Miranda | C16: INATIVO | D16: Financeiro | E16: Analista Financeiro III | F16: Analista Financeiro II | G16: 45383 | H16: 45626 | AV16: 3500 | AW16: 3500 | AX16: 3500 | AY16: 3500 | AZ16: 3500 | BA16: 3500 | BB16: 3500 | BC16: 7000 | BD16: 4000 | BE16: 4000 | BF16: 4000 | BX16: =SUM(J16:BU16) -> 43500
A17: 16 | B17: Douglas Mariano Ribeiro | C17: ATIVO | D17: Operacional | E17: Gestor Operacional | F17: Gestor Operacional | G17: 45894 | BP17: 500 | BQ17: 5000 | BR17: 5000 | BS17: 5000 | BT17: 5000 | BU17: 5000 | BV17: 5900 | BW17: 5900 | BX17: =SUM(J17:BW17) -> 37300
A18: 17 | B18: Diego Pereira Gomes | C18: ATIVO | D18: Operacional | E18: Assistente Adm Operacional III | F18: Assistente Adm Operacional III | G18: ='CONSOLIDADO ATIVO INATIVO NOVO'!J79 -> 45264 | BH18: 2000 | BI18: 3000 | BJ18: 3000 | BK18: 3000 | BL18: 3000 | BM18: 3000 | BN18: 3000 | BO18: 3000 | BP18: 3000 | BQ18: 3000 | BR18: 3000 | BS18: 3500 | BT18: 3500 | BU18: 3500 | BV18: 3500 | BW18: 3500 | BX18: =SUM(J18:BW18) -> 49500
A19: 18 | B19: Eduardo Luksevicius | C19: INATIVO | D19: Operacional | E19: Prestador Credenciado III | F19: Prestador Credenciado I | G19: ='CONSOLIDADO ATIVO INATIVO NOVO'!J81 -> 45785 | O19: 1290.32 | P19: 2500 | Q19: 2500 | R19: =2500+101.02 -> 2601.02 | S19: 2500 | T19: 2500 | U19: 2500 | V19: 2500 | W19: 3218.75 | X19: 3218.75 | Y19: 3218.75 | Z19: 3218.75 | AA19: 3218.75 | AB19: 3218.75 | AC19: 3218.75 | AD19: 3218.75 | AE19: 3218.75 | AF19: 3218.75 | AG19: 4098.85 | AH19: 4218.75 | AI19: 4275 | AJ19: 4275 | AK19: 4275 | AL19: 4275 | AM19: 4275 | AN19: 4275 | AO19: 4275 | AP19: 4275 | AQ19: 4275 | AR19: 4275 | AS19: 4275 | AT19: 4275 | AU19: =123.63+4275 -> 4398.63 | AV19: 5481.06 | AW19: =5481.06+123.63 -> 5604.69 | AX19: 5481.06 | AY19: 5481.06 | AZ19: 5481.06 | BA19: =5231.06+167.3 -> 5398.36 | BB19: =5481.06+695.39+908.4 -> 7084.85 | BC19: =5981.06+120 -> 6101.06 | BD19: 4981.06 | BE19: 5132.95 | BF19: 6662.11 | BG19: 5420.6 | BH19: 6485.6 | BI19: 6485.6 | BJ19: 4292.6 | BK19: 5447.05 | BL19: 7373.6 | BM19: 7373.6 | BN19: 7416.35 | BO19: 2407.1 | BP19: 0 | BX19: =SUM(J19:BU19) -> 230686.49
A20: 19 | B20: Fabio Aparecido Dutra Paranaiba | C20: INATIVO | D20: Operacional | E20: Supervisor Operacional | F20: Supervisor Operacional | G20: 44185 | H20: 45061 | J20: =1935.48 -> 1935.48 | K20: =5000+134.02 -> 5134.02 | L20: =5000+288.01 -> 5288.01 | M20: =5000+399.91 -> 5399.91 | N20: =5000+403.4 -> 5403.4 | O20: =5000+310.83 -> 5310.83 | P20: =5000+201.02 -> 5201.02 | Q20: =5000+425.59 -> 5425.59 | R20: =5000+1436.02+603.39 -> 7039.41 | S20: =5000+436.1 -> 5436.1 | T20: =7000+409.37 -> 7409.37 | U20: =7000+944.35 -> 7944.35 | V20: =7000+546.87 -> 7546.87 | W20: =7000+720.15 -> 7720.15 | X20: =7000+538.91 -> 7538.91 | Y20: =7000+627.79 -> 7627.79 | Z20: =7000+677.05 -> 7677.05 | AA20: =7000+469.27 -> 7469.27 | AB20: =7000+875.7 -> 7875.7 | AC20: =7000+2252.97+898.07 -> 10151.04 | AD20: =7000+391.24 -> 7391.24 | AE20: 7400 | AF20: 7400 | AG20: 7400 | AH20: 7400 | AI20: 7400 | AJ20: 7400 | AK20: 7400 | AL20: 7400 | AM20: =7400-394.94 -> 7005.06 | AN20: 7400 | AO20: 7400 | AP20: 0 | BX20: =SUM(J20:BU20) -> 218930.57
A21: 20 | B21: Fagner Evinson Tosatti Albuquerque Araruna | C21: INATIVO | D21: Operacional | E21: Prestador Credenciado III | F21: Prestador Credenciado III | G21: 45748 | BL21: 4350 | BM21: 4350 | BN21: 4350 | BO21: 1790 | BP21: 4250 | BX21: =SUM(J21:BU21) -> 19090
A22: 21 | B22: Fernando Rodrigues Teixeira | C22: INATIVO | D22: Operacional | E22: Prestador Credenciado III | F22: Prestador Credenciado III | G22: 45264 | H22: 45454 | AV22: 3838.71 | AW22: 4250 | AX22: 4250 | AY22: 4250 | AZ22: 4250 | BA22: 3825 | BB22: =506.36+2125 -> 2631.36 | BX22: =SUM(J22:BU22) -> 27295.07
A23: 22 | B23: Fernanda Nakita | C23: INATIVO | D23: Recursos Humanos | E23: Analista de Recursos Humanos III | F23: Analista de Recursos Humanos III | G23: 44516 | H23: 45342 | V23: 1144.33 | W23: 1300 | X23: =273+1300 -> 1573 | Y23: =1300+273 -> 1573 | Z23: =1300+270 -> 1570 | AA23: =1300+270 -> 1570 | AB23: =1300+270 -> 1570 | AC23: 1570 | AD23: 1570 | AE23: 1570 | AF23: 1570 | AG23: =500+1570 -> 2070 | AH23: =500+1570 -> 2070 | AI23: =500+1570 -> 2070 | AJ23: =500+1570 -> 2070 | AK23: =500+1570 -> 2070 | AL23: =500+1570 -> 2070 | AM23: =500+1570 -> 2070 | AN23: =500+1570 -> 2070 | ... AS23: =500+1570 -> 2070 | AT23: 2770 | AU23: 3270 | AV23: 2500 | AW23: 2500 | AX23: 2025.89 | AY23: 0 | AZ23: 0 | BA23: 0 | BB23: 0 | BC23: 0 | BX23: =SUM(J23:BU23) -> 56556.22
A24: 23 | B24: Gabriel Wagner Silva Bellini | C24: ATIVO | D24: Operacional | E24: Prestador Credenciado III | F24: Prestador Credenciado III | G24: ='CONSOLIDADO ATIVO INATIVO NOVO'!J85 -> 45505 | AX24: 586.21 | AY24: 4250 | AZ24: 4250 | BA24: 3825 | BB24: =4250+46.67 -> 4296.67 | BC24: =4250+2009.54+582.59+100 -> 6942.13 | BD24: =3825+100 -> 3925 | BE24: 4350 | BF24: 3925 | BG24: 4350 | BH24: 4350 | BI24: 4350 | BJ24: 4350 | BK24: 2015 | BL24: 6350 | BM24: 7350 | BN24: 7350 | BO24: 2780 | BP24: 6096 | BQ24: 6350 | BR24: 6350 | BS24: 6350 | BT24: 6350 | BU24: 6350 | BV24: 6350 | BW24: 6350 | BX24: =SUM(J24:BW24) -> 130141.01
A25: 24 | B25: Gabrielli Baeta de Oliveira Mendes | C25: INATIVO | D25: Recursos Humanos | E25: Analista de Recursos Humanos III | F25: Analista de Recursos Humanos III | G25: 45348 | H25: 45506 | AX25: 413.79 | AY25: 3000 | AZ25: 3000 | BA25: 3000 | BB25: 3000 | BC25: 3193.55 | BX25: =SUM(J25:BU25) -> 15607.34
A26: 25 | B26: Geovanil Barbosa de Lima | C26: INATIVO | D26: Financeiro | E26: Analista Financeiro I | F26: Analista Financeiro I | G26: 45484 | H26: 45576 | BC26: 3387.1 | BD26: 5000 | BE26: 5000 | BF26: 1833.33 | BX26: =SUM(J26:BU26) -> 15220.43
A27: 26 | B27: Geovanna Chaves da Silva Carvalho | C27: ATIVO | D27: Licitações | E27: Assistente de Licitações Nivel III | F27: Assistente de Licitações Nivel III | G27: 45688 | BJ27: 2583.33 | BK27: 2500 | BL27: 2500 | BM27: 3173.21 | BN27: 3182.94 | BO27: 3182.94 | BP27: 3975.37 | BQ27: 4668.12 | BR27: 4500 | BS27: 3431.02 | BT27: =2125+1416.94 -> 3541.94 | BU27: =3000+2238.61 -> 5238.61 | BV27: =3500+283.36 -> 3783.36 | BW27: =3500+2584.64 -> 6084.64 | BX27: =SUM(J27:BW27) -> 52345.48
A28: 27 | B28: Gisele Aparecida Pereira Lazari | C28: ATIVO | D28: Recursos Humanos | E28: Analista de Recursos Humanos III | F28: Analista de Recursos Humanos II | G28: ='CONSOLIDADO ATIVO INATIVO NOVO'!J89 -> 45810 | BC28: 2322.58 | BD28: 3000 | BE28: 3000 | BF28: 4000 | BG28: 4000 | BH28: 6000 | BI28: 4000 | BJ28: 4000 | BK28: 4000 | BL28: 4000 | BM28: 4000 | BN28: 4000 | BO28: 4000 | BP28: 4000 | BQ28: 4000 | BR28: 5000 | BS28: 5000 | BT28: 5000 | BU28: 5000 | BV28: 5000 | BW28: 5000 | BX28: =SUM(J28:BW28) -> 88322.58
A29: 28 | B29: Gracy Antonio Nascimento de Jesus | C29: INATIVO | D29: Recursos Humanos | E29: Analista de Recursos Humanos II | F29: Analista de Recursos Humanos II | G29: 45719 | BK29: 3850 | BL29: 4500 | BM29: 4500 | BN29: 4500 | BO29: 4500 | BP29: 4500 | BX29: =SUM(J29:BU29) -> 26350
A30: 29 | B30: Guilherme Matheus de Oliveira Barros | C30: ATIVO | D30: Financeiro | E30: Analista Financeiro Nível II | F30: Analista Financeiro Nível II | G30: 45677 | BI30: 1000 | BJ30: 3000 | BK30: 3000 | BL30: 3000 | BM30: 3000 | BN30: 3000 | BO30: 3000 | BP30: 4000 | BQ30: 4000 | BR30: 4000 | BS30: 4000 | BT30: 4000 | BU30: 4000 | BV30: 4000 | BW30: 4000 | BX30: =SUM(J30:BW30) -> 51000
A31: 30 | B31: Gustavo Francisco de Souza Almeida | C31: INATIVO | D31: Operacional | E31: Assistente Adm Operacional III | F31: Assistente Adm Operacional III | G31: 45743 | BL31: 2500 | BM31: 2500 | BN31: 2500 | BX31: =SUM(J31:BU31) -> 7500
A32: 31 | B32: Gustavo Fernandes Garcia | C32: INATIVO | D32: Tecnologia | E32: Suporte Nível III | F32: Suporte Nível III | G32: 45414 | H32: 45454 | AZ32: 5350 | BA32: =7000+277.85 -> 7277.85 | BB32: =600+300+2500 -> 3400 | BC32: 2500 | BX32: =SUM(J32:BU32) -> 18527.85
A33: 32 | B33: Kauanny Roza Martinelli | C33: INATIVO | D33: Comercial | E33: Assistente Comercial III | F33: Assistente Comercial III | G33: 45397 | H33: 45652 | AZ33: 1253.33 | BA33: 2470 | BB33: 2470 | BC33: 2470 | BD33: 2470 | BE33: 2470 | BF33: 2470 | BG33: 2470 | BX33: =SUM(J33:BU33) -> 18543.33
A34: 33 | B34: Lais Menezes Santos | C34: INATIVO | D34: Operacional | E34: Assistente Adm Operacional I | F34: Assistente Adm Operacional I | G34: 45566 | BF34: 2500 | BG34: 2500 | BH34: 2500 | BX34: =SUM(J34:BU34) -> 7500
A35: 34 | B35: Leandro Muniz Rodrigues da Silva | C35: INATIVO | D35: Operacional | E35: Prestador Credenciado III | F35: Prestador Credenciado III | G35: 44138 | H35: 44602 | J35: =188.6+39.2 -> 227.8 | K35: 4157.67 | L35: 4157.67 | M35: 4157.67 | N35: 3000 | O35: 3000 | P35: 3000 | Q35: 3000 | R35: =3000+838.72 -> 3838.72 | S35: 3000 | T35: 3000 | U35: 3000 | V35: 3000 | W35: =4275+1630.25 -> 5905.25 | X35: 4275 | Y35: 4275 | AD35: 0 | AE35: 0 | AM35: 0 | AN35: 0 | AO35: 0 | AP35: 0 | BX35: =SUM(J35:BU35) -> 54994.78
A36: 35 | B36: Luciana Serpeloni Borges | C36: INATIVO | D36: Comercial | E36: Assistente Comercial III | F36: Assistente Comercial III | G36: 45750 | BL36: 2763.07 | BM36: 2500 | BN36: 2500 | BO36: 2500 | BP36: 2500 | BQ36: 2500 | BR36: 2500 | BS36: 2500 | BT36: 2500 | BU36: 0 | BX36: =SUM(J36:BV36) -> 22763.07
A37: 36 | B37: Marcelo Mendes de Freitas | C37: INATIVO | D37: Tecnologia | E37: Consultor de Tecnologia | F37: Consultor de Tecnologia | G37: ='CONSOLIDADO ATIVO INATIVO NOVO'!J96 -> 45743 | BE37: 2800 | BF37: 3000 | BG37: 3000 | BH37: 3000 | BI37: 3000 | BJ37: 3000 | BK37: 3000 | BL37: 3000 | BM37: 3500 | BX37: =SUM(J37:BU37) -> 27300
A38: 37 | B38: Mathaus Lukservicius | C38: INATIVO | D38: Operacional | E38: Prestador Credenciado III | F38: Prestador Credenciado I | G38: 44046 | H38: 45506 | M38: 3000 | N38: 3000 | AV38: 3000 | AW38: 3000 | AX38: 3000 | AY38: 3000 | AZ38: 3000 | BA38: 3000 | BB38: 3000 | BC38: 3000 | BD38: 3000 | BX38: =SUM(J38:BU38) -> 33000
A39: 38 | B39: Matheus Cardoso Ferraz Amaro Santos | C39: INATIVO | D39: Tecnologia | E39: Suporte Nível III | F39: Suporte Nível III | G39: 45810 | BN39: 2416.66 | BO39: 2500 | BP39: 2500 | BQ39: 2500 | BR39: 2500 | BS39: 2500 | BT39: 2500 | BU39: 2500 | BX39: =SUM(J39:BV39) -> 19916.66
A40: 39 | B40: Matheus Rodrigues Abrantes de Paula | C40: ATIVO | D40: Jurídico | E40: Analista Juridico | F40: Analista Juridico | G40: 45547 | BE40: 1800 | BF40: 3000 | BG40: 3500 | BH40: 4500 | BI40: 4500 | BJ40: 4500 | BK40: 4500 | BL40: 4500 | BM40: 5103.25 | BN40: 4500 | BO40: 4500 | BP40: 6202.54 | BQ40: 7619.23 | BR40: =4500+757.6 -> 5257.6 | BS40: 5706.73 | BT40: =4200+2576.62 -> 6776.62 | BU40: =5000+2611.71 -> 7611.71 | BV40: =5000+330.58 -> 5330.58 | BW40: =5000+3015.41 -> 8015.41 | BX40: =SUM(J40:BW40) -> 97423.67
A41: 40 | B41: Matheus Prado | C41: INATIVO | D41: Jurídico | E41: Analista Juridico | F41: Analista Juridico | G41: 45863 | BO41: 1200 | BP41: 4487.69 | BQ41: 4834.48 | BR41: 4757.6 | BS41: 4674.75 | BT41: =9600+613 -> 10213 | BU41: 0 | BX41: =SUM(J41:BV41) -> 30167.52
A42: 41 | B42: Marcos Vinicius Fortes | C42: INATIVO | D42: Licitações | E42: Analista de Licitação Nível I / Jurídico | F42: Analista de Licitação Nível I / Jurídico | G42: 44907 | AJ42: 3096.77 | AK42: 4250 | AL42: 4250 | AM42: 4250 | AN42: 4250 | AO42: 4250 | AP42: 4250 | AQ42: 4250 | AR42: 4250 | AS42: 4250 | AT42: 4250 | AU42: 4250 | AV42: 4454.85 | AW42: 4454.85 | AX42: 4454.85 | AY42: 4454.84 | AZ42: 4454.85 | BA42: 4454.85 | BB42: 4454.85 | BC42: =4454.85+100 -> 4554.85 | BD42: 4109.36 | BE42: 4545.85 | BF42: 4109.37 | BG42: 3594.5 | BH42: 6068 | BI42: 4936 | BJ42: 5412 | BK42: 4612.25 | BL42: 5380 | BM42: 6100 | BN42: 6100 | BO42: 2335.5 | BX42: =SUM(J42:BU42) -> 142888.39
A43: 42 | B43: Marcos Antonio de Paula | C43: ATIVO | D43: Financeiro | E43: Gestor Financeiro | F43: Gestor Financeiro | G43: 45796 | BM43: 1950 | BN43: 4500 | BO43: 4500 | BP43: 4500 | BQ43: 4500 | BR43: 4500 | BS43: 5500 | BT43: 5500 | BU43: 5500 | BV43: 5500 | BW43: 5500 | BX43: =SUM(J43:BW43) -> 51950
A44: 43 | B44: Miguel A Gomes Guerrero | C44: INATIVO | D44: Oftamologico | E44: Tecnico Oftamologico | F44: Tecnico Oftamologico | G44: 44256 | L44: 1500 | M44: 700 | N44: 700 | O44: 1000 | P44: 1000 | Q44: 1600 | R44: 1000 | S44: 1300 | T44: 1000 | U44: 1000 | V44: 1000 | W44: 1000 | X44: 1000 | Y44: 1000 | Z44: 1000 | AA44: 1000 | AB44: 1000 | AC44: 1000 | AD44: 1000 | AE44: 1000 | AF44: 1000 | AG44: 1000 | AH44: 1000 | AI44: 1000 | AJ44: 1000 | AK44: 1000 | AL44: 1000 | AM44: 1000 | AN44: 1000 | AO44: 1000 | AP44: 1000 | AQ44: 1000 | AR44: 1000 | AS44: 1000 | AT44: 1000 | AU44: 1000 | AV44: 1000 | AW44: 1000 | AX44: 1000 | AY44: 1000 | AZ44: 1000 | BA44: 1000 | BB44: 1000 | BC44: 1000 | BD44: 1000 | BE44: 1000 | BF44: 1000 | BG44: 1000 | BH44: 1000 | BI44: 1000 | BJ44: 1000 | BK44: 1000 | BL44: 1000 | BX44: =SUM(J44:BU44) -> 53800
A45: 44 | B45: Nicole Fernanda Barbosa | C45: INATIVO | D45: Financeiro | E45: Gestor Financeiro | F45: Gestor Financeiro | G45: 45625 | H45: 38480 | BG45: 200 | BH45: 3000 | BI45: 4000 | BJ45: 4000 | BK45: 4000 | BX45: =SUM(J45:BU45) -> 15200
A46: 45 | B46: Nickolas Alves Custodio | C46: INATIVO | D46: Tecnologia | E46: Suporte Nível III | F46: Gestor de Tecnologia | G46: 45059 | AL46: =80+777.15 -> 857.15 | AM46: 1500 | AN46: 1500 | AO46: 1706.45 | AP46: 2000 | AQ46: 2000 | AR46: 2000 | AS46: 2000 | AT46: 2000 | AU46: 2000 | AV46: 2000 | AW46: 2000 | AX46: 2000 | AY46: 2000 | AZ46: =2000+1000 -> 3000 | BA46: 2500 | BB46: 2500 | BC46: =2500+2500 -> 5000 | BD46: 3000 | BE46: 3500 | BF46: 3500 | BG46: =4000+2000 -> 6000 | BH46: 4000 | BI46: 4000 | BJ46: 4000 | BK46: 4000 | BL46: 4000 | BM46: 4500 | BN46: 4500 | BO46: 4500 | BP46: 4500 | BQ46: 4500 | BR46: 4500 | BX46: =SUM(J46:BU46) -> 101563.6
A47: 46 | B47: Paulo de Tassio | C47: ATIVO | D47: Operacional | E47: Prestador Credenciado III | F47: Prestador Credenciado III | G47: 45691 | BJ47: 4421 | BK47: 4649 | BL47: 4350 | BM47: 4350 | BN47: 4350 | BO47: 4350 | BP47: 4350 | BQ47: 4350 | BR47: 4350 | BS47: 4182.42 | BT47: 3625.38 | BU47: 3143 | BV47: 5347.88 | BW47: =2550+1133.33+100 -> 3783.33 | BX47: =SUM(J47:BW47) -> 59602.01
A48: 47 | B48: Sonia Aparecida Ferreira | C48: INATIVO | D48: LImpeza | E48: Auxiliar de Limpeza | F48: Auxiliar de Limpeza | AI48: =130*3 -> 390 | AJ48: =130+130 -> 260 | AK48: =150+150 -> 300 | AL48: 150 | AM48: 300 | AN48: 300 | AO48: 300 | AP48: 300 | AQ48: 300 | AR48: 300 | AS48: 300 | AT48: 300 | AU48: 300 | AV48: 300 | AW48: 300 | AX48: 300 | AY48: 300 | AZ48: 300 | BX48: =SUM(J48:BU48) -> 5300
A49: 48 | B49: Rafael Luiz Claro | C49: ATIVO | D49: Operacional | E49: Engenheiro Mecânico | F49: Engenheiro Mecânico | G49: 45078 | AE49: 277.19 | AH49: 5004.12 | AI49: 6603.42 | AJ49: 1000 | AK49: 1000 | AL49: 1000 | AM49: 1000 | AN49: 1000 | AO49: 1000 | AP49: 2000 | AQ49: 2000 | AR49: 2000 | AS49: 2000 | AT49: 2000 | AU49: 2000 | AV49: 2000 | AW49: 2000 | AX49: 2000 | AY49: 1000 | AZ49: 1000 | BA49: 4000 | BB49: 1808 | BC49: 1952 | BD49: 1952 | BE49: 2002 | BF49: 1952 | BG49: 1952 | BH49: 1952 | BI49: 1952 | BJ49: 1338 | BK49: 1500 | BL49: 1631.78 | BM49: 1509.5 | BN49: 2048.86 | BO49: 2048.86 | BP49: 2464 | BQ49: 2631.41 | BR49: 2465.5 | BS49: 2857.5 | BT49: 2799.36 | BU49: 2780 | BV49: 2780 | BX49: =SUM(J49:BW49) -> 86261.5
A50: 49 | B50: Raphael Kaych Nunes Câmara | C50: ATIVO | D50: Tecnologia | E50: Suporte Nível III | F50: Surpevisor de TI | G50: 45740 | BL50: 2000 | BM50: 2500 | BN50: 2500 | BO50: 2500 | BP50: 2500 | BQ50: 2500 | BR50: 2500 | BS50: 4000 | BT50: 4000 | BU50: 4000 | BV50: 4000 | BW50: 4000 | BX50: =SUM(J50:BW50) -> 37000
A51: 50 | B51: Renato Ubiratan Pereira Leal Costa | C51: ATIVO | D51: Operacional | E51: Prestador Credenciado III | F51: Prestador Credenciado III | G51: 45028 | AN51: =2707.5+760.98 -> 3468.48 | AO51: 4275 | AP51: 4275 | AQ51: 4275 | AR51: 4275 | AS51: 4275 | AT51: 4275 | AU51: =43.35+4275 -> 4318.35 | AV51: 4347.25 | AW51: 4347.25 | AX51: =3875.53+819.88+471.72 -> 5167.13 | AY51: 4347.25 | AZ51: 4347.25 | BA51: 4347.25 | BB51: 5638.78 | BC51: =4347.25+1000+100+769.5 -> 6216.75 | BD51: 5286.93 | BE51: =4347.25+1000 -> 5347.25 | BF51: 5154.13 | BG51: 3188.7 | BH51: 4679.3 | BI51: 2335 | BJ51: 2525 | BK51: 2285 | BL51: 4416 | BM51: 6436 | BN51: 6436 | BO51: 1792 | BP51: 6250 | BQ51: 6765.2 | BR51: 3113 | BS51: 5450 | BT51: 5700 | BU51: 5773.88 | BV51: 6071.13 | BW51: 3407.5 | BX51: =SUM(J51:BW51) -> 164607.76
A52: 51 | B52: Renan Farias Poli | C52: INATIVO | D52: Operacional | E52: Prestador Credenciado III | F52: Prestador Credenciado III | G52: 45566 | BF52: 4250 | BG52: 3250.51 | BH52: 0 | BX52: =SUM(J52:BU52) -> 7500.51
A53: 52 | B53: Ricardo dos Santos Lima | C53: INATIVO | D53: Operacional | E53: Supervisor Operacional | F53: Gestor Operacional | G53: 45456 | BB53: 3300 | BC53: 5500 | BD53: 5500 | BE53: 5500 | BF53: 5500 | BG53: 7500 | BH53: 5500 | BI53: 5500 | BJ53: 5500 | BK53: 5500 | BL53: 5500 | BM53: 5500 | BN53: 5500 | BO53: 5500 | BP53: 5500 | BQ53: 5500 | BR53: 5500 | BS53: 5500 | BT53: 5500 | BU53: 5500 | BX53: =SUM(J53:BV53) -> 109800
A54: 53 | B54: Richard Salgado Costa | C54: INATIVO | D54: Operacional | E54: Gestor Operacional | F54: Gestor Operacional | G54: 44851 | H54: 45547 | AH54: =483.87+1572.58 -> 2056.45 | AI54: =3250+1000 -> 4250 | AJ54: 4250 | AK54: 5750 | AL54: 6000 | AM54: =6000 -> 6000 | AN54: 6000 | AO54: 6000 | AP54: 6000 | AQ54: 6000 | AR54: 7000 | AS54: 7000 | AT54: 7000 | AU54: 7000 | AV54: 7000 | AW54: 7000 | AX54: 7000 | AY54: 7000 | AZ54: 7000 | BA54: 7000 | BB54: 7000 | BC54: 9543.41 | BD54: 8012.08 | BE54: 11044.08 | BF54: 5712 | BX54: =SUM(J54:BU54) -> 163618.02
A55: 54 | B55: Thiago Mendonça de Castro | C55: INATIVO | D55: Jurídico | E55: Jurídico | F55: Jurídico | AI55: 2000 | AJ55: 2000 | AK55: 2000 | AL55: 3160.61 | AM55: 2000 | AN55: 0 | AO55: 0 | AP55: 0 | BX55: =SUM(J55:BU55) -> 11160.61
A56: 55 | B56: Vicente Quartieri Neto | C56: INATIVO | D56: Operacional | E56: Gestor Operacional | F56: Gestor Operacional | G56: 45597 | H56: 45730 | BG56: 5000 | BH56: 5000 | BI56: 5000 | BJ56: 5000 | BK56: 2333.33 | BX56: =SUM(J56:BU56) -> 22333.33
A57: 56 | B57: Vitor Manoel da Silva Chagas | C57: INATIVO | D57: Financeiro | E57: Assistente Finaceiro Nível III | F57: Assistente Finaceiro Nível III | G57: 45672 | H57: 45767 | BI57: 1250 | BJ57: 2500 | BK57: 2500 | BX57: =SUM(J57:BU57) -> 6250
A58: 57 | B58: William Hauro da Silva | C58: INATIVO | D58: Operacional | E58: Prestador Credenciado III | F58: Prestador Credenciado III | G58: 44586 | H58: 44986 | Y58: 727.1 | Z58: 3220 | AA58: 3220 | AB58: 3220 | AC58: 4275 | AD58: 4275 | AE58: 4275 | AF58: 4275 | AG58: 4208.05 | AH58: 4275 | AI58: 4275 | AJ58: 4275 | AK58: 4275 | AM58: 0 | AN58: 0 | AO58: 0 | AP58: 0 | BX58: =SUM(J58:BU58) -> 48795.15
A59: 58 | B59: Warley Xavier Lopes | C59: INATIVO | D59: Operacional | E59: Prestador Credenciado III | F59: Prestador Credenciado III | G59: 44851 | H59: 45626 | AH59: =483.87+1572.58 -> 2056.45 | AI59: =1000+3250 -> 4250 | AJ59: 4250 | AK59: 4250 | AL59: 4250 | AM59: 4250 | AN59: 4250 | AO59: 4250 | AP59: 4250 | AQ59: 4250 | AR59: 4250 | AS59: 4250 | AT59: 4250 | AU59: 4250 | AV59: 3217 | AW59: 4481.06 | AX59: 4481.06 | AY59: 4481.06 | AZ59: 4481.06 | BA59: 4481.06 | BB59: =4481.06+136.8 -> 4617.86 | BC59: 4797.66 | BD59: 4178.55 | BE59: =4481.06+100 -> 4581.06 | BF59: 4078.55 | BG59: 4078.55 | BX59: =SUM(J59:BU59) -> 109260.98
A60: 59 | B60: Vitor Oliveira Santana | C60: INATIVO | D60: Operacional | E60: Prestador Credenciado III | F60: Prestador Credenciado III | G60: 45870 | BP60: 2225 | BQ60: 4250 | BR60: 4250 | BX60: =SUM(J60:BU60) -> 10725
A61: 60 | B61: Walter Pozzeti Junior | C61: ATIVO | D61: Tecnologia | E61: Marketing | F61: Marketing | G61: 45382 | BL61: 3616.67 | BM61: 3500 | BN61: 3500 | BO61: 3500 | BP61: 3500 | BQ61: 3500 | BR61: 3500 | BS61: 3500 | BT61: 3500 | BU61: 3500 | BV61: 3500 | BW61: 3500 | BX61: =SUM(J61:BW61) -> 42116.67
A62: 61 | B62: Willian Camara | C62: ATIVO | D62: Tecnologia | E62: Suporte Nível III | F62: Suporte Nível II | G62: 45566 | BF62: 2500 | BG62: 2500 | BH62: 2500 | BI62: 4500 | BJ62: 4500 | BK62: 4500 | BL62: 3500 | BM62: 3500 | BN62: 3500 | BO62: 3500 | BP62: 3500 | BQ62: 3500 | BR62: 4500 | BS62: 4500 | BT62: 4500 | BU62: 4500 | BV62: 4500 | BW62: 4500 | BX62: =SUM(J62:BW62) -> 69000
A63: 62 | B63: Mario Renato Cerqueira Castro Cohen | C63: INATIVO | D63: Operacional | E63: Assistente Administrato Nível III | F63: Assistente Administrato Nível III | G63: 45901 | H63: 45950 | BQ63: 3000 | BX63: =SUM(J63:BU63) -> 3000
A64: 63 | B64: Josivan de Lima Silva | C64: ATIVO | D64: Operacional | E64: Prestador Credenciado III | F64: Prestador Credenciado III | G64: 45950 | BR64: 2100 | BS64: 4903.75 | BT64: 5350 | BU64: 5142.5 | BV64: 5637.5 | BW64: =4470.88+750+100 -> 5320.88 | BX64: =SUM(J64:BW64) -> 28454.63
A65: 64 | B65: Braian Castro Furquim da Mota | C65: ATIVO | D65: Operacional | E65: Prestador Credenciado III | F65: Supervisor Operacional | G65: 45940 | BR65: 3850 | BS65: 5350 | BT65: 5714.8 | BU65: 4957.5 | BV65: 5053.25 | BW65: =4500+900+500 -> 5900 | BX65: =SUM(J65:BW65) -> 30825.55
A66: 65 | B66: Leandro Lourenci Cunha | C66: ATIVO | D66: Operacional | E66: Prestador Credenciado III | F66: Prestador Credenciado III | G66: 45957 | BR66: 602 | BS66: 4489.75 | BT66: 5350 | BU66: 3449 | BV66: 5068.13 | BW66: =3888.75+750+100 -> 4738.75 | BX66: =SUM(J66:BW66) -> 23697.63
A67: 66 | B67: Michelle Guerra | C67: INATIVO | D67: Operacional | E67: Gestor de RH | F67: Gestor de RH | G67: 45943 | BR67: 5000 | BX67: =SUM(J67:BU67) -> 5000
A68: 67 | B68: Marcos Caetano do Nascimento | C68: ATIVO | D68: Jurídico | E68: Jurídico | F68: Jurídico | G68: 46055 | BV68: 4000 | BW68: 4000 | BX68: =SUM(J68:BW68) -> 8000
A69: 68 | B69: Paulo Mesquita da Cunha | C69: ATIVO | D69: Jurídico | E69: Jurídico | F69: Jurídico | G69: 46055 | BV69: 4000 | BW69: 4000 | BX69: =SUM(J69:BW69) -> 8000
A70: 69 | B70: Melissa Leite Machado | C70: ATIVO | D70: Financeiro | E70: Auxiliar Financeiro | F70: Auxiliar Financeiro | G70: 46055 | BU70: 2500 | BV70: 2500 | BW70: 2500 | BX70: =SUM(J70:BW70) -> 7500
A71: 70 | B71: Cleiton Martins Ornellas | C71: ATIVO | D71: Operacional | E71: Prestador Credenciado II | F71: Prestador Credenciado II | G71: 46049 | BV71: 6350 | BW71: 6350 | BX71: =SUM(J71:BW71) -> 12700
A72: 71 | B72: Jose Roberto de Lira | C72: ATIVO | D72: Operacional | E72: Prestador Credenciado III | F72: Prestador Credenciado III | G72: 45964 | BT72: 5350 | BU72: 5350 | BV72: 5350 | BW72: 5350 | BX72: =SUM(J72:BW72) -> 21400
A73: 72 | B73: Carlos Henrique Santos | C73: ATIVO | D73: Operacional | E73: Prestador Credenciado III | F73: Prestador Credenciado III | G73: 45931 | BU73: 5350 | BV73: 5000.13 | BW73: =4228.75+100+750 -> 5078.75 | BX73: =SUM(J73:BW73) -> 15428.88
A74: 73 | B74: Danyelle Vieira da Cunha | C74: ATIVO | D74: Tecnologia | E74: Marketing | F74: Marketing | G74: 45901 | BR74: 2500 | BS74: 2500 | BT74: 2500 | BU74: 2750 | BV74: 2500 | BW74: 3000 | BX74: =SUM(J74:BW74) -> 15750
A75: 74 | B75: Sandro Ribeiro da Silva | C75: ATIVO | D75: Operacional | E75: Prestador Credenciado III | F75: Prestador Credenciado III | G75: 45938 | BS75: 5350 | BT75: 5350 | BU75: 5350 | BV75: 5350 | BW75: =4201.13+100+460.8+750 -> 5511.93 | BX75: =SUM(J75:BW75) -> 26911.93
A76: 75 | B76: Marco Aurelio Dias Ferreira do Nascimento | C76: ATIVO | D76: Operacional | E76: Prestador Credenciado III | F76: Prestador Credenciado III | G76: 46071 | BV76: 1964.28 | BW76: 5000 | BX76: =SUM(J76:BW76) -> 6964.28
A77: 76 | B77: Flavio de Olveira Fontenelle | C77: ATIVO | D77: Operacional | E77: Prestador Credenciado III | F77: Prestador Credenciado III | G77: 46083 | BW77: 5000 | BX77: =SUM(J77:BW77) -> 5000
A78: 77 | B78: Renan Miranda | C78: ATIVO | D78: Operacional | E78: Prestador Credenciado III | F78: Prestador Credenciado III | G78: 46083 | BW78: =4250+100 -> 4350 | BX78: =SUM(J78:BW78) -> 4350
A79: 78 | B79: Cristiane Cavalcanti da Silva Sena | C79: ATIVO | D79: Recursos Humanos | E79: Analista de Recursos Humanos III | F79: Analista de Recursos Humanos III | G79: 46007 | BT79: 2152.22 | BU79: 4035.43 | BV79: 4035.43 | BW79: 4035.43 | BX79: =SUM(J79:BW79) -> 14258.51
A80: 78 | B80: Matheus Ignacchiti Franca | C80: ATIVO | D80: Operacional | E80: Aux. Administrativo III | F80: Aux. Administrativo III | G80: 46006 | BT80: 1250 | BU80: 2500 | BV80: 2500 | BW80: 2500 | BX80: =SUM(J80:BW80) -> 8750
A81: 79 | B81: Felipe Rodrigues Prado | C81: ATIVO | D81: Tecnologia | E81: Suporte Nível III | F81: Suporte Nível III | G81: 46007 | BT81: 1250 | BU81: 2500 | BV81: 2500 | BW81: 2500 | BX81: =SUM(J81:BW81) -> 8750
B83: Valores totais ao mês | J83: =SUM(J2:J59) -> 2163.28 | K83: =SUM(K2:K59) -> 17791.69 | L83: =SUM(L2:L59) -> 19445.68 | M83: =SUM(M2:M59) -> 21757.58 | N83: =SUM(N2:N59) -> 20603.4 | O83: =SUM(O2:O59) -> 19101.15 | P83: =SUM(P2:P59) -> 20201.02 | Q83: =SUM(Q2:Q59) -> 21025.59 | ... BE83: =SUM(BE2:BE59) -> 89027.49 | BF83: =SUM(BF3:BF62) -> 100670.37 | BG83: =SUM(BG3:BG62) -> 89174.71 | BH83: =SUM(BH3:BH62) -> 89393.65 | BI83: =SUM(BI3:BI62) -> 77285.1 | BJ83: =SUM(BJ2:BJ67) -> 82892.2 | BK83: =SUM(BK2:BK67) -> 82441.63 | BL83: =SUM(BL2:BL67) -> 96081.12 | BM83: =SUM(BM2:BM67) -> 104345.56 | BN83: =SUM(BN2:BN67) -> 107500.81 | BO83: =SUM(BO2:BO67) -> 81646.4 | BP83: =SUM(BP2:BP67) -> 100752.5 | BQ83: =SUM(BQ2:BQ67) -> 108737.67 | ... BX83: =SUM(BX2:BX67) -> 3720589.5

Sheet CLT NOVA
A1: ITEM | B1: FUNCIONÁRIOS | C1: STATUS | D1: SETOR | E1: CARGO INICIAL | F1: ÚLTIMO CARGO | G1: DATA INICIAL | H1: DESLIGAMENTO | I1: Ciclo do mês | J1: 44105 | K1: 44136 | L1: 44166 | M1: 44197 | N1: 44228 | O1: 44256 | P1: 44287 | Q1: 44317 | R1: 44348 | S1: 44378 | T1: 44409 | U1: 44440 | V1: 44470 | W1: 44501 | X1: 44531 | Y1: 44562 | Z1: 44593 | AA1: 44621 | AB1: 44652 | AC1: 44682 | AD1: 44713 | AE1: 44743 | AF1: 44774 | AG1: 44805 | AH1: 44835 | AI1: 44866 | AJ1: 44896 | AK1: 44927 | AL1: 44958 | AM1: 44986 | AN1: 45017 | AO1: 45047 | AP1: 45078 | AQ1: 45108 | AR1: 45139 | AS1: 45170 | AT1: 45200 | AU1: 45231 | AV1: 45261 | AW1: 45292 | AX1: 45323 | AY1: 45352 | AZ1: 45383 | BA1: 45413 | BB1: 45444 | BC1: 45474 | BD1: 45505 | BE1: 45536 | BF1: 45566 | BG1: 45597 | BH1: 45627 | BI1: 45658 | BJ1: 45689 | BK1: 45717 | BL1: 45748 | BM1: 45778 | BN1: 45809 | BO1: 45839 | BP1: 45870 | BQ1: 45901 | BR1: 45931 | BS1: 45962 | BT1: 45992 | BU1: 46023 | BV1: 46054 | BW1: 46082 | BX1: Total
A2: 1 | B2: Andrea Aparecida de Oliveira Ferreira | C2: Ativo | D2: Rancho | E2: Auxiliar de Serviços Gerais | F2: Auxiliar de Serviços Gerais | G2: ='CONSOLIDADO ATIVO INATIVO NOVO'!J7 -> 44972 | I2: Pagamento sem holerite
I3: Holerite | AU3: 61.66 | AV3: 1849.81 | AW3: 1849.81 | AX3: 1849.81 | AY3: 1849.81 | AZ3: 1849.81 | BA3: 1849.81 | BB3: =1849.81+100 -> 1949.81 | BC3: 1849.81 | BD3: 1849.81 | BE3: 1849.81 | BF3: 1849.81 | BG3: 1849.81 | BH3: 1849.81 | BI3: 1849.81 | BJ3: 1849.81 | BK3: 1849.81 | BL3: 1849.81 | BM3: 1849.81 | BN3: 1849.81 | BO3: 1849.81 | BP3: 1849.81 | BQ3: 1849.81 | BR3: 1849.81 | BS3: 3158.4 | BT3: 1849.81 | BU3: 1849.81 | BV3: 1849.81 | BW3: 1849.81
I4: Adiantamento
I5: Hora extra + D.S.R | AX5: 248.87 | BB5: =826.74+165.35 -> 992.09 | BK5: =1518.4+303.68 -> 1822.08 | BW5: =185.96+929.78 -> 1115.74
I6: Adicional noturno 20% +D.S.R | BF6: 1063.37
I7: VR
I8: VT | AU8: =4.8*2 -> 9.6 | AV8: 240 | AW8: 249.6 | AX8: 240 | AY8: 240 | AZ8: 249.6 | BA8: 249.6 | BB8: 240 | BC8: 259.2 | BD8: 240 | BE8: 230.4 | BF8: 240 | BG8: 240 | BH8: 240 | BI8: 249.6 | BJ8: 230.4 | BK8: 249.6 | BL8: 252 | BM8: 273 | BN8: 252 | BO8: 273 | BP8: 262.5 | BQ8: 273 | BR8: 283.5 | BS8: 241.5 | BT8: 241.5 | BU8: 273.5 | BV8: 252 | BW8: 231
I9: Ajuda de custo
I10: Cesta | AV10: 500 | AW10: 500 | AX10: 500 | AY10: 1000 | AZ10: 500 | BA10: 500 | BB10: 500 | BC10: 500 | BD10: 500 | BE10: 500 | BF10: 500 | BG10: 500 | BH10: 500 | BI10: 500 | BJ10: 500 | BK10: 500 | BL10: 500 | BM10: 500 | BN10: 500 | BO10: 500 | BP10: 500 | BQ10: 500 | BR10: 500 | BS10: 500 | BT10: 500 | BU10: 500 | BV10: 500 | BW10: 500
I11: Bonificação | BH11: 2000
I12: Comissões Rancho
I13: Férias
I14: Rescisão
I15: 13º | AV15: 142.59
I16: Descontos | AU16: 8.32 | AV16: 257.67 | AW16: 284.04 | AX16: 274.99 | AY16: =145.3+27.75+110.99 -> 284.04 | AZ16: 256.29 | BA16: 256.29 | BB16: =239.84+110.99 -> 350.83 | BC16: 256.29 | BD16: 256.29 | BE16: 256.29 | BF16: 359.39 | BG16: 256.29 | BH16: 256.29 | BI16: 254.7 | BJ16: 254.7 | BK16: 529.64 | BL16: 254.7 | BM16: 254.7 | BN16: 254.7 | BO16: 254.7 | BP16: 254.7 | BQ16: 254.7 | BR16: 254.7 | BS16: 1250.12 | BT16: 289.39 | BU16: 289.39 | BV16: 289.39 | BW16: =1095.36-739.92 -> 355.44
J17: =SUM(J2:J15)-J16 -> 0 | K17: =SUM(K2:K15)-K16 -> 0 | L17: =SUM(L2:L15)-L16 -> 0 | M17: =SUM(M2:M15)-M16 -> 0 | N17: =SUM(N2:N15)-N16 -> 0 | O17: =SUM(O2:O15)-O16 -> 0 | P17: =SUM(P2:P15)-P16 -> 0 | Q17: =SUM(Q2:Q15)-Q16 -> 0 | ... BE17: =SUM(BE2:BE15)-BE16 -> 2323.92 | BF17: =SUM(BF3+BF6+BF8+BF10)-BF16 -> 3293.79 | BG17: =SUM(BG3+BG6+BG8+BG10)-BG16 -> 2333.52 | BH17: =SUM(BH3+BH6+BH8+BH10+BH11)-BH16 -> 4333.52 | BI17: =BI3+BI8+BI10-BI16 -> 2344.71 | BJ17: =BJ3+BJ8+BJ10-BJ16 -> 2325.51 | BK17: =BK3+BK5+BK8+BK10-BK16 -> 3891.85 | BL17: =BL3+BL8+BL10-BL16 -> 2347.11 | BM17: =BM3+BM8+BM10-BM16 -> 2368.11 | BN17: =BN3+BN8+BN10-BN16 -> 2347.11 | BO17: =BO3+BO8+BO10-BO16 -> 2368.11 | BP17: =BP3+BP8+BP10-BP16 -> 2357.61 | BQ17: =BQ3+BQ8+BQ10-BQ16 -> 2368.11 | BR17: =BR3+BR8+BR10-BR16 -> 2378.61 | BS17: =BS3+BS8+BS10-BS16 -> 2649.78 | ... BV17: =BV3+BV8+BV10-BV16 -> 2312.42 | BW17: =BW3+BW5+BW8+BW10-BW16 -> 3341.11 | BX17: =SUM(J17:BW17) -> 73246.79
A18: ITEM | B18: FUNCIONÁRIOS | C18: STATUS | D18: SETOR | E18: CARGO INICIAL | F18: ÚLTIMO CARGO | G18: DATA INICIAL | H18: DESLIGAMENTO | I18: Ciclo do mês | J18: 44105 | K18: 44136 | L18: 44166 | M18: 44197 | N18: 44228 | O18: 44256 | P18: 44287 | Q18: 44317 | R18: 44348 | S18: 44378 | T18: 44409 | U18: 44440 | V18: 44470 | W18: 44501 | X18: 44531 | Y18: 44562 | Z18: 44593 | AA18: 44621 | AB18: 44652 | AC18: 44682 | AD18: 44713 | AE18: 44743 | AF18: 44774 | AG18: 44805 | AH18: 44835 | AI18: 44866 | AJ18: 44896 | AK18: 44927 | AL18: 44958 | AM18: 44986 | AN18: 45017 | AO18: 45047 | AP18: 45078 | AQ18: 45108 | AR18: 45139 | AS18: 45170 | AT18: 45200 | AU18: 45231 | AV18: 45261 | AW18: 45292 | AX18: 45323 | AY18: 45352 | AZ18: 45383 | BA18: 45413 | BB18: 45444 | BC18: 45474 | BD18: 45505 | BE18: 45536 | BF18: 45566 | BG18: 45597 | BH18: 45627 | BI18: 45658 | BX18: Total
A19: 2 | B19: Adolfo Gabriel Pereira | C19: Ativo | D19: Operacional | E19: Oficial de Serviços Gerais | F19: Oficial de Serviços Gerais | G19: ='CONSOLIDADO ATIVO INATIVO NOVO'!J2 -> 44270 | H19: 45664 | I19: Pagamento sem holerite
I20: Holerite | AV20: 1664.83 | AW20: 1849.81 | AX20: 1849.81 | AY20: 1849.81 | AZ20: 1849.81 | BA20: 1849.81 | BB20: 1849.81 | BG20: 1664.83 | BH20: 1849.81
I21: Adiantamento
I22: Hora extra + D.S.R
I23: Adicional noturno 20% +D.S.R
I24: VR
I25: VT
I26: Ajuda de custo | AV26: =90.3+435.34 -> 525.64 | AW26: 513.51 | AX26: 522.53 | AY26: 534.61 | AZ26: 532.01 | BA26: 533.03 | BB26: 532.99 | BC26: 541.49 | BG26: 288 | BH26: 490.01
I27: Cesta
I28: Comissões Rancho
I29: Férias
I30: Rescisão | BC30: 3603.58 | BI30: 44.12
I31: 13º | AV31: 142.59
I32: Descontos | AV32: 130.03 | AW32: 173.05 | AX32: 145.3 | AY32: =145.3+27.75 -> 173.05 | AZ32: 145.3 | BA32: 145.3 | BB32: 145.3 | BC32: 2232.99 | BG32: 240.87 | BH32: 652.05
J33: =SUM(J19:J31)-J32 -> 0 | K33: =SUM(K19:K31)-K32 -> 0 | L33: =SUM(L19:L31)-L32 -> 0 | M33: =SUM(M19:M31)-M32 -> 0 | N33: =SUM(N19:N31)-N32 -> 0 | O33: =SUM(O19:O31)-O32 -> 0 | P33: =SUM(P19:P31)-P32 -> 0 | Q33: =SUM(Q19:Q31)-Q32 -> 0 | ... BC33: =SUM(BC19:BC31)-BC32 -> 1912.08 | BG33: =SUM(BG19:BG31)-BG32 -> 1711.96 | BH33: =SUM(BH19:BH31)-BH32 -> 1687.77 | BI33: 44.12 | BX33: =SUM(J33:BJ33) -> 20899.2
A34: ITEM | B34: FUNCIONÁRIOS | C34: STATUS | D34: SETOR | E34: CARGO INICIAL | F34: ÚLTIMO CARGO | G34: DATA INICIAL | H34: DESLIGAMENTO | I34: Ciclo do mês | J34: 44105 | K34: 44136 | L34: 44166 | M34: 44197 | N34: 44228 | O34: 44256 | P34: 44287 | Q34: 44317 | R34: 44348 | S34: 44378 | T34: 44409 | U34: 44440 | V34: 44470 | W34: 44501 | X34: 44531 | Y34: 44562 | Z34: 44593 | AA34: 44621 | AB34: 44652 | AC34: 44682 | AD34: 44713 | AE34: 44743 | AF34: 44774 | AG34: 44805 | AH34: 44835 | AI34: 44866 | AJ34: 44896 | AK34: 44927 | AL34: 44958 | AM34: 44986 | AN34: 45017 | AO34: 45047 | AP34: 45078 | AQ34: 45108 | AR34: 45139 | AS34: 45170 | AT34: 45200 | AU34: 45231 | AV34: 45261 | AW34: 45292 | AX34: 45323 | AY34: 45352 | AZ34: 45383 | BA34: 45413 | BB34: 45444 | BC34: 45474 | BD34: 45505 | BE34: 45536 | BF34: 45566 | BG34: 45597 | BH34: 45627 | BI34: 45658 | BJ34: 45689 | BX34: Total
A35: 3 | B35: Alan Deyvid de Siqueira | C35: Inativo | D35: Operacional | E35: Oficial de Serviços Gerais | F35: Oficial de Serviços Gerais | G35: ='CONSOLIDADO ATIVO INATIVO NOVO'!J4 -> 44256 | I35: Pagamento sem holerite
I36: Holerite | AW36: 1233.21 | AX36: 1849.81 | AY36: 1849.81 | AZ36: 1999.81 | BA36: 1849.71 | BB36: 1849.81 | BC36: 1849.81 | BD36: 1849.81
I37: Adiantamento
I38: Hora extra + D.S.R | AX38: 58.96 | AZ38: 0.52 | BB38: =170.14+34.03 -> 204.17
I39: Adicional noturno 20% +D.S.R
I40: VR
I41: VT
I42: Ajuda de custo | AW42: 564.59 | AX42: 796.51 | AY42: 797.52 | AZ42: 820.01 | BA42: 822.11 | BB42: 795.5 | BC42: 843.51 | BD42: 844.54
I43: Cesta
I44: Comissões Rancho
I45: Férias
I46: Rescisão | BE46: 5131.76
I47: 13º
I48: Descontos | AW48: =92.49+27.75 -> 120.24 | AX48: 150.6 | AY48: 173.05 | AZ48: 145.34 | BA48: 145.3 | BB48: 163.67 | BC48: 145.3 | BD48: 145.3 | BE48: 250.79
J49: =SUM(J35:J47)-J48 -> 0 | K49: =SUM(K35:K47)-K48 -> 0 | L49: =SUM(L35:L47)-L48 -> 0 | M49: =SUM(M35:M47)-M48 -> 0 | N49: =SUM(N35:N47)-N48 -> 0 | O49: =SUM(O35:O47)-O48 -> 0 | P49: =SUM(P35:P47)-P48 -> 0 | Q49: =SUM(Q35:Q47)-Q48 -> 0 | ... BD49: =SUM(BD35:BD47)-BD48 -> 2549.05 | BE49: =BE46-BE48 -> 4880.97 | BX49: =SUM(J49:BJ49) -> 24571.89
A50: ITEM | B50: FUNCIONÁRIOS | C50: STATUS | D50: SETOR | E50: CARGO INICIAL | F50: ÚLTIMO CARGO | G50: DATA INICIAL | H50: DESLIGAMENTO | I50: Ciclo do mês | J50: 44105 | K50: 44136 | L50: 44166 | M50: 44197 | N50: 44228 | O50: 44256 | P50: 44287 | Q50: 44317 | R50: 44348 | S50: 44378 | T50: 44409 | U50: 44440 | V50: 44470 | W50: 44501 | X50: 44531 | Y50: 44562 | Z50: 44593 | AA50: 44621 | AB50: 44652 | AC50: 44682 | AD50: 44713 | AE50: 44743 | AF50: 44774 | AG50: 44805 | AH50: 44835 | AI50: 44866 | AJ50: 44896 | AK50: 44927 | AL50: 44958 | AM50: 44986 | AN50: 45017 | AO50: 45047 | AP50: 45078 | AQ50: 45108 | AR50: 45139 | AS50: 45170 | AT50: 45200 | AU50: 45231 | AV50: 45261 | AW50: 45292 | AX50: 45323 | AY50: 45352 | AZ50: 45383 | BA50: 45413 | BB50: 45444 | BC50: 45474 | BD50: 45505 | BE50: 45536 | BF50: 45566 | BG50: 45597 | BH50: 45627 | BI50: 45658 | BJ50: 45689 | BX50: Total
A51: 4 | B51: Alan Lima Vasconcelos | C51: Inativo | D51: Operacional | E51: Oficial de Serviços Gerais | F51: Oficial de Serviços Gerais | G51: ='CONSOLIDADO ATIVO INATIVO NOVO'!J4 -> 44256 | H51: ='CONSOLIDADO ATIVO INATIVO NOVO'!K4 -> 45778 | I51: Pagamento sem holerite
I52: Holerite | BE52: 431.62
I53: Adiantamento
I54: Hora extra + D.S.R
I55: Adicional noturno 20% +D.S.R
I56: VR
I57: VT
I58: Ajuda de custo | BE58: 181.37
I59: Cesta
I60: Comissões Rancho
I61: Férias
I62: Rescisão
I63: 13º
I64: Descontos | BE64: 32.37
J65: =SUM(J51:J63)-J64 -> 0 | K65: =SUM(K51:K63)-K64 -> 0 | L65: =SUM(L51:L63)-L64 -> 0 | M65: =SUM(M51:M63)-M64 -> 0 | N65: =SUM(N51:N63)-N64 -> 0 | O65: =SUM(O51:O63)-O64 -> 0 | P65: =SUM(P51:P63)-P64 -> 0 | Q65: =SUM(Q51:Q63)-Q64 -> 0 | ... BD65: =SUM(BD51:BD63)-BD64 -> 0 | BE65: =SUM(BE52:BE58)-BE64 -> 580.62 | BX65: =BE65 -> 580.62
A66: ITEM | B66: FUNCIONÁRIOS | C66: STATUS | D66: SETOR | E66: CARGO INICIAL | F66: ÚLTIMO CARGO | G66: DATA INICIAL | H66: DESLIGAMENTO | I66: Ciclo do mês | J66: 44105 | K66: 44136 | L66: 44166 | M66: 44197 | N66: 44228 | O66: 44256 | P66: 44287 | Q66: 44317 | R66: 44348 | S66: 44378 | T66: 44409 | U66: 44440 | V66: 44470 | W66: 44501 | X66: 44531 | Y66: 44562 | Z66: 44593 | AA66: 44621 | AB66: 44652 | AC66: 44682 | AD66: 44713 | AE66: 44743 | AF66: 44774 | AG66: 44805 | AH66: 44835 | AI66: 44866 | AJ66: 44896 | AK66: 44927 | AL66: 44958 | AM66: 44986 | AN66: 45017 | AO66: 45047 | AP66: 45078 | AQ66: 45108 | AR66: 45139 | AS66: 45170 | AT66: 45200 | AU66: 45231 | AV66: 45261 | AW66: 45292 | AX66: 45323 | AY66: 45352 | AZ66: 45383 | BA66: 45413 | BB66: 45444 | BC66: 45474 | BD66: 45505 | BE66: 45536 | BF66: 45566 | BG66: 45597 | BH66: 45627 | BI66: 45658 | BJ66: 45689 | BX66: Total
A67: 5 | B67: Ana Lucia de Lima | C67: Inativo | D67: Limpeza | E67: Auxiliar de Serviços Gerais | F67: Auxiliar de Serviços Gerais | G67: ='CONSOLIDADO ATIVO INATIVO NOVO'!J6 -> 44046 | H67: ='CONSOLIDADO ATIVO INATIVO NOVO'!K6 -> 45506 | I67: Pagamento sem holerite | R67: 150
I68: Holerite | P68: =465.42+20.51 -> 485.93 | Q68: 1214.82 | R68: 1214.82 | S68: 1214.82 | T68: 1738.17 | U68: 1214.82 | V68: 1214.82 | W68: 1214.82 | X68: 1214.82 | Y68: 1578.6 | Z68: 1635.07 | AA68: 1635.07 | AB68: 1635.07 | AC68: 1635.07 | AD68: 1578.6 | AE68: 1635.07 | AF68: 1635.07 | AG68: 1635.07 | AH68: 1708.83 | AI68: 1708.83 | AJ68: 1845.54 | AK68: 1950.93 | AL68: 1708.83 | AM68: =1082.26+59.82+299.05+99.68+657.91+219.3 -> 2418.02 | AN68: 1768.65 | AO68: 1768.65 | AP68: 1708.83
I69: Adiantamento | Z69: 300 | AC69: 1200 | AE69: 400 | AG69: 600 | AK69: 500 | AL69: 200 | AN69: 10.4 | AO69: 1200
I70: Hora extra + D.S.R | Y70: =134.22+33.56 -> 167.78 | AD70: =551.61+110.32 -> 661.93 | AH70: =28.02+112.08 -> 140.1 | AL70: =18.3+118.96 -> 137.26 | AP70: =105.98+529.89 -> 635.87
I71: Adicional noturno 20% +D.S.R
I72: VR
I73: VT | P73: 102.3 | Q73: 232.5 | R73: 251.1 | S73: 241.8 | T73: 241.8 | U73: 232.5 | V73: 232.5 | W73: 232.5 | X73: 223.2 | Y73: 232.5 | Z73: 223.2 | AA73: 263.1 | AB73: 249.6 | AC73: 249.6 | AD73: 249.6 | AE73: 249.6 | AF73: 259.2 | AG73: 240 | AH73: 240 | AI73: 230.4 | AJ73: 259.2 | AK73: 192 | AL73: 230.4 | AM73: 259.2 | AN73: 220.8 | AO73: 249.6 | AP73: 240 | AQ73: 249.6
I74: Ajuda de custo
I75: Cesta | Q75: 380 | R75: 400 | S75: 400 | T75: 400 | U75: 400 | V75: 800 | W75: 400 | X75: 400 | Y75: 400 | Z75: 400 | AA75: 400 | AB75: 400 | AC75: 400 | AD75: 400 | AE75: 400 | AF75: 400 | AG75: 400 | AH75: 400 | AI75: 400 | AJ75: 400 | AK75: 400 | AL75: 400 | AM75: 400 | AN75: 400 | AO75: 400 | AP75: 400 | AQ75: 400
I76: Comissões Rancho
I77: Férias | AJ77: 1032.72 | AM77: 1210.15
I78: Rescisão | AQ78: 2284.83
I79: 13º | W79: 387.85 | X79: 387.85 | AI79: 854.42 | AJ79: 718.8
I80: Descontos | P80: 34.9 | Q80: =88.21+273.34 -> 361.55 | R80: =88.21+273.34 -> 361.55 | S80: =88.21+220 -> 308.21 | T80: =139.93+220 -> 359.93 | U80: =88.21 -> 88.21 | V80: 88.21 | W80: 88.21 | X80: =58.17+88.21+69.81 -> 216.19 | Y80: =138.99+94.72 -> 233.71 | Z80: =123.89+94.72 -> 218.61 | AA80: =123.89+94.72 -> 218.61 | AB80: =123.89+94.72 -> 218.61 | AC80: =123.89+94.72+400 -> 618.61 | AD80: =183.46+94.72+400 -> 678.18 | AE80: =123.89+94.72+800 -> 1018.61 | AF80: =123.89+94.72 -> 218.61 | AG80: 518.61 | AH80: =148.22+102.53+300 -> 550.75 | AI80: =102.53+135.61 -> 238.14 | AJ80: 672.53 | AK80: 915.97 | AL80: =146.61+102.53+100+200 -> 549.14 | AM80: =91.03+64.94+65.79+100+1210.15 -> 1531.91 | AN80: =134.26+102.53+100+10.4 -> 347.19 | AO80: =133.99+102.53+100+240 -> 576.52 | AP80: =191.22+102.53+960 -> 1253.75
J81: =SUM(J67:J79)-J80 -> 0 | K81: =SUM(K67:K79)-K80 -> 0 | L81: =SUM(L67:L79)-L80 -> 0 | M81: =SUM(M67:M79)-M80 -> 0 | N81: =SUM(N67:N79)-N80 -> 0 | O81: =SUM(O67:O79)-O80 -> 0 | P81: =SUM(P67:P79)-P80 -> 553.33 | Q81: =SUM(Q67:Q79)-Q80 -> 1465.77 | ... BD81: =SUM(BD67:BD79)-BD80 -> 0 | BX81: =SUM(K81:AY81) -> 60370.38
A82: ITEM | B82: FUNCIONÁRIOS | C82: STATUS | D82: SETOR | E82: CARGO INICIAL | F82: ÚLTIMO CARGO | G82: DATA INICIAL | H82: DESLIGAMENTO | I82: Ciclo do mês | J82: 44105 | K82: 44136 | L82: 44166 | M82: 44197 | N82: 44228 | O82: 44256 | P82: 44287 | Q82: 44317 | R82: 44348 | S82: 44378 | T82: 44409 | U82: 44440 | V82: 44470 | W82: 44501 | X82: 44531 | Y82: 44562 | Z82: 44593 | AA82: 44621 | AB82: 44652 | AC82: 44682 | AD82: 44713 | AE82: 44743 | AF82: 44774 | AG82: 44805 | AH82: 44835 | AI82: 44866 | AJ82: 44896 | AK82: 44927 | AL82: 44958 | AM82: 44986 | AN82: 45017 | AO82: 45047 | AP82: 45078 | AQ82: 45108 | AR82: 45139 | AS82: 45170 | AT82: 45200 | AU82: 45231 | AV82: 45261 | AW82: 45292 | AX82: 45323 | AY82: 45352 | AZ82: 45383 | BA82: 45413 | BB82: 45444 | BC82: 45474 | BD82: 45505 | BE82: 45536 | BF82: 45566 | BG82: 45597 | BH82: 45627 | BI82: 45658 | BJ82: 45689 | BX82: Total
A83: 6 | B83: Ariane Amarante | C83: Inativo | D83: Financeiro | E83: Auxiliar Administrativo Financeiro | F83: Auxiliar Administrativo Financeiro | G83: ='CONSOLIDADO ATIVO INATIVO NOVO'!J9 -> 45028 | H83: ='CONSOLIDADO ATIVO INATIVO NOVO'!K9 -> 0 | I83: Pagamento sem holerite
I84: Holerite | AS84: 1056.26
I85: Adiantamento
I86: Hora extra + D.S.R
I87: Adicional noturno 20% +D.S.R
I88: VR
I89: VT
I90: Ajuda de custo | AS90: 266.02 | AT90: 427.37
I91: Cesta
I92: Comissões Rancho
I93: Férias
I94: Rescisão | AT94: =2196.35+156.56 -> 2352.91
I95: 13º
I96: Descontos | AS96: 79.21
J97: =SUM(J83:J95)-J96 -> 0 | K97: =SUM(K83:K95)-K96 -> 0 | L97: =SUM(L83:L95)-L96 -> 0 | M97: =SUM(M83:M95)-M96 -> 0 | N97: =SUM(N83:N95)-N96 -> 0 | O97: =SUM(O83:O95)-O96 -> 0 | P97: =SUM(P83:P95)-P96 -> 0 | Q97: =SUM(Q83:Q95)-Q96 -> 0 | ... BD97: =SUM(BD83:BD95)-BD96 -> 0 | BX97: =SUM(K97:AY97) -> 4023.35
A98: ITEM | B98: FUNCIONÁRIOS | C98: STATUS | D98: SETOR | E98: CARGO INICIAL | F98: ÚLTIMO CARGO | G98: DATA INICIAL | H98: DESLIGAMENTO | I98: Ciclo do mês | J98: 44105 | K98: 44136 | L98: 44166 | M98: 44197 | N98: 44228 | O98: 44256 | P98: 44287 | Q98: 44317 | R98: 44348 | S98: 44378 | T98: 44409 | U98: 44440 | V98: 44470 | W98: 44501 | X98: 44531 | Y98: 44562 | Z98: 44593 | AA98: 44621 | AB98: 44652 | AC98: 44682 | AD98: 44713 | AE98: 44743 | AF98: 44774 | AG98: 44805 | AH98: 44835 | AI98: 44866 | AJ98: 44896 | AK98: 44927 | AL98: 44958 | AM98: 44986 | AN98: 45017 | AO98: 45047 | AP98: 45078 | AQ98: 45108 | AR98: 45139 | AS98: 45170 | AT98: 45200 | AU98: 45231 | AV98: 45261 | AW98: 45292 | AX98: 45323 | AY98: 45352 | AZ98: 45383 | BA98: 45413 | BB98: 45444 | BC98: 45474 | BD98: 45505 | BE98: 45536 | BF98: 45566 | BG98: 45597 | BH98: 45627 | BI98: 45658 | BJ98: 45689 | BX98: Total
A99: 7 | B99: Bruno Luiz Marques | C99: Inativo | D99: Operacional | E99: Oficial de Serviços Gerais | F99: Oficial de Serviços Gerais | G99: ='CONSOLIDADO ATIVO INATIVO NOVO'!J10 -> 45059 | H99: ='CONSOLIDADO ATIVO INATIVO NOVO'!K10 -> 0 | I99: Pagamento sem holerite
I100: Holerite | AU100: 184.98 | AV100: 1849.81
...

Sheet MENSAL LÍQUIDO
A1: Mensal Líquido Colaboradores Mar Brasil 09/2022
A2: Colaboradores/Prestadores | B2: Contrato | C2: Ajuda de custo | D2: Vale transporte | E2: Cesta | F2: 0.06 | G2: 0.08 | H2: Total por pessoa
A3: Ana Lucia de Lima | B3: 1708.83 | C3: 0 | D3: 240 | E3: 400 | F3: =B3*0.06 -> 102.5298 | G3: =B3*0.08 -> 136.7064 | H3: =SUM(B3:E3)-SUM(F3:G3) -> 2109.5938
A4: Carlos Henryque Gomes da Silva | B4: 1708.83 | C4: 432.38 | D4: 0 | E4: 0 | F4: 0 | G4: =B4*0.08 -> 136.7064 | H4: =SUM(B4:E4)-SUM(F4:G4) -> 2004.5036
A5: Diana Miranda | B5: 1615.9 | C5: =#REF! -> #REF! | D5: 0 | E5: 400 | F5: 0 | G5: =B5*0.08 -> 129.272 | H5: =SUM(B5:E5)-SUM(F5:G5) -> #REF!
A6: Douglas Pedrosa Abrantes | B6: 1635.07 | D6: 249.6 | E6: 0 | F6: 0 | G6: =B6*0.08 -> 130.8056 | H6: =SUM(B6:E6)-SUM(F6:G6) -> 1753.8644
A7: Fagner Evinson Tosatti Albuquerque Araruna | B7: 1708.83 | C7: =#REF! -> #REF! | D7: 0 | E7: 0 | F7: 0 | G7: =B7*0.08 -> 136.7064 | H7: =SUM(B7:E7)-SUM(F7:G7) -> #REF!
A8: Gabriel Wagner Bellini | B8: 1708.83 | C8: =#REF! -> #REF! | D8: 0 | E8: 0 | F8: 0 | G8: =B8*0.08 -> 136.7064 | H8: =SUM(B8:E8)-SUM(F8:G8) -> #REF!
A9: Misael dos Santos | B9: 1708.83 | C9: =#REF! -> #REF! | D9: 0 | E9: 0 | F9: 0 | G9: =B9*0.08 -> 136.7064 | H9: =SUM(B9:E9)-SUM(F9:G9) -> #REF!
A10: Renan dos Santos Ramos Batista | B10: 1708.83 | C10: =#REF! -> #REF! | D10: 0 | E10: 0 | F10: 0 | G10: =B10*0.08 -> 136.7064 | H10: =SUM(B10:E10)-SUM(F10:G10) -> #REF!
A11: Renato Ubiratan Pereira Leal Costa | B11: 1708.83 | C11: =#REF! -> #REF! | D11: 0 | E11: 0 | F11: 0 | G11: =B11*0.08 -> 136.7064 | H11: =SUM(B11:E11)-SUM(F11:G11) -> #REF!
A12: Airton Rodrigues da Silva | B12: 5000 | C12: 0 | D12: 0 | E12: 0 | F12: 0 | G12: 0 | H12: =SUM(B12:E12)-SUM(F12:G12) -> 5000
A13: Alexandre Nascimento dos Santos | B13: 4275 | C13: 0 | D13: 0 | E13: 0 | F13: 0 | G13: 0 | H13: =SUM(B13:E13)-SUM(F13:G13) -> 4275
A14: Eduardo Lukservicius | B14: 3218.75 | C14: 0 | D14: 0 | E14: 0 | F14: 0 | G14: 0 | H14: =SUM(B14:E14)-SUM(F14:G14) -> 3218.75
A15: Fabio Aparecido Dutra Paranaiba | B15: 7000 | C15: 515.05 | D15: 0 | E15: 0 | F15: 0 | G15: 0 | H15: =SUM(B15:E15)-SUM(F15:G15) -> 7515.05
A16: Fernanda Nakita | B16: 1300 | C16: 270 | D16: 0 | E16: 0 | F16: 0 | G16: 0 | H16: =SUM(B16:E16)-SUM(F16:G16) -> 1570
A17: Mathaus Lukservicius | B17: 1000 | C17: 0 | D17: 0 | E17: 0 | F17: 0 | G17: 0 | H17: =SUM(B17:E17)-SUM(F17:G17) -> 1000
A18: Miguel A Gomes Guerreiro | B18: 1000 | C18: 0 | D18: 0 | E18: 0 | F18: 0 | G18: 0 | H18: =SUM(B18:E18)-SUM(F18:G18) -> 1000
A19: William Hauro da Silva | B19: 4275 | C19: 0 | D19: 0 | E19: 0 | F19: 0 | G19: 0 | H19: =SUM(B19:E19)-SUM(F19:G19) -> 4275
A20: Total | B20: =SUM(B3:B19) -> 42281.53 | C20: =SUM(C3:C19) -> #REF! | D20: =SUM(D3:D19) -> 489.6 | E20: =SUM(E3:E19) -> 800 | F20: =SUM(F3:F19) -> 102.5298 | G20: =SUM(G3:G19) -> 1217.0224 | H20: =SUM(B20:E20) -> #REF!

Sheet Rescisório - CLT
A1: Rescisório CLT
A2: Funcionários | B2: Ativo/ Inativo/Aviso prévio | C2: Valor pago | D2: Valor à pagar | E2: Total
A3: Carlos henryque Gomes da Silva | B3: Inativo
A4: =#REF! -> #REF! | B4: Inativo | C4: 0 | E4: =SUM(C4:D4) -> 0
A5: =#REF! -> #REF! | B5: Inativo | C5: =#REF! -> #REF! | D5: 0 | E5: =SUM(C5:D5) -> #REF!
A6: Fagner Evinson Tosatti Albuquerque Araruna | B6: Ativo | C6: 0 | D6: 0 | E6: =SUM(C6:D6) -> 0
A7: =#REF! -> #REF! | B7: Ativo | C7: 0 | D7: 0 | E7: =SUM(C7:D7) -> 0
A8: Misael dos Santos | B8: Ativo | C8: 0 | D8: 0 | E8: =SUM(C8:D8) -> 0
A9: Renan dos Santos Ramos Batista | B9: Ativo | C9: 0 | D9: 0 | E9: =SUM(C9:D9) -> 0
A10: =#REF! -> #REF! | B10: Ativo | C10: 0 | D10: 0 | E10: =SUM(C10:D10) -> 0
A11: =#REF! -> #REF! | B11: Inativo | C11: =#REF! -> #REF! | D11: 0 | E11: =SUM(C11:D11) -> #REF!
A12: TOTAL | E12: =SUM(E4:E11) -> #REF!

Sheet Aparecido
B1: Relatório de contas a pagar Período: 01/01/2021 à 31/12/2021 Gerado em 21/01/2022 às 09:36:09
A2: Código | B2: Destinado à | C2: Descrição | D2: Plano de contas | E2: Forma de pagamento | F2: Conta bancária | G2: Centro de custo | H2: Data | I2: NF-e | J2: Situação | K2: Valor | L2: Desconto | M2: Juros | N2: Taxa do banco | O2: Taxa da operadora | P2: Valor total
A3: 1584 | B3: Aparecido José da Silva | C3: 2ª parc. - Decimo terceiro - Aparecido | D3: Encargos funcionários - 13o salário | E3: PIX | F3: Conta corrente - Bradesco | G3: Guincho Praia Grande/SP - Pregão 166 2020 | H3: 20/12/2021 | I3: ------ | J3: Confirmado | K3: 486,96 | L3: 280,00 | M3: 0,00 | N3: 0,00 | O3: 0,00 | P3: 206,96
A4: 2284 | B4: Aparecido José da Silva | C4: Despesas - FGTS Rescisório Aparecido | D4: Encargos funcionários - FGTS | E4: Boleto Bancário | F4: Banco Prudentte | G4: Guincho Praia Grande/SP - Pregão 166 2020 | H4: 27/12/2021 | I4: ------ | J4: Confirmado | K4: 565,68 | L4: 0,00 | M4: 0,00 | N4: 0,00 | O4: 0,00 | P4: 565,68
A5: 2293 | B5: Aparecido José da Silva | C5: Despesas - Rescisão Aparecido | D5: Encargos - rescisões trabalhistas | E5: PIX | F5: Banco Prudentte | G5: Guincho Praia Grande/SP - Pregão 166 2020 | H5: 29/12/2021 | I5: ------ | J5: Confirmado | K5: 3.114,65 | L5: 0,00 | M5: 0,00 | N5: 0,00 | O5: 0,00 | P5: 3.114,65
A6: 1525 | B6: Aparecido José da Silva | C6: Holerite - Aparecido | D6: Encargo Funcionários - Holerite Mensal | E6: PIX | F6: Conta corrente - Bradesco | G6: Guincho Praia Grande/SP - Pregão 166 2020 | H6: 06/12/2021 | I6: ------ | J6: Confirmado | K6: 2.014,22 | L6: 943,90 | M6: 0,00 | N6: 0,00 | O6: 0,00 | P6: 1.070,32
A7: 1646 | B7: Aparecido José da Silva | C7: Adiantamento Holerite - Aparecido | D7: Adiantamento - funcionários | E7: PIX | F7: Conta corrente - Bradesco | G7: Guincho Praia Grande/SP - Pregão 166 2020 | H7: 20/12/2021 | I7: ------ | J7: Confirmado | K7: 779,13 | L7: 0,00 | M7: 0,00 | N7: 0,00 | O7: 0,00 | P7: 779,13
A8: 1474 | B8: Aparecido José da Silva | C8: Decimo terceiro - Aparecido | D8: Encargos funcionários - 13o salário | E8: PIX | F8: Conta corrente - Bradesco | G8: Guincho Praia Grande/SP - Pregão 166 2020 | H8: 30/11/2021 | I8: ------ | J8: Confirmado | K8: 243,48 | L8: 0,00 | M8: 0,00 | N8: 0,00 | O8: 0,00 | P8: 243,48
A9: 1366 | B9: Aparecido José da Silva | C9: Holerite | D9: Encargo Funcionários - Holerite Mensal | E9: PIX | F9: Conta corrente - Bradesco | G9: Guincho Praia Grande/SP - Pregão 166 2020 | H9: 04/11/2021 | I9: ------ | J9: Confirmado | K9: 2.560,20 | L9: 744,03 | M9: 0,00 | N9: 0,00 | O9: 0,00 | P9: 1.816,17
A10: 1373 | B10: Aparecido José da Silva | C10: Adiantamento Holerite | D10: Adiantamento - funcionários | E10: PIX | F10: Conta corrente - Bradesco | G10: Guincho Praia Grande/SP - Pregão 166 2020 | H10: 18/11/2021 | I10: ------ | J10: Confirmado | K10: 779,13 | L10: 23,41 | M10: 0,00 | N10: 0,00 | O10: 0,00 | P10: 755,72
A11: 129 | B11: Aparecido José da Silva | C11: Vale Refeição | D11: Encargos funcionários - alimentação | E11: PIX | F11: Conta corrente - Bradesco | G11: Guincho Praia Grande/SP - Pregão 166 2020 | H11: 30/11/2021 | I11: ------ | J11: Confirmado | K11: 241,72 | L11: 0,00 | M11: 0,00 | N11: 0,00 | O11: 0,00 | P11: 241,72
A12: 1404 | B12: Aparecido José da Silva | C12: Vale Transporte | D12: Encargos funcionários - vale transporte | E12: PIX | F12: Conta corrente - Bradesco | G12: Guincho Praia Grande/SP - Pregão 166 2020 | H12: 30/11/2021 | I12: ------ | J12: Confirmado | K12: 186,00 | L12: 0,00 | M12: 0,00 | N12: 0,00 | O12: 0,00 | P12: 186,00
A13: 1340 | B13: Aparecido José da Silva | C13: Diárias - Pre-contratação - Aparecido | D13: Remuneração funcionários | E13: Cartão de Crédito | F13: Banco Prudentte | G13: GL-07 | H13: 18/10/2021 | I13: ------ | J13: Confirmado | K13: 600,00 | L13: 0,00 | M13: 0,00 | N13: 0,00 | O13: 0,00 | P13: 600,00
... A17: 1396 | B17: Aparecido José da Silva | C17: Vale Refeição | D17: Encargos funcionários - alimentação | E17: PIX | F17: Conta corrente - Bradesco | G17: Guincho Praia Grande/SP - Pregão 166 2020 | H17: 29/10/2021 | I17: ------ | J17: Confirmado | K17: 241,72 | L17: 0,00 | M17: 0,00 | N17: 0,00 | O17: 0,00 | P17: 241,72
A18: TOTAIS
A19: Quantidade: | L19: 15
A20: Pagamentos atrasados: | L20: 0,00
A21: Pagamentos para hoje: | L21: 0,00
A22: Pagamentos futuros: | L22: 0,00
A23: Valor total à pagar: | L23: 0,00
A24: Valor total pago: | L24: 10.712,97
A25: Descontos: | L25: 1.991,34
A26: Juros: | L26: 0,00
A27: Taxas do banco: | L27: 0,00
A28: Taxas da operadora: | L28: 0,00
A29: Valor total: | L29: 10.712,97

Sheet Edimilson
B1: Relatório de contas a pagar Período: 01/01/2021 à 31/12/2021 Gerado em 21/01/2022 às 09:26:19
A2: Código | B2: Destinado à | C2: Descrição | D2: Plano de contas | E2: Forma de pagamento | F2: Conta bancária | G2: Centro de custo | H2: Data | I2: NF-e | J2: Situação | K2: Valor | L2: Desconto | M2: Juros | N2: Taxa do banco | O2: Taxa da operadora | P2: Valor total
A3: 80 | B3: Edimilson Jose Da Silva | C3: Vale Transporte | D3: Encargos funcionários - vale transporte | E3: PIX | F3: Investimentos Dauren | G3: Guincho Praia Grande/SP - Pregão 166 2020 | H3: 11/03/2021 | I3: ------ | J3: Confirmado | K3: 225,40 | L3: 0,00 | M3: 0,00 | N3: 0,00 | O3: 0,00 | P3: 225,40
A4: 73 | B4: Edimilson Jose Da Silva | C4: Vale Refeição | D4: Encargos funcionários - alimentação | E4: PIX | F4: Investimentos Dauren | G4: Guincho Praia Grande/SP - Pregão 166 2020 | H4: 17/03/2021 | I4: ------ | J4: Confirmado | K4: 241,72 | L4: 0,00 | M4: 0,00 | N4: 0,00 | O4: 0,00 | P4: 241,72
A5: 83 | B5: Edimilson Jose Da Silva | C5: Adiantamento Holerite | D5: Adiantamento - funcionários | E5: PIX | F5: Investimentos Dauren | G5: Guincho Praia Grande/SP - Pregão 166 2020 | H5: 19/03/2021 | I5: ------ | J5: Confirmado | K5: 675,24 | L5: 0,00 | M5: 0,00 | N5: 0,00 | O5: 0,00 | P5: 675,24
A6: 366 | B6: Edimilson Jose Da Silva | C6: Rescisão Edimilson | D6: Encargos - rescisões trabalhistas | E6: PIX | F6: Investimentos Dauren | G6: Guincho Praia Grande/SP - Pregão 166 2020 | H6: 31/03/2021 | I6: ------ | J6: Confirmado | K6: 4.003,86 | L6: 1.674,87 | M6: 0,00 | N6: 0,00 | O6: 0,00 | P6: 2.328,99
A7: 1131 | B7: Edimilson Jose Da Silva | C7: Serviços Avulsos - Diárias Motorista | D7: Encargo Funcionários - Holerite Mensal | E7: Dinheiro à Vista | F7: Conta corrente - Bradesco | G7: Guincho Praia Grande/SP - Pregão 166 2020 | H7: 19/07/2021 | I7: ------ | J7: Confirmado | K7: 240,00 | L7: 0,00 | M7: 0,00 | N7: 0,00 | O7: 0,00 | P7: 240,00
A8: 1244 | B8: Edimilson Jose Da Silva | C8: Despesas - Diárias GL5 - Pré-contratação | D8: Remuneração funcionários | E8: Cartão de Crédito | F8: Banco Prudentte | G8: Guincho Praia Grande/SP - Pregão 166 2020 | H8: 16/09/2021 | I8: ------ | J8: Confirmado | K8: 480,00 | L8: 0,00 | M8: 0,00 | N8: 0,00 | O8: 0,00 | P8: 480,00
A9: 1255 | B9: Edimilson Jose Da Silva | C9: Vale Refeição | D9: Encargos funcionários - alimentação | E9: PIX | F9: Conta corrente - Bradesco | G9: Guincho Praia Grande/SP - Pregão 166 2020 | H9: 30/09/2021 | I9: ------ | J9: Confirmado | K9: 241,72 | L9: 0,00 | M9: 0,00 | N9: 0,00 | O9: 0,00 | P9: 241,72
A10: 1256 | B10: Edimilson Jose Da Silva | C10: Vale Transporte | D10: Encargos funcionários - vale transporte | E10: PIX | F10: Conta corrente - Bradesco | G10: Guincho Praia Grande/SP - Pregão 166 2020 | H10: 30/09/2021 | I10: ------ | J10: Confirmado | K10: 176,00 | L10: 0,00 | M10: 0,00 | N10: 0,00 | O10: 0,00 | P10: 176,00
A11: 1359 | B11: Edimilson Jose Da Silva | C11: Holerite | D11: Encargo Funcionários - Holerite Mensal | E11: PIX | F11: Banco Prudentte | G11: Guincho Praia Grande/SP - Pregão 166 2020 | H11: 05/10/2021 | I11: ------ | J11: Confirmado | K11: 660,64 | L11: 0,00 | M11: 0,00 | N11: 0,00 | O11: 0,00 | P11: 660,64
A12: 196 | B12: Edimilson Jose Da Silva | C12: Adiantamento Holerite | D12: Adiantamento - funcionários | E12: PIX | F12: Conta corrente - Bradesco | G12: Guincho Praia Grande/SP - Pregão 166 2020 | H12: 20/10/2021 | I12: ------ | J12: Confirmado | K12: 779,13 | L12: 0,00 | M12: 0,00 | N12: 0,00 | O12: 0,00 | P12: 779,13
A13: 1389 | B13: Edimilson Jose Da Silva | C13: Vale Transporte | D13: Encargos funcionários - vale transporte | E13: PIX | F13: Conta corrente - Bradesco | G13: Guincho Praia Grande/SP - Pregão 166 2020 | H13: 29/10/2021 | I13: ------ | J13: Confirmado | K13: 165,00 | L13: 0,00 | M13: 0,00 | N13: 0,00 | O13: 0,00 | P13: 165,00
... A23: 1677 | B23: Edimilson Jose Da Silva | C23: Vale Refeição | D23: Encargos funcionários - alimentação | E23: PIX | F23: Conta corrente - Bradesco | G23: Guincho Praia Grande/SP - Pregão 166 2020 | H23: 22/12/2021 | I23: ------ | J23: Confirmado | K23: 241,72 | L23: 0,00 | M23: 0,00 | N23: 0,00 | O23: 0,00 | P23: 241,72
A24: TOTAIS
A25: Quantidade: | L25: 21
A26: Pagamentos atrasados: | L26: 0,00
A27: Pagamentos para hoje: | L27: 0,00
A28: Pagamentos futuros: | L28: 0,00
A29: Valor total à pagar: | L29: 0,00
A30: Valor total pago: | L30: 11.203,91
A31: Descontos: | L31: 3.836,70
A32: Juros: | L32: 0,00
A33: Taxas do banco: | L33: 0,00
A34: Taxas da operadora: | L34: 0,00
A35: Valor total: | L35: 11.203,91
A36: Descontos: | L36: 4.921,31
... A38: Taxas do banco: | L38: 0,00
A39: Taxas da operadora: | L39: 0,00 | N39: 559.12 | O39: 13268.61 | P39: =O39+N39 -> 13827.73
A40: Valor total: | L40: 13.827,73

Sheet Fabio
B1: Relatório de contas a pagar Período: 01/01/2021 à 31/12/2021 Gerado em 21/01/2022 às 10:05:35
A2: Código | B2: Destinado à | C2: Descrição | D2: Plano de contas | E2: Forma de pagamento | F2: Conta bancária | G2: Centro de custo | H2: Data | I2: NF-e | J2: Situação | K2: Valor | L2: Desconto | M2: Juros | N2: Taxa do banco | O2: Taxa da operadora | P2: Valor total
A3: 1257 | B3: Fabio Henrique Domingos Da Silva | C3: Vale Refeição | D3: Encargos funcionários - alimentação | E3: PIX | F3: Conta corrente - Bradesco | G3: Guincho Praia Grande/SP - Pregão 166 2020 | H3: 30/09/2021 | I3: ------ | J3: Confirmado | K3: 241,72 | L3: 0,00 | M3: 0,00 | N3: 0,00 | O3: 0,00 | P3: 241,72
A4: 1321 | B4: Fabio Henrique Domingos Da Silva | C4: Adiantamento Holerite | D4: Adiantamento - funcionários | E4: PIX | F4: Conta corrente - Bradesco | G4: Guincho Praia Grande/SP - Pregão 166 2020 | H4: 20/10/2021 | I4: ------ | J4: Confirmado | K4: 779,13 | L4: 0,00 | M4: 0,00 | N4: 0,00 | O4: 0,00 | P4: 779,13
A5: 1394 | B5: Fabio Henrique Domingos Da Silva | C5: Vale Refeição | D5: Encargos funcionários - alimentação | E5: PIX | F5: Conta corrente - Bradesco | G5: Guincho Praia Grande/SP - Pregão 166 2020 | H5: 29/10/2021 | I5: ------ | J5: Confirmado | K5: 241,72 | L5: 0,00 | M5: 0,00 | N5: 0,00 | O5: 0,00 | P5: 241,72
A6: 1364 | B6: Fabio Henrique Domingos Da Silva | C6: Holerite | D6: Encargo Funcionários - Holerite Mensal | E6: PIX | F6: Conta corrente - Bradesco | G6: Guincho Praia Grande/SP - Pregão 166 2020 | H6: 04/11/2021 | I6: ------ | J6: Confirmado | K6: 2.563,71 | L6: 1.004,16 | M6: 0,00 | N6: 0,00 | O6: 0,00 | P6: 1.559,55
A7: 1371 | B7: Fabio Henrique Domingos Da Silva | C7: Adiantamento Holerite | D7: Adiantamento - funcionários | E7: PIX | F7: Conta corrente - Bradesco | G7: Guincho Praia Grande/SP - Pregão 166 2020 | H7: 18/11/2021 | I7: ------ | J7: Confirmado | K7: 779,13 | L7: 0,00 | M7: 0,00 | N7: 0,00 | O7: 0,00 | P7: 779,13
A8: 1477 | B8: Fabio Henrique Domingos Da Silva | C8: Decimo terceiro - Fabio | D8: Encargos funcionários - 13o salário | E8: PIX | F8: Conta corrente - Bradesco | G8: Guincho Praia Grande/SP - Pregão 166 2020 | H8: 30/11/2021 | I8: ------ | J8: Confirmado | K8: 243,48 | L8: 0,00 | M8: 0,00 | N8: 0,00 | O8: 0,00 | P8: 243,48
A9: 1489 | B9: Fabio Henrique Domingos Da Silva | C9: Vale Refeição | D9: Encargos funcionários - alimentação | E9: PIX | F9: Conta corrente - Bradesco | G9: Guincho Praia Grande/SP - Pregão 166 2020 | H9: 30/11/2021 | I9: ------ | J9: Confirmado | K9: 241,72 | L9: 0,00 | M9: 0,00 | N9: 0,00 | O9: 0,00 | P9: 241,72
A10: 1527 | B10: Fabio Henrique Domingos Da Silva | C10: Holerite - Fabio | D10: Encargo Funcionários - Holerite Mensal | E10: PIX | F10: Conta corrente - Bradesco | G10: Guincho Praia Grande/SP - Pregão 166 2020 | H10: 06/12/2021 | I10: ------ | J10: Confirmado | K10: 2.180,23 | L10: 958,85 | M10: 0,00 | N10: 0,00 | O10: 0,00 | P10: 1.221,38
A11: 1590 | B11: Fabio Henrique Domingos Da Silva | C11: 2ª parc. - Decimo terceiro - Fabio | D11: Encargos funcionários - 13o salário | E11: PIX | F11: Conta corrente - Bradesco | G11: Guincho Praia Grande/SP - Pregão 166 2020 | H11: 20/12/2021 | I11: ------ | J11: Confirmado | K11: 486,96 | L11: 280,00 | M11: 0,00 | N11: 0,00 | O11: 0,00 | P11: 206,96
A12: 1648 | B12: Fabio Henrique Domingos Da Silva | C12: Adiantamento Holerite - Fabio | D12: Adiantamento - funcionários | E12: PIX | F12: Conta corrente - Bradesco | G12: Guincho Praia Grande/SP - Pregão 166 2020 | H12: 20/12/2021 | I12: ------ | J12: Confirmado | K12: 779,13 | L12: 0,00 | M12: 0,00 | N12: 0,00 | O12: 0,00 | P12: 779,13
A13: 1680 | B13: Fabio Henrique Domingos Da Silva | C13: Vale Refeição | D13: Encargos funcionários - alimentação | E13: PIX | F13: Conta corrente - Bradesco | G13: Guincho Praia Grande/SP - Pregão 166 2020 | H13: 22/12/2021 | I13: ------ | J13: Confirmado | K13: 241,72 | L13: 0,00 | M13: 0,00 | N13: 0,00 | O13: 0,00 | P13: 241,72
A14: TOTAIS
A15: Quantidade: | L15: 11
A16: Pagamentos atrasados: | L16: 0,00
A17: Pagamentos para hoje: | L17: 0,00
A18: Pagamentos futuros: | L18: 0,00
A19: Valor total à pagar: | L19: 0,00
A20: Valor total pago: | L20: 6.535,64
A21: Descontos: | L21: 2.243,01
A22: Juros: | L22: 0,00
A23: Taxas do banco: | L23: 0,00
A24: Taxas da operadora: | L24: 0,00
A25: Valor total: | L25: 6.535,64

Sheet Marcio
B1: Relatório de contas a pagar Período: 01/01/2021 à 31/12/2021 Gerado em 21/01/2022 às 10:14:10
A2: Código | B2: Destinado à | C2: Descrição | D2: Plano de contas | E2: Forma de pagamento | F2: Conta bancária | G2: Centro de custo | H2: Data | I2: NF-e | J2: Situação | K2: Valor | L2: Desconto | M2: Juros | N2: Taxa do banco | O2: Taxa da operadora | P2: Valor total
A3: 666 | B3: Marcio Augusto da Silva | C3: Serviços Avulsos - Diárias Motorista | D3: Encargo Funcionários - Holerite Mensal | E3: Dinheiro à Vista | F3: Conta corrente - Bradesco | G3: Guincho Praia Grande/SP - Pregão 166 2020 | H3: 44425 | I3: ------ | J3: Confirmado | K3: 480 | L3: 0 | M3: 0 | N3: 0 | O3: 0 | P3: 480
A4: 1192 | B4: Marcio Augusto da Silva | C4: Vale Refeição | D4: Encargos funcionários - alimentação | E4: PIX | F4: Conta corrente - Bradesco | G4: Guincho Praia Grande/SP - Pregão 166 2020 | H4: 44439 | I4: ------ | J4: Confirmado | K4: 241.72 | L4: 0 | M4: 0 | N4: 0 | O4: 0 | P4: 241.72
A5: 667 | B5: Marcio Augusto da Silva | C5: Serviços Avulsos - Diárias Motorista | D5: Encargo Funcionários - Holerite Mensal | E5: Dinheiro à Vista | F5: Conta corrente - Bradesco | G5: Guincho Praia Grande/SP - Pregão 166 2020 | H5: 44442 | I5: ------ | J5: Confirmado | K5: 600 | L5: 0 | M5: 0 | N5: 0 | O5: 0 | P5: 600
A6: 1226 | B6: Marcio Augusto da Silva | C6: Adiantamento Holerite | D6: Adiantamento - funcionários | E6: PIX | F6: Conta corrente - Bradesco | G6: Guincho Praia Grande/SP - Pregão 166 2020 | H6: 44459 | I6: ------ | J6: Confirmado | K6: 779.13 | L6: 0 | M6: 0 | N6: 0 | O6: 0 | P6: 779.13
A7: 1258 | B7: Marcio Augusto da Silva | C7: Vale Refeição | D7: Encargos funcionários - alimentação | E7: PIX | F7: Conta corrente - Bradesco | G7: Guincho Praia Grande/SP - Pregão 166 2020 | H7: 44469 | I7: ------ | J7: Confirmado | K7: 241.72 | L7: 0 | M7: 0 | N7: 0 | O7: 0 | P7: 241.72
A8: 1288 | B8: Marcio Augusto da Silva | C8: Serviços Avulsos - Diárias Motorista | D8: Encargo Funcionários - Holerite Mensal | E8: PIX | F8: Conta corrente - Bradesco | G8: Guincho Praia Grande/SP - Pregão 166 2020 | H8: 44474 | I8: ------ | J8: Confirmado | K8: 2202.81 | L8: 960.88 | M8: 0 | N8: 0 | O8: 0 | P8: 1241.93
A9: 1322 | B9: Marcio Augusto da Silva | C9: Adiantamento Holerite | D9: Adiantamento - funcionários | E9: PIX | F9: Conta corrente - Bradesco | G9: Guincho Praia Grande/SP - Pregão 166 2020 | H9: 44489 | I9: ------ | J9: Confirmado | K9: 779.13 | L9: 0 | M9: 0 | N9: 0 | O9: 0 | P9: 779.13
A10: 1395 | B10: Marcio Augusto da Silva | C10: Vale Refeição | D10: Encargos funcionários - alimentação | E10: PIX | F10: Conta corrente - Bradesco | G10: Guincho Praia Grande/SP - Pregão 166 2020 | H10: 44498 | I10: ------ | J10: Confirmado | K10: 241.72 | L10: 0 | M10: 0 | N10: 0 | O10: 0 | P10: 241.72
A11: 1365 | B11: Marcio Augusto da Silva | C11: Holerite | D11: Encargo Funcionários - Holerite Mensal | E11: PIX | F11: Conta corrente - Bradesco | G11: Guincho Praia Grande/SP - Pregão 166 2020 | H11: 44504 | I11: ------ | J11: Confirmado | K11: 2280.99 | L11: 970.24 | M11: 0 | N11: 0 | O11: 0 | P11: 1310.75
A12: 1372 | B12: Marcio Augusto da Silva | C12: Adiantamento Holerite | D12: Adiantamento - funcionários | E12: PIX | F12: Conta corrente - Bradesco | G12: Guincho Praia Grande/SP - Pregão 166 2020 | H12: 44518 | I12: ------ | J12: Confirmado | K12: 779.13 | L12: 13.94 | M12: 0 | N12: 0 | O12: 0 | P12: 765.19
A13: 1478 | B13: Marcio Augusto da Silva | C13: Decimo terceiro - Marcio | D13: Encargos funcionários - 13o salário | E13: PIX | F13: Conta corrente - Bradesco | G13: Guincho Praia Grande/SP - Pregão 166 2020 | H13: 44530 | I13: ------ | J13: Confirmado | K13: 324.64 | L13: 0 | M13: 0 | N13: 0 | O13: 0 | P13: 324.64
A14: 1490 | B14: Marcio Augusto da Silva | C14: Vale Refeição | D14: Encargos funcionários - alimentação | E14: PIX | F14: Conta corrente - Bradesco | G14: Guincho Praia Grande/SP - Pregão 166 2020 | H14: 44530 | I14: ------ | J14: Confirmado | K14: 241.72 | L14: 0 | M14: 0 | N14: 0 | O14: 0 | P14: 241.72
... A18: 1676 | B18: Marcio Augusto da Silva | C18: Vale Refeição | D18: Encargos funcionários - alimentação | E18: PIX | F18: Conta corrente - Bradesco | G18: Guincho Praia Grande/SP - Pregão 166 2020 | H18: 44552 | I18: ------ | J18: Confirmado | K18: 241.72 | L18: 0 | M18: 0 | N18: 0 | O18: 0 | P18: 241.72
A19: TOTAIS
A20: Quantidade: | L20: 16
A21: Pagamentos atrasados: | L21: 0
A22: Pagamentos para hoje: | L22: 0
A23: Pagamentos futuros: | L23: 0
A24: Valor total à pagar: | L24: 0
A25: Valor total pago: | L25: 9765.82
A26: Descontos: | L26: 3277.24
A27: Juros: | L27: 0
A28: Taxas do banco: | L28: 0
A29: Taxas da operadora: | L29: 0
A30: Valor total: | L30: 9765.82

Sheet Rosinaldo
B1: Relatório de contas a pagar Período: 01/01/2021 à 31/12/2021 Gerado em 21/01/2022 às 10:23:29
A2: Código | B2: Destinado à | C2: Descrição | D2: Plano de contas | E2: Forma de pagamento | F2: Conta bancária | G2: Centro de custo | H2: Data | I2: NF-e | J2: Situação | K2: Valor | L2: Desconto | M2: Juros | N2: Taxa do banco | O2: Taxa da operadora | P2: Valor total
A3: 1245 | B3: Rosinaldo Soares | C3: Despesas - Diárias GL5 - pre-contratação | D3: Remuneração funcionários | E3: Cartão de Crédito | F3: Banco Prudentte | G3: Guincho Praia Grande/SP - Pregão 166 2020 | H3: 16/09/2021 | I3: ------ | J3: Confirmado | K3: 240,00 | L3: 0,00 | M3: 0,00 | N3: 0,00 | O3: 0,00 | P3: 240,00
A4: 127 | B4: Rosinaldo Soares | C4: Vale Refeição | D4: Encargos funcionários - alimentação | E4: PIX | F4: Conta corrente - Bradesco | G4: Guincho Praia Grande/SP - Pregão 166 2020 | H4: 30/09/2021 | I4: ------ | J4: Confirmado | K4: 241,72 | L4: 0,00 | M4: 0,00 | N4: 0,00 | O4: 0,00 | P4: 241,72
A5: 315 | B5: Rosinaldo Soares | C5: Vale Transporte | D5: Encargos funcionários - vale transporte | E5: PIX | F5: Conta corrente - Bradesco | G5: Guincho Praia Grande/SP - Pregão 166 2020 | H5: 30/09/2021 | I5: ------ | J5: Confirmado | K5: 148,50 | L5: 0,00 | M5: 0,00 | N5: 0,00 | O5: 0,00 | P5: 148,50
A6: 1287 | B6: Rosinaldo Soares | C6: Despesas - Holerite | D6: Encargo Funcionários - Holerite Mensal | E6: PIX | F6: Conta corrente - Bradesco | G6: Guincho Praia Grande/SP - Pregão 166 2020 | H6: 05/10/2021 | I6: ------ | J6: Confirmado | K6: 714,20 | L6: 53,56 | M6: 0,00 | N6: 0,00 | O6: 0,00 | P6: 660,64
A7: 1323 | B7: Rosinaldo Soares | C7: Adiantamento Holerite | D7: Adiantamento - funcionários | E7: PIX | F7: Conta corrente - Bradesco | G7: Guincho Praia Grande/SP - Pregão 166 2020 | H7: 20/10/2021 | I7: ------ | J7: Confirmado | K7: 779,13 | L7: 0,00 | M7: 0,00 | N7: 0,00 | O7: 0,00 | P7: 779,13
A8: 1388 | B8: Rosinaldo Soares | C8: Vale Transporte | D8: Encargos funcionários - vale transporte | E8: PIX | F8: Conta corrente - Bradesco | G8: Guincho Praia Grande/SP - Pregão 166 2020 | H8: 29/10/2021 | I8: ------ | J8: Confirmado | K8: 158,40 | L8: 0,00 | M8: 0,00 | N8: 0,00 | O8: 0,00 | P8: 158,40
A9: 1392 | B9: Rosinaldo Soares | C9: Vale Refeição | D9: Encargos funcionários - alimentação | E9: PIX | F9: Conta corrente - Bradesco | G9: Guincho Praia Grande/SP - Pregão 166 2020 | H9: 29/10/2021 | I9: ------ | J9: Confirmado | K9: 241,72 | L9: 0,00 | M9: 0,00 | N9: 0,00 | O9: 0,00 | P9: 241,72
A10: 1363 | B10: Rosinaldo Soares | C10: Holerite | D10: Encargo Funcionários - Holerite Mensal | E10: PIX | F10: Conta corrente - Bradesco | G10: Guincho Praia Grande/SP - Pregão 166 2020 | H10: 04/11/2021 | I10: ------ | J10: Confirmado | K10: 1.947,82 | L10: 937,93 | M10: 0,00 | N10: 0,00 | O10: 0,00 | P10: 1.009,89
A11: 1368 | B11: Rosinaldo Soares | C11: Adiantamento Holerite | D11: Adiantamento - funcionários | E11: PIX | F11: Conta corrente - Bradesco | G11: Guincho Praia Grande/SP - Pregão 166 2020 | H11: 18/11/2021 | I11: ------ | J11: Confirmado | K11: 779,13 | L11: 0,00 | M11: 0,00 | N11: 0,00 | O11: 0,00 | P11: 779,13
A12: 1405 | B12: Rosinaldo Soares | C12: Vale Transporte | D12: Encargos funcionários - vale transporte | E12: PIX | F12: Conta corrente - Bradesco | G12: Guincho Praia Grande/SP - Pregão 166 2020 | H12: 30/11/2021 | I12: ------ | J12: Confirmado | K12: 148,50 | L12: 0,00 | M12: 0,00 | N12: 0,00 | O12: 0,00 | P12: 148,50
A13: 1480 | B13: Rosinaldo Soares | C13: Decimo terceiro - Rosinaldo | D13: Encargos funcionários - 13o salário | E13: PIX | F13: Conta corrente - Bradesco | G13: Guincho Praia Grande/SP - Pregão 166 2020 | H13: 30/11/2021 | I13: ------ | J13: Confirmado | K13: 243,48 | L13: 0,00 | M13: 0,00 | N13: 0,00 | O13: 0,00 | P13: 243,48
... A18: 1679 | B18: Rosinaldo Soares | C18: Vale Refeição | D18: Encargos funcionários - alimentação | E18: PIX | F18: Conta corrente - Bradesco | G18: Guincho Praia Grande/SP - Pregão 166 2020 | H18: 22/12/2021 | I18: ------ | J18: Confirmado | K18: 241,72 | L18: 0,00 | M18: 0,00 | N18: 0,00 | O18: 0,00 | P18: 241,72
A19: TOTAIS
A20: Quantidade: | L20: 16
A21: Pagamentos atrasados: | L21: 0,00
A22: Pagamentos para hoje: | L22: 0,00
A23: Pagamentos futuros: | L23: 0,00
A24: Valor total à pagar: | L24: 0,00
A25: Valor total pago: | L25: 7.130,53
A26: Descontos: | L26: 2.209,42
A27: Juros: | L27: 0,00
A28: Taxas do banco: | L28: 0,00
A29: Taxas da operadora: | L29: 0,00
A30: Valor total: | L30: 7.130,53

Sheet Sergio
B1: Relatório de contas a pagar Período: 01/01/2021 à 31/12/2021 Gerado em 21/01/2022 às 10:32:13
A2: Código | B2: Destinado à | C2: Descrição | D2: Plano de contas | E2: Forma de pagamento | F2: Conta bancária | G2: Centro de custo | H2: Data | I2: NF-e | J2: Situação | K2: Valor | L2: Desconto | M2: Juros | N2: Taxa do banco | O2: Taxa da operadora | P2: Valor total
A3: 784 | B3: Sergio Ricardo Pereira da Silva | C3: Vale Refeição | D3: Encargos funcionários - alimentação | E3: PIX | F3: Conta corrente - Bradesco | G3: Guincho Praia Grande/SP - Pregão 166 2020 | H3: 31/05/2021 | I3: ------ | J3: Confirmado | K3: 241,72 | L3: 0,00 | M3: 0,00 | N3: 0,00 | O3: 0,00 | P3: 241,72
A4: 781 | B4: Sergio Ricardo Pereira da Silva | C4: Holerite - Sergio | D4: Encargo Funcionários - Holerite Mensal | E4: PIX | F4: Conta corrente - Bradesco | G4: Guincho Praia Grande/SP - Pregão 166 2020 | H4: 07/06/2021 | I4: ------ | J4: Confirmado | K4: 1.947,82 | L4: 1.227,12 | M4: 0,00 | N4: 0,00 | O4: 0,00 | P4: 720,70
A5: 766 | B5: Sergio Ricardo Pereira da Silva | C5: Adiantamento Holerite | D5: Adiantamento - funcionários | E5: PIX | F5: Conta corrente - Bradesco | G5: Guincho Praia Grande/SP - Pregão 166 2020 | H5: 16/06/2021 | I5: ------ | J5: Confirmado | K5: 779,13 | L5: 0,00 | M5: 0,00 | N5: 0,00 | O5: 0,00 | P5: 779,13
A6: 774 | B6: Sergio Ricardo Pereira da Silva | C6: Vale Refeição | D6: Encargos funcionários - alimentação | E6: PIX | F6: Conta corrente - Bradesco | G6: Guincho Praia Grande/SP - Pregão 166 2020 | H6: 30/06/2021 | I6: ------ | J6: Confirmado | K6: 241,72 | L6: 0,00 | M6: 0,00 | N6: 0,00 | O6: 0,00 | P6: 241,72
A7: 768 | B7: Sergio Ricardo Pereira da Silva | C7: Holerite - Sergio | D7: Encargo Funcionários - Holerite Mensal | E7: PIX | F7: Conta corrente - Bradesco | G7: Guincho Praia Grande/SP - Pregão 166 2020 | H7: 06/07/2021 | I7: ------ | J7: Confirmado | K7: 1.947,82 | L7: 1.017,93 | M7: 0,00 | N7: 0,00 | O7: 0,00 | P7: 929,89
A8: 785 | B8: Sergio Ricardo Pereira da Silva | C8: Adiantamento Holerite | D8: Adiantamento - funcionários | E8: PIX | F8: Conta corrente - Bradesco | G8: Guincho Praia Grande/SP - Pregão 166 2020 | H8: 20/07/2021 | I8: ------ | J8: Confirmado | K8: 779,13 | L8: 0,00 | M8: 0,00 | N8: 0,00 | O8: 0,00 | P8: 779,13
A9: 775 | B9: Sergio Ricardo Pereira da Silva | C9: Vale Refeição | D9: Encargos funcionários - alimentação | E9: PIX | F9: Conta corrente - Bradesco | G9: Guincho Praia Grande/SP - Pregão 166 2020 | H9: 30/07/2021 | I9: ------ | J9: Confirmado | K9: 241,72 | L9: 0,00 | M9: 0,00 | N9: 0,00 | O9: 0,00 | P9: 241,72
A10: 769 | B10: Sergio Ricardo Pereira da Silva | C10: Holerite - Sergio | D10: Encargo Funcionários - Holerite Mensal | E10: PIX | F10: Conta corrente - Bradesco | G10: Guincho Praia Grande/SP - Pregão 166 2020 | H10: 06/08/2021 | I10: ------ | J10: Confirmado | K10: 2.263,03 | L10: 968,08 | M10: 0,00 | N10: 0,00 | O10: 0,00 | P10: 1.294,95
A11: 786 | B11: Sergio Ricardo Pereira da Silva | C11: Adiantamento Holerite | D11: Adiantamento - funcionários | E11: PIX | F11: Conta corrente - Bradesco | G11: Guincho Praia Grande/SP - Pregão 166 2020 | H11: 20/08/2021 | I11: ------ | J11: Confirmado | K11: 779,13 | L11: 12,76 | M11: 0,00 | N11: 0,00 | O11: 0,00 | P11: 766,37
A12: 776 | B12: Sergio Ricardo Pereira da Silva | C12: Vale Refeição | D12: Encargos funcionários - alimentação | E12: PIX | F12: Conta corrente - Bradesco | G12: Guincho Praia Grande/SP - Pregão 166 2020 | H12: 31/08/2021 | I12: ------ | J12: Confirmado | K12: 241,72 | L12: 0,00 | M12: 0,00 | N12: 0,00 | O12: 0,00 | P12: 241,72
A13: 770 | B13: Sergio Ricardo Pereira da Silva | C13: Holerite - Sergio | D13: Encargo Funcionários - Holerite Mensal | E13: PIX | F13: Conta corrente - Bradesco | G13: Guincho Praia Grande/SP - Pregão 166 2020 | H13: 06/09/2021 | I13: ------ | J13: Confirmado | K13: 1.947,82 | L13: 937,93 | M13: 0,00 | N13: 0,00 | O13: 0,00 | P13: 1.009,89
... A26: 1597 | B26: Sergio Ricardo Pereira da Silva | C26: 2ª parc. - Decimo terceiro - Sergio R | D26: Encargos funcionários - 13o salário | E26: PIX | F26: Conta corrente - Bradesco | G26: Guincho Praia Grande/SP - Pregão 166 2020 | H26: 20/12/2021 | I26: ------ | J26: Confirmado | K26: 1.136,23 | L26: 653,87 | M26: 0,00 | N26: 0,00 | O26: 0,00 | P26: 482,36
A27: TOTAIS
A28: Quantidade: | L28: 24
A29: Pagamentos atrasados: | L29: 0,00
A30: Pagamentos para hoje: | L30: 0,00
A31: Pagamentos futuros: | L31: 0,00
A32: Valor total à pagar: | L32: 0,00
A33: Valor total pago: | L33: 16.414,76
A34: Descontos: | L34: 7.845,53
A35: Juros: | L35: 0,00
A36: Taxas do banco: | L36: 0,00
A37: Taxas da operadora: | L37: 0,00
A38: Valor total: | L38: 16.414,76

Sheet Thiago
B1: Relatório de contas a pagar Período: 01/01/2021 à 31/12/2021 Gerado em 21/01/2022 às 10:40:55
A2: Código | B2: Destinado à | C2: Descrição | D2: Plano de contas | E2: Forma de pagamento | F2: Conta bancária | G2: Centro de custo | H2: Data | I2: NF-e | J2: Situação | K2: Valor | L2: Desconto | M2: Juros | N2: Taxa do banco | O2: Taxa da operadora | P2: Valor total
A3: 74 | B3: Thiago Alves Do Sacramento | C3: Vale Refeição | D3: Encargos funcionários - alimentação | E3: PIX | F3: Investimentos Dauren | G3: Guincho Praia Grande/SP - Pregão 166 2020 | H3: 17/03/2021 | I3: ------ | J3: Confirmado | K3: 241,72 | L3: 0,00 | M3: 0,00 | N3: 0,00 | O3: 0,00 | P3: 241,72
A4: 92 | B4: Thiago Alves Do Sacramento | C4: Vale Refeição | D4: Encargos funcionários - alimentação | E4: PIX | F4: Investimentos Dauren | G4: Guincho Praia Grande/SP - Pregão 166 2020 | H4: 31/03/2021 | I4: ------ | J4: Confirmado | K4: 241,72 | L4: 0,00 | M4: 0,00 | N4: 0,00 | O4: 0,00 | P4: 241,72
A5: 102 | B5: Thiago Alves Do Sacramento | C5: Vale Refeição | D5: Encargos funcionários - alimentação | E5: PIX | F5: Conta corrente - Bradesco | G5: Guincho Praia Grande/SP - Pregão 166 2020 | H5: 30/04/2021 | I5: ------ | J5: Confirmado | K5: 241,72 | L5: 0,00 | M5: 0,00 | N5: 0,00 | O5: 0,00 | P5: 241,72
A6: 103 | B6: Thiago Alves Do Sacramento | C6: Vale Refeição | D6: Encargos funcionários - alimentação | E6: PIX | F6: Conta corrente - Bradesco | G6: Guincho Praia Grande/SP - Pregão 166 2020 | H6: 31/05/2021 | I6: ------ | J6: Confirmado | K6: 241,72 | L6: 0,00 | M6: 0,00 | N6: 0,00 | O6: 0,00 | P6: 241,72
A7: 104 | B7: Thiago Alves Do Sacramento | C7: Vale Refeição | D7: Encargos funcionários - alimentação | E7: PIX | F7: Conta corrente - Bradesco | G7: Guincho Praia Grande/SP - Pregão 166 2020 | H7: 30/06/2021 | I7: ------ | J7: Confirmado | K7: 241,72 | L7: 0,00 | M7: 0,00 | N7: 0,00 | O7: 0,00 | P7: 241,72
A8: 105 | B8: Thiago Alves Do Sacramento | C8: Vale Refeição | D8: Encargos funcionários - alimentação | E8: PIX | F8: Conta corrente - Bradesco | G8: Guincho Praia Grande/SP - Pregão 166 2020 | H8: 30/07/2021 | I8: ------ | J8: Confirmado | K8: 241,72 | L8: 0,00 | M8: 0,00 | N8: 0,00 | O8: 0,00 | P8: 241,72
A9: 106 | B9: Thiago Alves Do Sacramento | C9: Vale Refeição | D9: Encargos funcionários - alimentação | E9: PIX | F9: Conta corrente - Bradesco | G9: Guincho Praia Grande/SP - Pregão 166 2020 | H9: 31/08/2021 | I9: ------ | J9: Confirmado | K9: 241,72 | L9: 0,00 | M9: 0,00 | N9: 0,00 | O9: 0,00 | P9: 241,72
A10: 107 | B10: Thiago Alves Do Sacramento | C10: Vale Refeição | D10: Encargos funcionários - alimentação | E10: PIX | F10: Conta corrente - Bradesco | G10: Guincho Praia Grande/SP - Pregão 166 2020 | H10: 30/09/2021 | I10: ------ | J10: Confirmado | K10: 241,72 | L10: 0,00 | M10: 0,00 | N10: 0,00 | O10: 0,00 | P10: 241,72
A11: 108 | B11: Thiago Alves Do Sacramento | C11: Vale Refeição | D11: Encargos funcionários - alimentação | E11: PIX | F11: Conta corrente - Bradesco | G11: Guincho Praia Grande/SP - Pregão 166 2020 | H11: 29/10/2021 | I11: ------ | J11: Confirmado | K11: 241,72 | L11: 0,00 | M11: 0,00 | N11: 0,00 | O11: 0,00 | P11: 241,72
A12: 109 | B12: Thiago Alves Do Sacramento | C12: Vale Refeição | D12: Encargos funcionários - alimentação | E12: PIX | F12: Conta corrente - Bradesco | G12: Guincho Praia Grande/SP - Pregão 166 2020 | H12: 30/11/2021 | I12: ------ | J12: Confirmado | K12: 241,72 | L12: 0,00 | M12: 0,00 | N12: 0,00 | O12: 0,00 | P12: 241,72
A13: 1473 | B13: Thiago Alves Do Sacramento | C13: Decimo Terceiro - Thiago | D13: Encargos funcionários - 13o salário | E13: PIX | F13: Conta corrente - Bradesco | G13: Guincho Praia Grande/SP - Pregão 166 2020 | H13: 30/11/2021 | I13: ------ | J13: Confirmado | K13: 811,59 | L13: 0,00 | M13: 0,00 | N13: 0,00 | O13: 0,00 | P13: 811,59
... A34: 179 | B34: Thiago Alves Do Sacramento | C34: Adiantamento Holerite - Thiago | D34: Adiantamento - funcionários | E34: PIX | F34: Conta corrente - Bradesco | G34: Guincho Praia Grande/SP - Pregão 166 2020 | H34: 20/12/2021 | I34: ------ | J34: Confirmado | K34: 779,13 | L34: 0,00 | M34: 0,00 | N34: 0,00 | O34: 0,00 | P34: 779,13
A36: TOTAIS
A37: Quantidade: | L37: 32
A38: Pagamentos atrasados: | L38: 0,00
A39: Pagamentos para hoje: | L39: 0,00
A40: Pagamentos futuros: | L40: 0,00
A41: Valor total à pagar: | L41: 0,00
A42: Valor total pago: | L42: 22.976,60
A43: Descontos: | L43: 9.852,84
A44: Juros: | L44: 0,00
A45: Taxas do banco: | L45: 0,00
A46: Taxas da operadora: | L46: 0,00
A47: Valor total: | L47: 22.976,60

Sheet Vinicius
B1: Relatório de contas a pagar Período: 21/01/2021 à 31/12/2021 Gerado em 21/01/2022 às 10:52:13
A2: Código | B2: Destinado à | C2: Descrição | D2: Plano de contas | E2: Forma de pagamento | F2: Conta bancária | G2: Centro de custo | H2: Data | I2: NF-e | J2: Situação | K2: Valor | L2: Desconto | M2: Juros | N2: Taxa do banco | O2: Taxa da operadora | P2: Valor total
A3: 1352 | B3: Vinicius Sozio Cornes | C3: Diárias - Pré-contratação | D3: Remuneração funcionários | E3: Cartão de Crédito | F3: Banco Prudentte | G3: CONECTIUS | H3: 19/10/2021 | I3: ------ | J3: Confirmado | K3: 360,00 | L3: 0,00 | M3: 0,00 | N3: 0,00 | O3: 0,00 | P3: 360,00
A4: 1326 | B4: Vinicius Sozio Cornes | C4: Adiantamento Holerite | D4: Adiantamento - funcionários | E4: PIX | F4: Conta corrente - Bradesco | G4: Guincho Praia Grande/SP - Pregão 166 2020 | H4: 20/10/2021 | I4: ------ | J4: Confirmado | K4: 597,33 | L4: 0,00 | M4: 0,00 | N4: 0,00 | O4: 0,00 | P4: 597,33
A5: 1397 | B5: Vinicius Sozio Cornes | C5: Vale Refeição | D5: Encargos funcionários - alimentação | E5: PIX | F5: Conta corrente - Bradesco | G5: Guincho Praia Grande/SP - Pregão 166 2020 | H5: 29/10/2021 | I5: ------ | J5: Confirmado | K5: 241,72 | L5: 0,00 | M5: 0,00 | N5: 0,00 | O5: 0,00 | P5: 241,72
A6: 1367 | B6: Vinicius Sozio Cornes | C6: Holerite | D6: Encargo Funcionários - Holerite Mensal | E6: PIX | F6: Conta corrente - Bradesco | G6: Guincho Praia Grande/SP - Pregão 166 2020 | H6: 04/11/2021 | I6: ------ | J6: Confirmado | K6: 2.453,30 | L6: 809,11 | M6: 0,00 | N6: 0,00 | O6: 0,00 | P6: 1.644,19
A7: 1374 | B7: Vinicius Sozio Cornes | C7: Adiantamento Holerite | D7: Adiantamento - funcionários | E7: PIX | F7: Conta corrente - Bradesco | G7: Guincho Praia Grande/SP - Pregão 166 2020 | H7: 18/11/2021 | I7: ------ | J7: Confirmado | K7: 779,13 | L7: 0,00 | M7: 0,00 | N7: 0,00 | O7: 0,00 | P7: 779,13
A8: 1482 | B8: Vinicius Sozio Cornes | C8: Decimo terceiro - Vinicius | D8: Encargos funcionários - 13o salário | E8: PIX | F8: Conta corrente - Bradesco | G8: Guincho Praia Grande/SP - Pregão 166 2020 | H8: 30/11/2021 | I8: ------ | J8: Confirmado | K8: 243,48 | L8: 0,00 | M8: 0,00 | N8: 0,00 | O8: 0,00 | P8: 243,48
A9: 1491 | B9: Vinicius Sozio Cornes | C9: Vale Refeição | D9: Encargos funcionários - alimentação | E9: PIX | F9: Conta corrente - Bradesco | G9: Guincho Praia Grande/SP - Pregão 166 2020 | H9: 30/11/2021 | I9: ------ | J9: Confirmado | K9: 241,72 | L9: 0,00 | M9: 0,00 | N9: 0,00 | O9: 0,00 | P9: 241,72
A10: 1531 | B10: Vinicius Sozio Cornes | C10: Holerite - Vinicius | D10: Encargo Funcionários - Holerite Mensal | E10: PIX | F10: Conta corrente - Bradesco | G10: Guincho Praia Grande/SP - Pregão 166 2020 | H10: 06/12/2021 | I10: ------ | J10: Confirmado | K10: 1.947,82 | L10: 937,93 | M10: 0,00 | N10: 0,00 | O10: 0,00 | P10: 1.009,89
A11: 198 | B11: Vinicius Sozio Cornes | C11: Adiantamento Holerite - Vinicius | D11: Adiantamento - funcionários | E11: PIX | F11: Conta corrente - Bradesco | G11: Guincho Praia Grande/SP - Pregão 166 2020 | H11: 20/12/2021 | I11: ------ | J11: Confirmado | K11: 779,13 | L11: 0,00 | M11: 0,00 | N11: 0,00 | O11: 0,00 | P11: 779,13
A12: 1599 | B12: Vinicius Sozio Cornes | C12: 2ª parc. - Decimo terceiro - Vinicius | D12: Encargos funcionários - 13o salário | E12: PIX | F12: Conta corrente - Bradesco | G12: Guincho Praia Grande/SP - Pregão 166 2020 | H12: 20/12/2021 | I12: ------ | J12: Confirmado | K12: 486,96 | L12: 280,00 | M12: 0,00 | N12: 0,00 | O12: 0,00 | P12: 206,96
A13: 1681 | B13: Vinicius Sozio Cornes | C13: Vale Refeição | D13: Encargos funcionários - alimentação | E13: PIX | F13: Conta corrente - Bradesco | G13: Guincho Praia Grande/SP - Pregão 166 2020 | H13: 22/12/2021 | I13: ------ | J13: Confirmado | K13: 241,72 | L13: 0,00 | M13: 0,00 | N13: 0,00 | O13: 0,00 | P13: 241,72
A14: TOTAIS
A15: Quantidade: | L15: 11
A16: Pagamentos atrasados: | L16: 0,00
A17: Pagamentos para hoje: | L17: 0,00
A18: Pagamentos futuros: | L18: 0,00
A19: Valor total à pagar: | L19: 0,00
A20: Valor total pago: | L20: 6.345,27
A21: Descontos: | L21: 2.027,04
A22: Juros: | L22: 0,00
A23: Taxas do banco: | L23: 0,00
A24: Taxas da operadora: | L24: 0,00
A25: Valor total: | L25: 6.345,27

Sheet Raphael
B1: Relatório de contas a pagar Período: 21/01/2021 à 31/12/2021 Gerado em 21/01/2022 às 10:57:00
A2: Código | B2: Destinado à | C2: Descrição | D2: Plano de contas | E2: Forma de pagamento | F2: Conta bancária | G2: Centro de custo | H2: Data | I2: NF-e | J2: Situação | K2: Valor | L2: Desconto | M2: Juros | N2: Taxa do banco | O2: Taxa da operadora | P2: Valor total
A3: 77 | B3: Raphael Silva Dos Anjos | C3: Vale Refeição | D3: Encargos funcionários - alimentação | E3: PIX | F3: Investimentos Dauren | G3: Guincho Praia Grande/SP - Pregão 166 2020 | H3: 17/03/2021 | I3: ------ | J3: Confirmado | K3: 241,72 | L3: 0,00 | M3: 0,00 | N3: 0,00 | O3: 0,00 | P3: 241,72
A4: 86 | B4: Raphael Silva Dos Anjos | C4: Adiantamento Holerite | D4: Adiantamento - funcionários | E4: PIX | F4: Investimentos Dauren | G4: Guincho Praia Grande/SP - Pregão 166 2020 | H4: 19/03/2021 | I4: ------ | J4: Confirmado | K4: 675,24 | L4: 0,00 | M4: 0,00 | N4: 0,00 | O4: 0,00 | P4: 675,24
A5: 430 | B5: Raphael Silva Dos Anjos | C5: Reembolso Vale Transporte | D5: Encargos funcionários - vale transporte | E5: PIX | F5: Investimentos Dauren | G5: Guincho Praia Grande/SP - Pregão 166 2020 | H5: 29/03/2021 | I5: ------ | J5: Confirmado | K5: 6,10 | L5: 0,00 | M5: 0,00 | N5: 0,00 | O5: 0,00 | P5: 6,10
A6: 131 | B6: Raphael Silva Dos Anjos | C6: Vale Refeição | D6: Encargos funcionários - alimentação | E6: PIX | F6: Investimentos Dauren | G6: Guincho Praia Grande/SP - Pregão 166 2020 | H6: 31/03/2021 | I6: ------ | J6: Confirmado | K6: 241,72 | L6: 0,00 | M6: 0,00 | N6: 0,00 | O6: 0,00 | P6: 241,72
A7: 40 | B7: Raphael Silva Dos Anjos | C7: Holerite | D7: Encargo Funcionários - Holerite Mensal | E7: PIX | F7: Investimentos Dauren | G7: Guincho Praia Grande/SP - Pregão 166 2020 | H7: 07/04/2021 | I7: ------ | J7: Confirmado | K7: 1.951,79 | L7: 899,33 | M7: 0,00 | N7: 0,00 | O7: 0,00 | P7: 1.052,46
A8: 199 | B8: Raphael Silva Dos Anjos | C8: Adiantamento Holerite | D8: Adiantamento - funcionários | E8: PIX | F8: Investimentos Dauren | G8: Guincho Praia Grande/SP - Pregão 166 2020 | H8: 20/04/2021 | I8: ------ | J8: Confirmado | K8: 779,13 | L8: 0,00 | M8: 0,00 | N8: 0,00 | O8: 0,00 | P8: 779,13
A9: 132 | B9: Raphael Silva Dos Anjos | C9: Vale Refeição | D9: Encargos funcionários - alimentação | E9: PIX | F9: Conta corrente - Bradesco | G9: Guincho Praia Grande/SP - Pregão 166 2020 | H9: 30/04/2021 | I9: ------ | J9: Confirmado | K9: 241,72 | L9: 0,00 | M9: 0,00 | N9: 0,00 | O9: 0,00 | P9: 241,72
A10: 264 | B10: Raphael Silva Dos Anjos | C10: Holerite - Raphael | D10: Encargo Funcionários - Holerite Mensal | E10: PIX | F10: Conta corrente - Bradesco | G10: Guincho Praia Grande/SP - Pregão 166 2020 | H10: 06/05/2021 | I10: ------ | J10: Confirmado | K10: 2.141,19 | L10: 955,33 | M10: 0,00 | N10: 0,00 | O10: 0,00 | P10: 1.185,86
A11: 200 | B11: Raphael Silva Dos Anjos | C11: Adiantamento Holerite | D11: Adiantamento - funcionários | E11: PIX | F11: Conta corrente - Bradesco | G11: Guincho Praia Grande/SP - Pregão 166 2020 | H11: 20/05/2021 | I11: ------ | J11: Confirmado | K11: 779,13 | L11: 0,00 | M11: 0,00 | N11: 0,00 | O11: 0,00 | P11: 779,13
A12: 133 | B12: Raphael Silva Dos Anjos | C12: Vale Refeição | D12: Encargos funcionários - alimentação | E12: PIX | F12: Conta corrente - Bradesco | G12: Guincho Praia Grande/SP - Pregão 166 2020 | H12: 31/05/2021 | I12: ------ | J12: Confirmado | K12: 241,72 | L12: 0,00 | M12: 0,00 | N12: 0,00 | O12: 0,00 | P12: 241,72
A13: 265 | B13: Raphael Silva Dos Anjos | C13: Holerite | D13: Encargo Funcionários - Holerite Mensal | E13: PIX | F13: Conta corrente - Bradesco | G13: Guincho Praia Grande/SP - Pregão 166 2020 | H13: 07/06/2021 | I13: ------ | J13: Confirmado | K13: 1.947,82 | L13: 937,93 | M13: 0,00 | N13: 0,00 | O13: 0,00 | P13: 1.009,89
... A35: 140 | B35: Raphael Silva Dos Anjos | C35: Vale Refeição | D35: Encargos funcionários - alimentação | E35: PIX | F35: Conta corrente - Bradesco | G35: Guincho Praia Grande/SP - Pregão 166 2020 | H35: 22/12/2021 | I35: ------ | J35: Confirmado | K35: 241,72 | L35: 0,00 | M35: 0,00 | N35: 0,00 | O35: 0,00 | P35: 241,72
A36: TOTAIS
A37: Quantidade: | L37: 33
A38: Pagamentos atrasados: | L38: 0,00
A39: Pagamentos para hoje: | L39: 0,00
A40: Pagamentos futuros: | L40: 0,00
A41: Valor total à pagar: | L41: 0,00
A42: Valor total pago: | L42: 25.403,10
A43: Descontos: | L43: 10.227,42
A44: Juros: | L44: 0,00
A45: Taxas do banco: | L45: 0,00
A46: Taxas da operadora: | L46: 0,00
A47: Valor total: | L47: 25.403,10

Sheet William
B1: Relatório de contas a pagar Período: 01/01/2021 à 31/12/2021 Gerado em 21/01/2022 às 11:27:45
A2: Código | B2: Destinado à | C2: Descrição | D2: Plano de contas | E2: Forma de pagamento | F2: Conta bancária | G2: Centro de custo | H2: Data | I2: NF-e | J2: Situação | K2: Valor | L2: Desconto | M2: Juros | N2: Taxa do banco | O2: Taxa da operadora | P2: Valor total
A3: 1247 | B3: William Donizeti Stein Loro | C3: Despesas - Diárias GL5 Pré-contratação | D3: Remuneração funcionários | E3: Cartão de Crédito | F3: Banco Prudentte | G3: Guincho Praia Grande/SP - Pregão 166 2020 | H3: 16/09/2021 | I3: ------ | J3: Confirmado | K3: 360,00 | L3: 0,00 | M3: 0,00 | N3: 0,00 | O3: 0,00 | P3: 360,00
A4: 1259 | B4: William Donizeti Stein Loro | C4: Vale Refeição | D4: Encargos funcionários - alimentação | E4: PIX | F4: Conta corrente - Bradesco | G4: Guincho Praia Grande/SP - Pregão 166 2020 | H4: 30/09/2021 | I4: ------ | J4: Confirmado | K4: 241,72 | L4: 0,00 | M4: 0,00 | N4: 0,00 | O4: 0,00 | P4: 241,72
A5: 261 | B5: William Donizeti Stein Loro | C5: Holerite | D5: Encargo Funcionários - Holerite Mensal | E5: PIX | F5: Conta corrente - Bradesco | G5: Guincho Praia Grande/SP - Pregão 166 2020 | H5: 05/10/2021 | I5: ------ | J5: Confirmado | K5: 908,98 | L5: 68,17 | M5: 0,00 | N5: 0,00 | O5: 0,00 | P5: 840,81
A6: 1327 | B6: William Donizeti Stein Loro | C6: Adiantamento Holerite | D6: Adiantamento - funcionários | E6: PIX | F6: Conta corrente - Bradesco | G6: Guincho Praia Grande/SP - Pregão 166 2020 | H6: 20/10/2021 | I6: ------ | J6: Confirmado | K6: 779,13 | L6: 0,00 | M6: 0,00 | N6: 0,00 | O6: 0,00 | P6: 779,13
A7: 128 | B7: William Donizeti Stein Loro | C7: Vale Refeição | D7: Encargos funcionários - alimentação | E7: PIX | F7: Conta corrente - Bradesco | G7: Guincho Praia Grande/SP - Pregão 166 2020 | H7: 29/10/2021 | I7: ------ | J7: Confirmado | K7: 241,72 | L7: 0,00 | M7: 0,00 | N7: 0,00 | O7: 0,00 | P7: 241,72
A8: 1361 | B8: William Donizeti Stein Loro | C8: Holerite | D8: Encargo Funcionários - Holerite Mensal | E8: PIX | F8: Conta corrente - Bradesco | G8: Guincho Praia Grande/SP - Pregão 166 2020 | H8: 04/11/2021 | I8: ------ | J8: Confirmado | K8: 2.812,72 | L8: 1.034,04 | M8: 0,00 | N8: 0,00 | O8: 0,00 | P8: 1.778,68
A9: 197 | B9: William Donizeti Stein Loro | C9: Adiantamento Holerite | D9: Adiantamento - funcionários | E9: PIX | F9: Conta corrente - Bradesco | G9: Guincho Praia Grande/SP - Pregão 166 2020 | H9: 18/11/2021 | I9: ------ | J9: Confirmado | K9: 779,13 | L9: 49,04 | M9: 0,00 | N9: 0,00 | O9: 0,00 | P9: 730,09
A10: 1483 | B10: William Donizeti Stein Loro | C10: Decimo terceiro - Wiliam | D10: Encargos funcionários - 13o salário | E10: PIX | F10: Conta corrente - Bradesco | G10: Guincho Praia Grande/SP - Pregão 166 2020 | H10: 30/11/2021 | I10: ------ | J10: Confirmado | K10: 243,48 | L10: 0,00 | M10: 0,00 | N10: 0,00 | O10: 0,00 | P10: 243,48
A11: 1492 | B11: William Donizeti Stein Loro | C11: Vale Refeição | D11: Encargos funcionários - alimentação | E11: PIX | F11: Conta corrente - Bradesco | G11: Guincho Praia Grande/SP - Pregão 166 2020 | H11: 30/11/2021 | I11: ------ | J11: Confirmado | K11: 241,72 | L11: 0,00 | M11: 0,00 | N11: 0,00 | O11: 0,00 | P11: 241,72
A12: 1532 | B12: William Donizeti Stein Loro | C12: Holerite - Wiliam | D12: Encargo Funcionários - Holerite Mensal | E12: PIX | F12: Conta corrente - Bradesco | G12: Guincho Praia Grande/SP - Pregão 166 2020 | H12: 06/12/2021 | I12: ------ | J12: Confirmado | K12: 2.180,23 | L12: 958,85 | M12: 0,00 | N12: 0,00 | O12: 0,00 | P12: 1.221,38
A13: 1601 | B13: William Donizeti Stein Loro | C13: 2ª parc. - Decimo terceiro - Wiliam | D13: Encargos funcionários - 13o salário | E13: PIX | F13: Conta corrente - Bradesco | G13: Guincho Praia Grande/SP - Pregão 166 2020 | H13: 20/12/2021 | I13: ------ | J13: Confirmado | K13: 486,96 | L13: 280,00 | M13: 0,00 | N13: 0,00 | O13: 0,00 | P13: 206,96
... A15: 1678 | B15: William Donizeti Stein Loro | C15: Vale Refeição | D15: Encargos funcionários - alimentação | E15: PIX | F15: Conta corrente - Bradesco | G15: Guincho Praia Grande/SP - Pregão 166 2020 | H15: 22/12/2021 | I15: ------ | J15: Confirmado | K15: 241,72 | L15: 0,00 | M15: 0,00 | N15: 0,00 | O15: 0,00 | P15: 241,72
A16: TOTAIS
A17: Quantidade: | L17: 13
A18: Pagamentos atrasados: | L18: 0,00
A19: Pagamentos para hoje: | L19: 0,00
A20: Pagamentos futuros: | L20: 0,00
A21: Valor total à pagar: | L21: 0,00
A22: Valor total pago: | L22: 7.906,54
A23: Descontos: | L23: 2.390,10
A24: Juros: | L24: 0,00
A25: Taxas do banco: | L25: 0,00
A26: Taxas da operadora: | L26: 0,00
A27: Valor total: | L27: 7.906,54
